Workbook
Name DossierPDF: IF(LEFT(CELL("filename",Références!$A$1),9)="C:\Users\",LEFT(CELL("filename",Références!$A$1),FIND("\",CELL("filename",Références!$A$1),10))&"OneDrive - entpe.fr\bibliographie\","")

Sheet Lisez-moi
B2: Bibliographie de thèse — Lucas DAVID
B3: Distribution hétérogène de la pression de contact pneu-chaussée propagée dans un calcul EF viscoélastique — chaussées aéronautiques (ENTPE, LTDS, partenariat STAC). Vérification sur sources primaires du 22/09/2026.
B5: En chiffres (calculé)
B6: Références | C6: ='Tableau de bord'!C6&" références, dont "&'Tableau de bord'!C7&" issues de la bibliographie du TFE" -> 179 références, dont 39 issues de la bibliographie du TFE
B7: Vérification | C7: ='Tableau de bord'!C8&" vérifiées sur source primaire, "&'Tableau de bord'!C9&" partiellement, "&'Tableau de bord'!C10&" non vérifiée(s) ; "&'Tableau de bord'!C11&" DOI, tous résolus" -> 140 vérifiées sur source primaire, 38 partiellement, 1 non vérifiée(s) ; 106 DOI, tous résolus
B8: Accès | C8: ='Tableau de bord'!C12&" téléchargeables tout de suite, "&'Tableau de bord'!C13&" via l'abonnement ENTPE, "&'Tableau de bord'!C14&" payantes, "&'Tableau de bord'!C15&" à demander ou localiser" -> 56 téléchargeables tout de suite, 80 via l'abonnement ENTPE, 28 payantes, 15 à demander ou localiser
B9: Où tu en es | C9: ='Tableau de bord'!C27&" : "&'Tableau de bord'!C17&" lues, "&'Tableau de bord'!C20&" en retard. Prochaine action : "&'Tableau de bord'!C32 -> 1 — octobre 2026 : 0 lues, 0 en retard. Prochaine action : Envoyer ou relancer 3 demande(s) : feuille Demandes
B10: Fiches de lecture | C10: =COUNTIF('Lecture détaillée'!$J$5:$J$204,"Complet")&" d'après un résumé complet, "&COUNTIF('Lecture détaillée'!$J$5:$J$204,"Partiel")&" d'après un texte partiel, "&COUNTIF('Lecture détaillée'!$J$5:$J$204,"Aucun")&" fiches de repérage (pas de résumé en ligne)" -> 70 d'après un résumé complet, 18 d'après un texte partiel, 91 fiches de repérage (pas de résumé en ligne)
B12: Nouveau : lecture détaillée et analyse croisée
B13: • Lecture détaillée : une fiche par référence (objectif, méthode, résultats annoncés, limites, ce que ça t'apporte, ce qu'il faudra vérifier en lisant), avec sept dimensions (pneu, contact, loi, méthode, chargement, cible, validation). Filtre par axe, par « Texte lu » ou par mot.
B14: • Les fiches viennent des résumés publiés, pas du texte intégral : 70 résumés complets, 18 textes partiels, 34 fiches de repérage pour les documents sans résumé en ligne (normes, ouvrages, thèses anciennes, manuels, rapport confidentiel du CSIR). Rien n'y est inventé : quand le résumé ne dit rien, la fiche le dit.
B15: • Analyse croisée : répartition par axe, croisements clés, synthèses par thème, convergences, divergences, lacunes, place de ta thèse et points à vérifier dans ton TFE. Matrice croisée : le classement de chaque référence, modifiable.
B16: • En relisant les résumés, une vingtaine de notes de la base ont été corrigées (par exemple : pas de nappe Tekscan dans les résumés de Manyo et d'Oubahdou ; piste 14R/32L de Toulouse = chaussée rigide renforcée ; pneu de tourisme chez He et al. 2021). Une correction s'ajoute à la feuille Corrections TFE.
B18: Ce qui change par rapport à la version précédente (63 références)
B19: • 122 références au lieu de 63, dont les 39 de la bibliographie du TFE, toutes revérifiées une par une ; les axes 3 (viscoélasticité), 4 (module complexe), 5 (calcul de structures) et 6 (endommagement) sont maintenant couverts.
B20: • Jiang et al. (2019) : le DOI cité dans le TFE ne mène nulle part ; le bon DOI est 10.1080/10298436.2017.1380803.
B21: • Rapport HTPT d'Airbus : il est public (site d'Airbus) ; sa Figure 26 montre des pressions calculées, pas mesurées (légende de ta Figure 1-23 à corriger).
B22: • Normes : NF EN 1427 citée dans l'édition de janvier 2018, annulée en juin 2026 ; module complexe = NF EN 12697-26+A1 (2023) ; NF EN 1426, citée dans ton texte, est ajoutée.
B23: • OACI : Annexe 14 vol. I, 9e édition (2022) ; Doc 9157 partie 3, 3e édition (2022). Transition ACN-PCN vers ACR-PCR : adoptée en juillet 2020, applicable au 28/11/2024.
B24: • Les deux pistes de ta soutenance ont leurs références : domaine fréquentiel (VEROAD, Siddharthan, ViscoRoute, éléments spectraux) et superposition semi-analytique (Boussinesq, Love, Johnson, DC-FFT, code de Jacq, Manyo, Cardoso da Silva).
... B27: Les feuilles
B28: Tableau de bord | C28: Vue d'ensemble, avancement par axe et par mois, charge de lecture du mois, prochaines lectures conseillées, graphiques. Rien à saisir.
B29: Références | C29: La base : une ligne par référence. Colonnes jaunes à remplir (statut, date, PDF, Zotero, note, pertinence, commentaire). Colonne Ouvrir = lien le plus direct (PDF libre, sinon page éditeur par le DOI, sinon notice, sinon recherche). Groupes de colonnes repliables avec les boutons + / − au-dessus des en-têtes.
B30: Lecture détaillée | C30: Une fiche de lecture par référence, d'après son résumé, liée par l'ID ; colonne « Texte lu » : Complet, Partiel ou Aucun.
B31: Analyse croisée | C31: Répartition par axe et par catégorie (calculée), croisements clés, synthèses par thème, convergences, divergences, lacunes, place de ta thèse, points à vérifier dans le TFE.
B32: Matrice croisée | C32: Le classement de chaque référence (● par catégorie) ; les totaux et l'Analyse croisée en dépendent. Modifiable.
B33: Planning | C33: Six mois, octobre 2026 → mars 2027 : objectif de fin de mois, documents à demander en amont, liste des lectures tirée de Références.
B34: Demandes | C34: PEB, documentation ENTPE, STAC : date limite d'envoi calculée d'après le délai, relance automatique à +21 jours (réglable).
B35: Corrections TFE | C35: Les écarts constatés entre ta bibliographie de TFE et les sources primaires, avec la correction et sa source.
B36: Pistes non couvertes | C36: Sujets cherchés sans source vérifiable. Rien n'y est inventé.
B37: Notes de lecture | C37: Une ligne par référence, liée par l'ID (le tri de Références ne casse rien).
B38: Paramètres | C38: Date de début, capacité mensuelle, barème du score, temps de lecture par priorité, dossiers utilisés par les macros, listes de choix.
B40: Couleurs
B41: Fond jaune | C41: Cellule à remplir ou réglage modifiable.
B42: Fond gris | C42: Cellule calculée : ne pas écrire dedans.
B43: Rouge / orange / vert | C43: En retard, non vérifié ou à demander / ce mois-ci, partiel ou payant / lu, vérifié ou PDF libre.
B45: Exemple de ligne de notes remplie
B46: ID | C46: BIB-0xx (Tiouajni et al. 2011)
B47: Apport central (reformulé) | C47: Approche un modèle à spectre continu (2S2P1D) par un Kelvin-Voigt généralisé de taille finie, en 3D, en ajustant les modules sur une grille de temps de retard.
B48: Lien avec mes travaux | C48: Méthode suivie pour mes 9 branches (§2.7) ; vérifier la plage de fréquences et le nombre de branches retenus.
B49: Équations, valeurs, figures | C49: Relation d'identification des modules ; tableau des paramètres ; figure de comparaison des isothermes.
B50: Chapitre visé / À citer | C50: Chapitre 2 / Oui
B52: Travailler sur trois appareils (PC travail, PC perso, iPad)
B53: Zotero | C53: Importer le RIS une seule fois (Fichier > Importer…), sur un seul poste : les métadonnées se synchronisent ensuite gratuitement et sans limite via ton compte Zotero.
B54: PDF | C54: Pour que les PDF suivent sur les trois appareils, il faut des fichiers « stockés » (pas liés) et une synchronisation des fichiers : stockage Zotero (payant au-delà de 300 Mo) ou WebDAV gratuit (Koofr, 10 Go ; ou un Nextcloud de l'école s'il existe). Zotero pour iPad accepte le WebDAV.
B55: Après l'import | C55: Tout sélectionner > clic droit > « Trouver un PDF disponible » : Zotero récupère seul les PDF en accès libre. Pour les autres, la colonne Ouvrir de l'Excel mène à l'éditeur (accès ENTPE), à la boutique ou à la notice.
B56: Mots-clés Zotero | C56: « Axe n - … », « Priorite: … », « Acces: Libre / Payant / Restreint / A verifier », « Mois: n », « TFE », « NON VERIFIE », « cle:… » (clé commune à Zotero, à l'Excel et aux notes Obsidian).
B57: Excel | C57: Garder ce classeur dans ton OneDrive ENTPE pour l'ouvrir partout. Sur iPad, toutes les formules, listes, couleurs et liens fonctionnent ; seules les macros sont réservées aux PC Windows.
B58: Obsidian | C58: Le zip notes_obsidian_references.zip contient une note par référence (nommée par sa clé) et le séquençage : à décompresser dans ton vault, synchronisé par Git comme aujourd'hui.
B60: Installer les macros (PC Windows)
B61: 1. Ouvrir ce classeur dans Excel pour Windows, puis Alt+F11 (éditeur VBA).
B62: 2. Fichier > Importer un fichier… > choisir BiblioThese.bas.
B63: 3. Fermer l'éditeur, puis Fichier > Enregistrer sous > « Classeur Excel (prenant en charge les macros) (*.xlsm) ».
B64: 4. Régler les dossiers dans Paramètres (C11, C12) ; lancer une macro avec Alt+F8, ou l'épingler dans la barre d'outils Accès rapide.
B66: Les macros
B67: OuvrirLien | C67: Ouvre le lien de chaque ligne sélectionnée (avec le proxy de Paramètres C13 pour les liens éditeur).
B68: OuvrirPDFLibresDuMois | C68: Ouvre d'un coup tous les PDF libres du mois en cours pas encore récupérés.
B69: MarquerLu / MarquerPDFRecupere | C69: Passe les lignes sélectionnées à « Lu » avec la date du jour, ou « PDF récupéré » à Oui.
B70: FiltrerMoisEnCours / AfficherTout | C70: Filtre Références sur le mois en cours non lu, puis retire les filtres.
B71: TrierParScore / TrierParID | C71: Trie Références par score décroissant (quoi lire maintenant), ou revient à l'ordre de lecture (ID).
B72: AjouterReference | C72: Crée une nouvelle ligne pré-remplie (ID suivant, statut À lire) et demande clé, titre, auteurs, année, axe, priorité, mois.
B73: VerifierDoublons | C73: Signale les clés, DOI et titres en double.
B74: VerifierLiens | C74: Teste chaque lien (code HTTP) et note le résultat dans « État du lien » : repère les liens morts.
B75: ExporterRIS | C75: Écrit un fichier RIS depuis la feuille : au choix toute la base, ou seulement les références pas encore dans Zotero (colonne « Dans Zotero »), pour importer tes ajouts sans créer de doublons.
B76: GenererNotesObsidian | C76: Crée une note Markdown par référence dans le vault, avec sa fiche de Lecture détaillée quand elle existe, sans jamais écraser une note existante.
B77: GenererPointMensuel | C77: Écrit dans le vault un point d'étape du mois (lu, restant, retards, demandes à relancer, prochaines lectures).
B78: ExporterCalendrierICS | C78: Crée un fichier .ics (début de chaque mois du plan, dates limites d'envoi, relances) à ouvrir dans ton agenda, y compris sur iPad.
... B80: MajTableauDeBord | C80: Recalcule tout et affiche un résumé.
B82: Règles de vérification suivies
B83: • Chaque métadonnée a été constatée sur une source primaire (DOI résolu par OpenAlex ou Crossref, page éditeur, notice theses.fr, TRID, AFNOR, OACI, STAC, FAA, Airbus).
B84: • Un DOI n'est inscrit que s'il a été résolu ; aucun DOI n'est reconstruit. Pour Road Materials and Pavement Design, le DOI Taylor & Francis (10.1080/…) est le pérenne ; un doublon Lavoisier (10.3166/…) peut exister pour les anciens numéros.
B85: • Statut « Partiel » ou « Non vérifié » : la note dit NON VÉRIFIÉ et précise ce qui manque. Ne pas citer ces références en l'état.
B86: • Les références sans DOI (rapports, normes, thèses, guides) sont gardées avec leur identifiant pérenne : numéro de rapport, référence de norme, ISBN, NNT, identifiant HAL ou URL officielle.

Sheet Tableau de bord
B2: Tableau de bord bibliographique
B3: Tout est calculé depuis la feuille Références : rien à saisir ici.
B4: Vue d'ensemble | F4: Avancement par axe
B5: Indicateur | C5: Valeur | F5: Axe | G5: Intitulé | H5: Total | I5: INCONTOURNABLE | J5: Lues | K5: Reste | L5: % lu | M5: Heures restantes
B6: Références au total | C6: =COUNTA(Références!$B$2:$B$201) -> 179 | F6: 1 | G6: Mesure de la pression de contact pneu-chaussée | H6: =COUNTIF(Références!$G$2:$G$201,F6) -> 16 | I6: =COUNTIFS(Références!$G$2:$G$201,F6,Références!$H$2:$H$201,"INCONTOURNABLE") -> 3 | J6: =COUNTIFS(Références!$G$2:$G$201,F6,Références!$J$2:$J$201,"Lu") -> 0 | K6: =H6-J6-COUNTIFS(Références!$G$2:$G$201,F6,Références!$J$2:$J$201,"Écarté") -> 16 | L6: =IFERROR(J6/(H6-COUNTIFS(Références!$G$2:$G$201,F6,Références!$J$2:$J$201,"Écarté")),0) -> 0 | M6: =SUMIFS(Références!$AT$2:$AT$201,Références!$G$2:$G$201,F6)-SUMIFS(Références!$AT$2:$AT$201,Références!$G$2:$G$201,F6,Références!$J$2:$J$201,"Lu")-SUMIFS(Références!$AT$2:$AT$201,Références!$G$2:$G$201,F6,Références!$J$2:$J$201,"Écarté") -> 45
B7: dont bibliographie du TFE | C7: =COUNTIF(Références!$F$2:$F$201,"Oui") -> 39 | F7: 2 | G7: Modélisation du pneu et du contact | H7: =COUNTIF(Références!$G$2:$G$201,F7) -> 36 | I7: =COUNTIFS(Références!$G$2:$G$201,F7,Références!$H$2:$H$201,"INCONTOURNABLE") -> 4 | J7: =COUNTIFS(Références!$G$2:$G$201,F7,Références!$J$2:$J$201,"Lu") -> 0 | K7: =H7-J7-COUNTIFS(Références!$G$2:$G$201,F7,Références!$J$2:$J$201,"Écarté") -> 36 | L7: =IFERROR(J7/(H7-COUNTIFS(Références!$G$2:$G$201,F7,Références!$J$2:$J$201,"Écarté")),0) -> 0 | M7: =SUMIFS(Références!$AT$2:$AT$201,Références!$G$2:$G$201,F7)-SUMIFS(Références!$AT$2:$AT$201,Références!$G$2:$G$201,F7,Références!$J$2:$J$201,"Lu")-SUMIFS(Références!$AT$2:$AT$201,Références!$G$2:$G$201,F7,Références!$J$2:$J$201,"Écarté") -> 80
B8: Vérifiées sur source primaire | C8: =COUNTIF(Références!$AL$2:$AL$201,"Vérifié") -> 140 | F8: 3 | G8: Viscoélasticité des enrobés | H8: =COUNTIF(Références!$G$2:$G$201,F8) -> 20 | I8: =COUNTIFS(Références!$G$2:$G$201,F8,Références!$H$2:$H$201,"INCONTOURNABLE") -> 3 | J8: =COUNTIFS(Références!$G$2:$G$201,F8,Références!$J$2:$J$201,"Lu") -> 0 | K8: =H8-J8-COUNTIFS(Références!$G$2:$G$201,F8,Références!$J$2:$J$201,"Écarté") -> 20 | L8: =IFERROR(J8/(H8-COUNTIFS(Références!$G$2:$G$201,F8,Références!$J$2:$J$201,"Écarté")),0) -> 0 | M8: =SUMIFS(Références!$AT$2:$AT$201,Références!$G$2:$G$201,F8)-SUMIFS(Références!$AT$2:$AT$201,Références!$G$2:$G$201,F8,Références!$J$2:$J$201,"Lu")-SUMIFS(Références!$AT$2:$AT$201,Références!$G$2:$G$201,F8,Références!$J$2:$J$201,"Écarté") -> 57
B9: Vérification partielle | C9: =COUNTIF(Références!$AL$2:$AL$201,"Partiel") -> 38 | F9: 4 | G9: Caractérisation expérimentale du module complexe | H9: =COUNTIF(Références!$G$2:$G$201,F9) -> 10 | I9: =COUNTIFS(Références!$G$2:$G$201,F9,Références!$H$2:$H$201,"INCONTOURNABLE") -> 3 | J9: =COUNTIFS(Références!$G$2:$G$201,F9,Références!$J$2:$J$201,"Lu") -> 0 | K9: =H9-J9-COUNTIFS(Références!$G$2:$G$201,F9,Références!$J$2:$J$201,"Écarté") -> 10 | L9: =IFERROR(J9/(H9-COUNTIFS(Références!$G$2:$G$201,F9,Références!$J$2:$J$201,"Écarté")),0) -> 0 | M9: =SUMIFS(Références!$AT$2:$AT$201,Références!$G$2:$G$201,F9)-SUMIFS(Références!$AT$2:$AT$201,Références!$G$2:$G$201,F9,Références!$J$2:$J$201,"Lu")-SUMIFS(Références!$AT$2:$AT$201,Références!$G$2:$G$201,F9,Références!$J$2:$J$201,"Écarté") -> 31
B10: Non vérifiées | C10: =COUNTIF(Références!$AL$2:$AL$201,"Non vérifié") -> 1 | F10: 5 | G10: Calcul de structures viscoélastiques | H10: =COUNTIF(Références!$G$2:$G$201,F10) -> 45 | I10: =COUNTIFS(Références!$G$2:$G$201,F10,Références!$H$2:$H$201,"INCONTOURNABLE") -> 6 | J10: =COUNTIFS(Références!$G$2:$G$201,F10,Références!$J$2:$J$201,"Lu") -> 0 | K10: =H10-J10-COUNTIFS(Références!$G$2:$G$201,F10,Références!$J$2:$J$201,"Écarté") -> 45 | L10: =IFERROR(J10/(H10-COUNTIFS(Références!$G$2:$G$201,F10,Références!$J$2:$J$201,"Écarté")),0) -> 0 | M10: =SUMIFS(Références!$AT$2:$AT$201,Références!$G$2:$G$201,F10)-SUMIFS(Références!$AT$2:$AT$201,Références!$G$2:$G$201,F10,Références!$J$2:$J$201,"Lu")-SUMIFS(Références!$AT$2:$AT$201,Références!$G$2:$G$201,F10,Références!$J$2:$J$201,"Écarté") -> 123
B11: Avec DOI vérifié | C11: =COUNTA(Références!$AC$2:$AC$201) -> 106 | F11: 6 | G11: Fatigue et endommagement | H11: =COUNTIF(Références!$G$2:$G$201,F11) -> 23 | I11: =COUNTIFS(Références!$G$2:$G$201,F11,Références!$H$2:$H$201,"INCONTOURNABLE") -> 4 | J11: =COUNTIFS(Références!$G$2:$G$201,F11,Références!$J$2:$J$201,"Lu") -> 0 | K11: =H11-J11-COUNTIFS(Références!$G$2:$G$201,F11,Références!$J$2:$J$201,"Écarté") -> 23 | L11: =IFERROR(J11/(H11-COUNTIFS(Références!$G$2:$G$201,F11,Références!$J$2:$J$201,"Écarté")),0) -> 0 | M11: =SUMIFS(Références!$AT$2:$AT$201,Références!$G$2:$G$201,F11)-SUMIFS(Références!$AT$2:$AT$201,Références!$G$2:$G$201,F11,Références!$J$2:$J$201,"Lu")-SUMIFS(Références!$AT$2:$AT$201,Références!$G$2:$G$201,F11,Références!$J$2:$J$201,"Écarté") -> 65
B12: Téléchargeables tout de suite (PDF libre) | C12: =COUNTIF(Références!$AJ$2:$AJ$201,"PDF libre")+COUNTIF(Références!$AJ$2:$AJ$201,"PDF libre (dépôt)") -> 56 | F12: 7 | G12: Chaussées aéronautiques | H12: =COUNTIF(Références!$G$2:$G$201,F12) -> 22 | I12: =COUNTIFS(Références!$G$2:$G$201,F12,Références!$H$2:$H$201,"INCONTOURNABLE") -> 5 | J12: =COUNTIFS(Références!$G$2:$G$201,F12,Références!$J$2:$J$201,"Lu") -> 0 | K12: =H12-J12-COUNTIFS(Références!$G$2:$G$201,F12,Références!$J$2:$J$201,"Écarté") -> 22 | L12: =IFERROR(J12/(H12-COUNTIFS(Références!$G$2:$G$201,F12,Références!$J$2:$J$201,"Écarté")),0) -> 0 | M12: =SUMIFS(Références!$AT$2:$AT$201,Références!$G$2:$G$201,F12)-SUMIFS(Références!$AT$2:$AT$201,Références!$G$2:$G$201,F12,Références!$J$2:$J$201,"Lu")-SUMIFS(Références!$AT$2:$AT$201,Références!$G$2:$G$201,F12,Références!$J$2:$J$201,"Écarté") -> 73
B13: Via l'abonnement de l'ENTPE (éditeur) | C13: =COUNTIF(Références!$AJ$2:$AJ$201,"Éditeur (abonnement)") -> 80 | F13: 8 | G13: Littérature grise et normative | H13: =COUNTIF(Références!$G$2:$G$201,F13) -> 7 | I13: =COUNTIFS(Références!$G$2:$G$201,F13,Références!$H$2:$H$201,"INCONTOURNABLE") -> 0 | J13: =COUNTIFS(Références!$G$2:$G$201,F13,Références!$J$2:$J$201,"Lu") -> 0 | K13: =H13-J13-COUNTIFS(Références!$G$2:$G$201,F13,Références!$J$2:$J$201,"Écarté") -> 7 | L13: =IFERROR(J13/(H13-COUNTIFS(Références!$G$2:$G$201,F13,Références!$J$2:$J$201,"Écarté")),0) -> 0 | M13: =SUMIFS(Références!$AT$2:$AT$201,Références!$G$2:$G$201,F13)-SUMIFS(Références!$AT$2:$AT$201,Références!$G$2:$G$201,F13,Références!$J$2:$J$201,"Lu")-SUMIFS(Références!$AT$2:$AT$201,Références!$G$2:$G$201,F13,Références!$J$2:$J$201,"Écarté") -> 11
B14: Payantes (normes, OACI, SAE, RGRA) | C14: =COUNTIF(Références!$AJ$2:$AJ$201,"Payant (boutique)") -> 28 | F14: Total | H14: =SUM(H6:H13) -> 179 | I14: =SUM(I6:I13) -> 28 | J14: =SUM(J6:J13) -> 0 | K14: =SUM(K6:K13) -> 179 | M14: =SUM(M6:M13) -> 485
B15: À demander ou à localiser | C15: =COUNTIF(Références!$AJ$2:$AJ$201,"Non diffusé (à demander)")+COUNTIF(Références!$AJ$2:$AJ$201,"Notice en ligne (texte à localiser)") -> 15 | F15: Avancement par mois
B16: Lecture | F16: Mois | G16: Libellé | H16: Total | I16: Lues | J16: Reste | K16: Heures prévues | L16: Heures restantes | M16: Capacité | N16: Charge | O16: État
B17: Lues | C17: =COUNTIF(Références!$J$2:$J$201,"Lu") -> 0 | F17: 1 | G17: octobre 2026 | H17: =COUNTIF(Références!$I$2:$I$201,F17) -> 20 | I17: =COUNTIFS(Références!$I$2:$I$201,F17,Références!$J$2:$J$201,"Lu") -> 0 | J17: =H17-I17-COUNTIFS(Références!$I$2:$I$201,F17,Références!$J$2:$J$201,"Écarté") -> 20 | K17: =SUMIFS(Références!$AT$2:$AT$201,Références!$I$2:$I$201,F17) -> 72 | L17: =K17-SUMIFS(Références!$AT$2:$AT$201,Références!$I$2:$I$201,F17,Références!$J$2:$J$201,"Lu")-SUMIFS(Références!$AT$2:$AT$201,Références!$I$2:$I$201,F17,Références!$J$2:$J$201,"Écarté") -> 72 | M17: =Paramètres!$C$10 -> 65 | N17: =IFERROR(K17/M17,0) -> 1.1076923 | O17: =IF(J17=0,"Terminé",IF(F17<Paramètres!$C$8,"En retard",IF(F17=Paramètres!$C$8,"En cours","À venir"))) -> En cours
B18: En cours de lecture | C18: =COUNTIF(Références!$J$2:$J$201,"En cours") -> 0 | F18: 2 | G18: novembre 2026 | H18: =COUNTIF(Références!$I$2:$I$201,F18) -> 29 | I18: =COUNTIFS(Références!$I$2:$I$201,F18,Références!$J$2:$J$201,"Lu") -> 0 | J18: =H18-I18-COUNTIFS(Références!$I$2:$I$201,F18,Références!$J$2:$J$201,"Écarté") -> 29 | K18: =SUMIFS(Références!$AT$2:$AT$201,Références!$I$2:$I$201,F18) -> 70 | L18: =K18-SUMIFS(Références!$AT$2:$AT$201,Références!$I$2:$I$201,F18,Références!$J$2:$J$201,"Lu")-SUMIFS(Références!$AT$2:$AT$201,Références!$I$2:$I$201,F18,Références!$J$2:$J$201,"Écarté") -> 70 | M18: =Paramètres!$C$10 -> 65 | N18: =IFERROR(K18/M18,0) -> 1.0769231 | O18: =IF(J18=0,"Terminé",IF(F18<Paramètres!$C$8,"En retard",IF(F18=Paramètres!$C$8,"En cours","À venir"))) -> À venir
B19: Taux de lecture | C19: =IFERROR(C17/(C6-COUNTIF(Références!$J$2:$J$201,"Écarté")),0) -> 0 | F19: 3 | G19: décembre 2026 | H19: =COUNTIF(Références!$I$2:$I$201,F19) -> 20 | I19: =COUNTIFS(Références!$I$2:$I$201,F19,Références!$J$2:$J$201,"Lu") -> 0 | J19: =H19-I19-COUNTIFS(Références!$I$2:$I$201,F19,Références!$J$2:$J$201,"Écarté") -> 20 | K19: =SUMIFS(Références!$AT$2:$AT$201,Références!$I$2:$I$201,F19) -> 55 | L19: =K19-SUMIFS(Références!$AT$2:$AT$201,Références!$I$2:$I$201,F19,Références!$J$2:$J$201,"Lu")-SUMIFS(Références!$AT$2:$AT$201,Références!$I$2:$I$201,F19,Références!$J$2:$J$201,"Écarté") -> 55 | M19: =Paramètres!$C$10 -> 65 | N19: =IFERROR(K19/M19,0) -> 0.84615385 | O19: =IF(J19=0,"Terminé",IF(F19<Paramètres!$C$8,"En retard",IF(F19=Paramètres!$C$8,"En cours","À venir"))) -> À venir
B20: En retard | C20: =COUNTIF(Références!$K$2:$K$201,"EN RETARD") -> 0 | F20: 4 | G20: janvier 2027 | H20: =COUNTIF(Références!$I$2:$I$201,F20) -> 29 | I20: =COUNTIFS(Références!$I$2:$I$201,F20,Références!$J$2:$J$201,"Lu") -> 0 | J20: =H20-I20-COUNTIFS(Références!$I$2:$I$201,F20,Références!$J$2:$J$201,"Écarté") -> 29 | K20: =SUMIFS(Références!$AT$2:$AT$201,Références!$I$2:$I$201,F20) -> 73 | L20: =K20-SUMIFS(Références!$AT$2:$AT$201,Références!$I$2:$I$201,F20,Références!$J$2:$J$201,"Lu")-SUMIFS(Références!$AT$2:$AT$201,Références!$I$2:$I$201,F20,Références!$J$2:$J$201,"Écarté") -> 73 | M20: =Paramètres!$C$10 -> 65 | N20: =IFERROR(K20/M20,0) -> 1.1230769 | O20: =IF(J20=0,"Terminé",IF(F20<Paramètres!$C$8,"En retard",IF(F20=Paramètres!$C$8,"En cours","À venir"))) -> À venir
B21: À lire ce mois-ci | C21: =COUNTIF(Références!$K$2:$K$201,"Ce mois-ci") -> 20 | F21: 5 | G21: février 2027 | H21: =COUNTIF(Références!$I$2:$I$201,F21) -> 41 | I21: =COUNTIFS(Références!$I$2:$I$201,F21,Références!$J$2:$J$201,"Lu") -> 0 | J21: =H21-I21-COUNTIFS(Références!$I$2:$I$201,F21,Références!$J$2:$J$201,"Écarté") -> 41 | K21: =SUMIFS(Références!$AT$2:$AT$201,Références!$I$2:$I$201,F21) -> 112 | L21: =K21-SUMIFS(Références!$AT$2:$AT$201,Références!$I$2:$I$201,F21,Références!$J$2:$J$201,"Lu")-SUMIFS(Références!$AT$2:$AT$201,Références!$I$2:$I$201,F21,Références!$J$2:$J$201,"Écarté") -> 112 | M21: =Paramètres!$C$10 -> 65 | N21: =IFERROR(K21/M21,0) -> 1.7230769 | O21: =IF(J21=0,"Terminé",IF(F21<Paramètres!$C$8,"En retard",IF(F21=Paramètres!$C$8,"En cours","À venir"))) -> À venir
B22: PDF libres encore à télécharger | C22: =COUNTIFS(Références!$AJ$2:$AJ$201,"PDF libre",Références!$O$2:$O$201,"<>Oui")+COUNTIFS(Références!$AJ$2:$AJ$201,"PDF libre (dépôt)",Références!$O$2:$O$201,"<>Oui") -> 29 | F22: 6 | G22: mars 2027 | H22: =COUNTIF(Références!$I$2:$I$201,F22) -> 40 | I22: =COUNTIFS(Références!$I$2:$I$201,F22,Références!$J$2:$J$201,"Lu") -> 0 | J22: =H22-I22-COUNTIFS(Références!$I$2:$I$201,F22,Références!$J$2:$J$201,"Écarté") -> 40 | K22: =SUMIFS(Références!$AT$2:$AT$201,Références!$I$2:$I$201,F22) -> 103 | L22: =K22-SUMIFS(Références!$AT$2:$AT$201,Références!$I$2:$I$201,F22,Références!$J$2:$J$201,"Lu")-SUMIFS(Références!$AT$2:$AT$201,Références!$I$2:$I$201,F22,Références!$J$2:$J$201,"Écarté") -> 103 | M22: =Paramètres!$C$10 -> 65 | N22: =IFERROR(K22/M22,0) -> 1.5846154 | O22: =IF(J22=0,"Terminé",IF(F22<Paramètres!$C$8,"En retard",IF(F22=Paramètres!$C$8,"En cours","À venir"))) -> À venir
B23: Demandes à envoyer ou à relancer | C23: =COUNTIF(Demandes!$N$4:$N$40,"ENVOYER MAINTENANT")+COUNTIF(Demandes!$N$4:$N$40,"RELANCER") -> 3 | F23: Total | H23: =SUM(H17:H22) -> 179 | I23: =SUM(I17:I22) -> 0 | J23: =SUM(J17:J22) -> 179 | K23: =SUM(K17:K22) -> 485 | L23: =SUM(L17:L22) -> 485
B24: Corrections du TFE restantes | C24: =COUNTIF('Corrections TFE'!$H$4:$H$60,"Non") -> 20
F25: Prochaines lectures conseillées (plus haut score, non lues)
B26: Ce mois-ci | F26: Rang | G26: Citation | H26: Priorité | I26: Mois | J26: Score | K26: Ouvrir | L26: Titre
B27: Mois du plan en cours | C27: =IF(Paramètres!$C$8>6,"Plan terminé",Paramètres!$C$8&" — "&INDEX(Paramètres!$T$6:$T$11,Paramètres!$C$8)) -> 1 — octobre 2026 | F27: 1 | G27: =IF(J27<1,"",INDEX(Références!$C$2:$C$201,MATCH(LARGE(Références!$BA$2:$BA$201,1),Références!$BA$2:$BA$201,0))) -> De Beer et al. (2012) | H27: =IF(J27<1,"",INDEX(Références!$H$2:$H$201,MATCH(LARGE(Références!$BA$2:$BA$201,1),Références!$BA$2:$BA$201,0))) -> INCONTOURNABLE | I27: =IF(J27<1,"",INDEX(Références!$I$2:$I$201,MATCH(LARGE(Références!$BA$2:$BA$201,1),Références!$BA$2:$BA$201,0))) -> 1 | J27: =IFERROR(LARGE(Références!$BA$2:$BA$201,1),0) -> 140.00998 | K27: =IF(J27<1,"",HYPERLINK(INDEX(Références!$AF$2:$AF$201,MATCH(LARGE(Références!$BA$2:$BA$201,1),Références!$BA$2:$BA$201,0)),"Ouvrir")) -> Ouvrir | L27: =IF(J27<1,"",INDEX(Références!$D$2:$D$201,MATCH(LARGE(Références!$BA$2:$BA$201,1),Références!$BA$2:$BA$201,0))) -> Toward using tire-road contact stresses in pavement design and analysis
B28: Heures restantes ce mois-ci | C28: =SUMIFS(Références!$AT$2:$AT$201,Références!$I$2:$I$201,Paramètres!$C$8)-SUMIFS(Références!$AT$2:$AT$201,Références!$I$2:$I$201,Paramètres!$C$8,Références!$J$2:$J$201,"Lu")-SUMIFS(Références!$AT$2:$AT$201,Références!$I$2:$I$201,Paramètres!$C$8,Références!$J$2:$J$201,"Écarté") -> 72 | F28: 2 | G28: =IF(J28<1,"",INDEX(Références!$C$2:$C$201,MATCH(LARGE(Références!$BA$2:$BA$201,2),Références!$BA$2:$BA$201,0))) -> Sadoun et al. (2022) | H28: =IF(J28<1,"",INDEX(Références!$H$2:$H$201,MATCH(LARGE(Références!$BA$2:$BA$201,2),Références!$BA$2:$BA$201,0))) -> INCONTOURNABLE | I28: =IF(J28<1,"",INDEX(Références!$I$2:$I$201,MATCH(LARGE(Références!$BA$2:$BA$201,2),Références!$BA$2:$BA$201,0))) -> 1 | J28: =IFERROR(LARGE(Références!$BA$2:$BA$201,2),0) -> 140.00995 | K28: =IF(J28<1,"",HYPERLINK(INDEX(Références!$AF$2:$AF$201,MATCH(LARGE(Références!$BA$2:$BA$201,2),Références!$BA$2:$BA$201,0)),"Ouvrir")) -> Ouvrir | L28: =IF(J28<1,"",INDEX(Références!$D$2:$D$201,MATCH(LARGE(Références!$BA$2:$BA$201,2),Références!$BA$2:$BA$201,0))) -> Top-down cracking in airfield pavement structures—An in-situ test survey
B29: Heures en retard (mois passés) | C29: =SUMIFS(Références!$AT$2:$AT$201,Références!$K$2:$K$201,"EN RETARD") -> 0 | F29: 3 | G29: =IF(J29<1,"",INDEX(Références!$C$2:$C$201,MATCH(LARGE(Références!$BA$2:$BA$201,3),Références!$BA$2:$BA$201,0))) -> Airbus S.A.S. (2010) | H29: =IF(J29<1,"",INDEX(Références!$H$2:$H$201,MATCH(LARGE(Références!$BA$2:$BA$201,3),Références!$BA$2:$BA$201,0))) -> INCONTOURNABLE | I29: =IF(J29<1,"",INDEX(Références!$I$2:$I$201,MATCH(LARGE(Références!$BA$2:$BA$201,3),Références!$BA$2:$BA$201,0))) -> 1 | J29: =IFERROR(LARGE(Références!$BA$2:$BA$201,3),0) -> 140.00994 | K29: =IF(J29<1,"",HYPERLINK(INDEX(Références!$AF$2:$AF$201,MATCH(LARGE(Références!$BA$2:$BA$201,3),Références!$BA$2:$BA$201,0)),"Ouvrir")) -> Ouvrir | L29: =IF(J29<1,"",INDEX(Références!$D$2:$D$201,MATCH(LARGE(Références!$BA$2:$BA$201,3),Références!$BA$2:$BA$201,0))) -> High Tire Pressure Test (HTPT) — Final report
B30: Capacité mensuelle (h) | C30: =Paramètres!$C$10 -> 65 | F30: 4 | G30: =IF(J30<1,"",INDEX(Références!$C$2:$C$201,MATCH(LARGE(Références!$BA$2:$BA$201,4),Références!$BA$2:$BA$201,0))) -> Petitjean et al. (2001) | H30: =IF(J30<1,"",INDEX(Références!$H$2:$H$201,MATCH(LARGE(Références!$BA$2:$BA$201,4),Références!$BA$2:$BA$201,0))) -> INCONTOURNABLE | I30: =IF(J30<1,"",INDEX(Références!$I$2:$I$201,MATCH(LARGE(Références!$BA$2:$BA$201,4),Références!$BA$2:$BA$201,0))) -> 1 | J30: =IFERROR(LARGE(Références!$BA$2:$BA$201,4),0) -> 140.00993 | K30: =IF(J30<1,"",HYPERLINK(INDEX(Références!$AF$2:$AF$201,MATCH(LARGE(Références!$BA$2:$BA$201,4),Références!$BA$2:$BA$201,0)),"Ouvrir")) -> Ouvrir | L30: =IF(J30<1,"",INDEX(Références!$D$2:$D$201,MATCH(LARGE(Références!$BA$2:$BA$201,4),Références!$BA$2:$BA$201,0))) -> LCPC / Airbus / STBA A380 Pavement Experimental Programme
B31: Charge | C31: =IF(C28+C29>C30,"Surcharge : reporter des « A consulter » au mois suivant","Dans la capacité") -> Surcharge : reporter des « A consulter » au mois suivant | F31: 5 | G31: =IF(J31<1,"",INDEX(Références!$C$2:$C$201,MATCH(LARGE(Références!$BA$2:$BA$201,5),Références!$BA$2:$BA$201,0))) -> Olard & Di Benedetto (2003) | H31: =IF(J31<1,"",INDEX(Références!$H$2:$H$201,MATCH(LARGE(Références!$BA$2:$BA$201,5),Références!$BA$2:$BA$201,0))) -> INCONTOURNABLE | I31: =IF(J31<1,"",INDEX(Références!$I$2:$I$201,MATCH(LARGE(Références!$BA$2:$BA$201,5),Références!$BA$2:$BA$201,0))) -> 2 | J31: =IFERROR(LARGE(Références!$BA$2:$BA$201,5),0) -> 135.00979 | K31: =IF(J31<1,"",HYPERLINK(INDEX(Références!$AF$2:$AF$201,MATCH(LARGE(Références!$BA$2:$BA$201,5),Références!$BA$2:$BA$201,0)),"Ouvrir")) -> Ouvrir | L31: =IF(J31<1,"",INDEX(Références!$D$2:$D$201,MATCH(LARGE(Références!$BA$2:$BA$201,5),Références!$BA$2:$BA$201,0))) -> General "2S2P1D" model and relation between the linear viscoelastic behaviours of bituminous binders and mixes
B32: Prochaine action | C32: =IF(C23>0,"Envoyer ou relancer "&C23&" demande(s) : feuille Demandes",IF(C22>0,"Télécharger "&C22&" PDF libre(s) : colonne Ouvrir",IF(G27="","Rien en attente","Lire "&G27))) -> Envoyer ou relancer 3 demande(s) : feuille Demandes | F32: 6 | G32: =IF(J32<1,"",INDEX(Références!$C$2:$C$201,MATCH(LARGE(Références!$BA$2:$BA$201,6),Références!$BA$2:$BA$201,0))) -> Tiouajni et al. (2011) | H32: =IF(J32<1,"",INDEX(Références!$H$2:$H$201,MATCH(LARGE(Références!$BA$2:$BA$201,6),Références!$BA$2:$BA$201,0))) -> INCONTOURNABLE | I32: =IF(J32<1,"",INDEX(Références!$I$2:$I$201,MATCH(LARGE(Références!$BA$2:$BA$201,6),Références!$BA$2:$BA$201,0))) -> 2 | J32: =IFERROR(LARGE(Références!$BA$2:$BA$201,6),0) -> 135.00978 | K32: =IF(J32<1,"",HYPERLINK(INDEX(Références!$AF$2:$AF$201,MATCH(LARGE(Références!$BA$2:$BA$201,6),Références!$BA$2:$BA$201,0)),"Ouvrir")) -> Ouvrir | L32: =IF(J32<1,"",INDEX(Références!$D$2:$D$201,MATCH(LARGE(Références!$BA$2:$BA$201,6),Références!$BA$2:$BA$201,0))) -> Approximation of linear viscoelastic model in the 3 dimensional case with mechanical analogues of finite size: Application to bituminous materials
F33: 7 | G33: =IF(J33<1,"",INDEX(Références!$C$2:$C$201,MATCH(LARGE(Références!$BA$2:$BA$201,7),Références!$BA$2:$BA$201,0))) -> De Beer & Fisher (2013) | H33: =IF(J33<1,"",INDEX(Références!$H$2:$H$201,MATCH(LARGE(Références!$BA$2:$BA$201,7),Références!$BA$2:$BA$201,0))) -> INCONTOURNABLE | I33: =IF(J33<1,"",INDEX(Références!$I$2:$I$201,MATCH(LARGE(Références!$BA$2:$BA$201,7),Références!$BA$2:$BA$201,0))) -> 1 | J33: =IFERROR(LARGE(Références!$BA$2:$BA$201,7),0) -> 130.00997 | K33: =IF(J33<1,"",HYPERLINK(INDEX(Références!$AF$2:$AF$201,MATCH(LARGE(Références!$BA$2:$BA$201,7),Références!$BA$2:$BA$201,0)),"Ouvrir")) -> Ouvrir | L33: =IF(J33<1,"",INDEX(Références!$D$2:$D$201,MATCH(LARGE(Références!$BA$2:$BA$201,7),Références!$BA$2:$BA$201,0))) -> Stress-In-Motion (SIM) system for capturing tri-axial tyre–road interaction in the contact patch
F34: 8 | G34: =IF(J34<1,"",INDEX(Références!$C$2:$C$201,MATCH(LARGE(Références!$BA$2:$BA$201,8),Références!$BA$2:$BA$201,0))) -> Tielking (1989) | H34: =IF(J34<1,"",INDEX(Références!$H$2:$H$201,MATCH(LARGE(Références!$BA$2:$BA$201,8),Références!$BA$2:$BA$201,0))) -> INCONTOURNABLE | I34: =IF(J34<1,"",INDEX(Références!$I$2:$I$201,MATCH(LARGE(Références!$BA$2:$BA$201,8),Références!$BA$2:$BA$201,0))) -> 1 | J34: =IFERROR(LARGE(Références!$BA$2:$BA$201,8),0) -> 130.00996 | K34: =IF(J34<1,"",HYPERLINK(INDEX(Références!$AF$2:$AF$201,MATCH(LARGE(Références!$BA$2:$BA$201,8),Références!$BA$2:$BA$201,0)),"Ouvrir")) -> Ouvrir | L34: =IF(J34<1,"",INDEX(Références!$D$2:$D$201,MATCH(LARGE(Références!$BA$2:$BA$201,8),Références!$BA$2:$BA$201,0))) -> Aircraft tire/pavement pressure distribution
F36: Accès aux documents
G37: Accès document | H37: Nombre | I37: Part
G38: PDF libre | H38: =COUNTIF(Références!$AJ$2:$AJ$201,G38) -> 41 | I38: =IFERROR(H38/$C$6,0) -> 0.22905028
G39: PDF libre (dépôt) | H39: =COUNTIF(Références!$AJ$2:$AJ$201,G39) -> 15 | I39: =IFERROR(H39/$C$6,0) -> 0.083798883
G40: Éditeur (abonnement) | H40: =COUNTIF(Références!$AJ$2:$AJ$201,G40) -> 80 | I40: =IFERROR(H40/$C$6,0) -> 0.44692737
G41: Payant (boutique) | H41: =COUNTIF(Références!$AJ$2:$AJ$201,G41) -> 28 | I41: =IFERROR(H41/$C$6,0) -> 0.15642458
G42: Non diffusé (à demander) | H42: =COUNTIF(Références!$AJ$2:$AJ$201,G42) -> 7 | I42: =IFERROR(H42/$C$6,0) -> 0.039106145
G43: Notice en ligne (texte à localiser) | H43: =COUNTIF(Références!$AJ$2:$AJ$201,G43) -> 8 | I43: =IFERROR(H43/$C$6,0) -> 0.044692737

Sheet Références
A1: ID | B1: Clé | C1: Citation | D1: Titre | E1: Ouvrir | F1: TFE | G1: Axe | H1: Priorité | I1: Mois | J1: Statut lecture | K1: État | L1: Alerte | M1: Score | N1: Date lecture | O1: PDF récupéré | P1: Dans Zotero | Q1: Note Obsidian | R1: Pertinence (1-5) | S1: Commentaire | T1: Type RIS | U1: Type | V1: Auteurs | W1: Année | X1: Support (revue, actes) | Y1: Vol. | Z1: N° | AA1: Pages | AB1: Éditeur / institution | AC1: DOI | AD1: Identifiant (rapport, norme, ISBN, NNT, HAL) | AE1: Type de lien | AF1: Lien (URL) | AG1: doi.org | AH1: Chercher | AI1: Accès | AJ1: Accès document | AK1: Comment l'obtenir | AL1: Vérification | AM1: Source de vérification | AN1: Vérifié le | AO1: Contribution et lien avec tes travaux | AP1: Voir aussi | AQ1: Littérature grise | AR1: Intitulé de l'axe | AS1: Mois (libellé) | AT1: Temps estimé (h) | AU1: État du lien (macro) | AV1: Lien contrôlé le | AW1: Fichier de note | AX1: Rang dans le mois | AY1: Clé mois-rang | AZ1: URL de recherche | BA1: Score de tri | BB1: Fichier PDF
A2: BIB-001 | B2: debeer2012toward | C2: =IF($B2="","",IFERROR(LEFT(LEFT($V2,FIND(";",$V2&";")-1),FIND(",",LEFT($V2,FIND(";",$V2&";")-1))-1),LEFT($V2,FIND(";",$V2&";")-1))&IF((LEN($V2)-LEN(SUBSTITUTE($V2,";",""))+1)=1,"",IF((LEN($V2)-LEN(SUBSTITUTE($V2,";",""))+1)=2," & "&IFERROR(LEFT(TRIM(MID($V2,FIND(";",$V2)+1,FIND(";",$V2&";",FIND(";",$V2)+1)-FIND(";",$V2)-1)),FIND(",",TRIM(MID($V2,FIND(";",$V2)+1,FIND(";",$V2&";",FIND(";",$V2)+1)-FIND(";",$V2)-1)))-1),TRIM(MID($V2,FIND(";",$V2)+1,FIND(";",$V2&";",FIND(";",$V2)+1)-FIND(";",$V2)-1)))," et al."))&" ("&$W2&")") -> De Beer et al. (2012) | D2: Toward using tire-road contact stresses in pavement design and analysis | E2: =IF(OR($B2="",$AF2=""),"",HYPERLINK(IF(AND(Paramètres!$C$13<>"",$AJ2="Éditeur (abonnement)"),Paramètres!$C$13&$AF2,$AF2),"Ouvrir : "&$AE2)) -> Ouvrir : Page éditeur (DOI) | F2: Oui | G2: 1 | H2: INCONTOURNABLE | I2: 1 | J2: À lire | K2: =IF($B2="","",IF($J2="Lu","Lu",IF($J2="Écarté","Écarté",IF($I2<Paramètres!$C$8,"EN RETARD",IF($I2=Paramètres!$C$8,"Ce mois-ci",IF($I2=Paramètres!$C$8+1,"Mois prochain","À venir")))))) -> Ce mois-ci | L2: =IF($B2="","",IF($AL2="Non vérifié","Ne pas citer en l'état : métadonnées non vérifiées",IF($AL2="Partiel","Vérification à compléter avant de citer",IF($O2="Oui","",IF(OR($AJ2="PDF libre",$AJ2="PDF libre (dépôt)"),"PDF libre à télécharger",IF($AJ2="Éditeur (abonnement)","À télécharger via l'accès ENTPE",IF($AJ2="Payant (boutique)","À consulter via l'abonnement de l'école",IF($AJ2="Non diffusé (à demander)","Document à demander (feuille Demandes)","Texte intégral à localiser")))))))) | M2: =IF($B2="","",IF(OR($J2="Lu",$J2="Écarté"),0,IFERROR(INDEX(Paramètres!$C$17:$C$19,MATCH($H2,Paramètres!$B$17:$B$19,0)),0)+Paramètres!$C$20*(7-$I2)+IF($I2<Paramètres!$C$8,Paramètres!$C$21,0)+IF($F2="Oui",Paramètres!$C$22,0)+IF($AL2<>"Vérifié",Paramètres!$C$23,0)+IF(AND($O2<>"Oui",OR($AJ2="PDF libre",$AJ2="PDF libre (dépôt)")),Paramètres!$C$24,0))) -> 140 | O2: =IF($BB2="","Non",HYPERLINK(DossierPDF&$BB2,"Oui")) -> Oui | P2: Non | Q2: Non | T2: JOUR | U2: =IF($B2="","",IFERROR(INDEX(Paramètres!$N$6:$N$13,MATCH($T2,Paramètres!$M$6:$M$13,0)),$T2)) -> Article de revue | V2: De Beer, M.; Maina, J. W.; van Rensburg, Y.; Greben, J. M. | W2: 2012 | X2: Tire Science and Technology | Y2: 40 | Z2: 4 | AA2: 246-271 | AC2: 10.2346/tire.12.400403 | AE2: Page éditeur (DOI) | AF2: https://doi.org/10.2346/tire.12.400403 | AG2: =IF($AC2="","",HYPERLINK("https://doi.org/"&$AC2,"doi.org")) -> doi.org | AH2: =IF($AZ2="","",HYPERLINK($AZ2,"Scholar")) -> Scholar | AI2: Payant | AJ2: Éditeur (abonnement) | AK2: Tire Science and Technology (The Tire Society) : accès par abonnement ; résumé libre sur le dépôt du CSIR. | AL2: Vérifié | AM2: OpenAlex (DOI) + résumé CSIR | AN2: 22/09/2026 | AO2: Plaide pour intégrer des contraintes de contact mesurées dans le calcul des chaussées, en particulier près de la surface, où le modèle circulaire uniforme ne suffit plus à expliquer les dégradations. Lien avec ta thèse : justification bibliographique centrale de ta problématique. | AP2: De Beer & Fisher (2013) ; De Beer et al. (2004) | AQ2: Non | AR2: =IF($B2="","",IFERROR(INDEX(Paramètres!$Q$6:$Q$13,MATCH($G2,Paramètres!$P$6:$P$13,0)),"")) -> Mesure de la pression de contact pneu-chaussée | AS2: =IF($B2="","",IFERROR(INDEX(Paramètres!$T$6:$T$11,MATCH($I2,Paramètres!$S$6:$S$11,0)),"")) -> octobre 2026 | AT2: =IF($B2="","",IFERROR(INDEX(Paramètres!$C$27:$C$29,MATCH($H2,Paramètres!$B$27:$B$29,0)),0)) -> 6 | AW2: =IF($B2="","",$B2&".md") -> debeer2012toward.md | AX2: =IF($B2="","",COUNTIF($I$2:I2,$I2)) -> 1 | AY2: =IF($B2="","",$I2&"-"&$AX2) -> 1-1 | AZ2: https://scholar.google.com/scholar?q=%22Toward+using+tire-road+contact+stresses+in+pavement+design+and+analysis%22 | BA2: =IF($B2="","",$M2+(1000-ROW())/100000) -> 140.00998 | BB2: BIB-001_DeBeer-etal_2012_Tire-road-contact-stresses-pavement-design.pdf
A3: BIB-002 | B3: debeer2013sim | C3: =IF($B3="","",IFERROR(LEFT(LEFT($V3,FIND(";",$V3&";")-1),FIND(",",LEFT($V3,FIND(";",$V3&";")-1))-1),LEFT($V3,FIND(";",$V3&";")-1))&IF((LEN($V3)-LEN(SUBSTITUTE($V3,";",""))+1)=1,"",IF((LEN($V3)-LEN(SUBSTITUTE($V3,";",""))+1)=2," & "&IFERROR(LEFT(TRIM(MID($V3,FIND(";",$V3)+1,FIND(";",$V3&";",FIND(";",$V3)+1)-FIND(";",$V3)-1)),FIND(",",TRIM(MID($V3,FIND(";",$V3)+1,FIND(";",$V3&";",FIND(";",$V3)+1)-FIND(";",$V3)-1)))-1),TRIM(MID($V3,FIND(";",$V3)+1,FIND(";",$V3&";",FIND(";",$V3)+1)-FIND(";",$V3)-1)))," et al."))&" ("&$W3&")") -> De Beer & Fisher (2013) | D3: Stress-In-Motion (SIM) system for capturing tri-axial tyre–road interaction in the contact patch | E3: =IF(OR($B3="",$AF3=""),"",HYPERLINK(IF(AND(Paramètres!$C$13<>"",$AJ3="Éditeur (abonnement)"),Paramètres!$C$13&$AF3,$AF3),"Ouvrir : "&$AE3)) -> Ouvrir : Page éditeur (DOI) | F3: Non | G3: 1 | H3: INCONTOURNABLE | I3: 1 | J3: À lire | K3: =IF($B3="","",IF($J3="Lu","Lu",IF($J3="Écarté","Écarté",IF($I3<Paramètres!$C$8,"EN RETARD",IF($I3=Paramètres!$C$8,"Ce mois-ci",IF($I3=Paramètres!$C$8+1,"Mois prochain","À venir")))))) -> Ce mois-ci | L3: =IF($B3="","",IF($AL3="Non vérifié","Ne pas citer en l'état : métadonnées non vérifiées",IF($AL3="Partiel","Vérification à compléter avant de citer",IF($O3="Oui","",IF(OR($AJ3="PDF libre",$AJ3="PDF libre (dépôt)"),"PDF libre à télécharger",IF($AJ3="Éditeur (abonnement)","À télécharger via l'accès ENTPE",IF($AJ3="Payant (boutique)","À consulter via l'abonnement de l'école",IF($AJ3="Non diffusé (à demander)","Document à demander (feuille Demandes)","Texte intégral à localiser")))))))) | M3: =IF($B3="","",IF(OR($J3="Lu",$J3="Écarté"),0,IFERROR(INDEX(Paramètres!$C$17:$C$19,MATCH($H3,Paramètres!$B$17:$B$19,0)),0)+Paramètres!$C$20*(7-$I3)+IF($I3<Paramètres!$C$8,Paramètres!$C$21,0)+IF($F3="Oui",Paramètres!$C$22,0)+IF($AL3<>"Vérifié",Paramètres!$C$23,0)+IF(AND($O3<>"Oui",OR($AJ3="PDF libre",$AJ3="PDF libre (dépôt)")),Paramètres!$C$24,0))) -> 130 | O3: =IF($BB3="","Non",HYPERLINK(DossierPDF&$BB3,"Oui")) -> Oui | P3: Non | Q3: Non | T3: JOUR | U3: =IF($B3="","",IFERROR(INDEX(Paramètres!$N$6:$N$13,MATCH($T3,Paramètres!$M$6:$M$13,0)),$T3)) -> Article de revue | V3: De Beer, M.; Fisher, C. | W3: 2013 | X3: Measurement | Y3: 46 | Z3: 7 | AA3: 2155-2173 | AC3: 10.1016/j.measurement.2013.03.012 | AE3: Page éditeur (DOI) | AF3: https://doi.org/10.1016/j.measurement.2013.03.012 | AG3: =IF($AC3="","",HYPERLINK("https://doi.org/"&$AC3,"doi.org")) -> doi.org | AH3: =IF($AZ3="","",HYPERLINK($AZ3,"Scholar")) -> Scholar | AI3: Payant | AJ3: Éditeur (abonnement) | AK3: Elsevier (ScienceDirect) : accès par l'abonnement de l'ENTPE. | AL3: Vérifié | AM3: OpenAlex (DOI) | AN3: 22/09/2026 | AO3: Description complète du système SIM : conception des capteurs, étalonnage, capture des trois composantes de contrainte dans l'empreinte. Lien avec ta thèse : pour discuter la fiabilité des données que tu as utilisées et préparer une campagne de mesure dédiée (ta perspective n° 1). | AP3: De Beer et al. (1997) | AQ3: Non | AR3: =IF($B3="","",IFERROR(INDEX(Paramètres!$Q$6:$Q$13,MATCH($G3,Paramètres!$P$6:$P$13,0)),"")) -> Mesure de la pression de contact pneu-chaussée | AS3: =IF($B3="","",IFERROR(INDEX(Paramètres!$T$6:$T$11,MATCH($I3,Paramètres!$S$6:$S$11,0)),"")) -> octobre 2026 | AT3: =IF($B3="","",IFERROR(INDEX(Paramètres!$C$27:$C$29,MATCH($H3,Paramètres!$B$27:$B$29,0)),0)) -> 6 | AW3: =IF($B3="","",$B3&".md") -> debeer2013sim.md | AX3: =IF($B3="","",COUNTIF($I$2:I3,$I3)) -> 2 | AY3: =IF($B3="","",$I3&"-"&$AX3) -> 1-2 | AZ3: https://scholar.google.com/scholar?q=%22Stress-In-Motion+%28SIM%29+system+for+capturing+tri-axial+tyre%E2%80%93road+interaction+in+the+contact+patch%22 | BA3: =IF($B3="","",$M3+(1000-ROW())/100000) -> 130.00997 | BB3: BIB-002_DeBeer-Fisher_2013_Stress-In-Motion-SIM-system.pdf
A4: BIB-003 | B4: tielking1989afesc | C4: =IF($B4="","",IFERROR(LEFT(LEFT($V4,FIND(";",$V4&";")-1),FIND(",",LEFT($V4,FIND(";",$V4&";")-1))-1),LEFT($V4,FIND(";",$V4&";")-1))&IF((LEN($V4)-LEN(SUBSTITUTE($V4,";",""))+1)=1,"",IF((LEN($V4)-LEN(SUBSTITUTE($V4,";",""))+1)=2," & "&IFERROR(LEFT(TRIM(MID($V4,FIND(";",$V4)+1,FIND(";",$V4&";",FIND(";",$V4)+1)-FIND(";",$V4)-1)),FIND(",",TRIM(MID($V4,FIND(";",$V4)+1,FIND(";",$V4&";",FIND(";",$V4)+1)-FIND(";",$V4)-1)))-1),TRIM(MID($V4,FIND(";",$V4)+1,FIND(";",$V4&";",FIND(";",$V4)+1)-FIND(";",$V4)-1)))," et al."))&" ("&$W4&")") -> Tielking (1989) | D4: Aircraft tire/pavement pressure distribution | E4: =IF(OR($B4="",$AF4=""),"",HYPERLINK(IF(AND(Paramètres!$C$13<>"",$AJ4="Éditeur (abonnement)"),Paramètres!$C$13&$AF4,$AF4),"Ouvrir : "&$AE4)) -> Ouvrir : Texte intégral libre | F4: Non | G4: 1 | H4: INCONTOURNABLE | I4: 1 | J4: À lire | K4: =IF($B4="","",IF($J4="Lu","Lu",IF($J4="Écarté","Écarté",IF($I4<Paramètres!$C$8,"EN RETARD",IF($I4=Paramètres!$C$8,"Ce mois-ci",IF($I4=Paramètres!$C$8+1,"Mois prochain","À venir")))))) -> Ce mois-ci | L4: =IF($B4="","",IF($AL4="Non vérifié","Ne pas citer en l'état : métadonnées non vérifiées",IF($AL4="Partiel","Vérification à compléter avant de citer",IF($O4="Oui","",IF(OR($AJ4="PDF libre",$AJ4="PDF libre (dépôt)"),"PDF libre à télécharger",IF($AJ4="Éditeur (abonnement)","À télécharger via l'accès ENTPE",IF($AJ4="Payant (boutique)","À consulter via l'abonnement de l'école",IF($AJ4="Non diffusé (à demander)","Document à demander (feuille Demandes)","Texte intégral à localiser")))))))) | M4: =IF($B4="","",IF(OR($J4="Lu",$J4="Écarté"),0,IFERROR(INDEX(Paramètres!$C$17:$C$19,MATCH($H4,Paramètres!$B$17:$B$19,0)),0)+Paramètres!$C$20*(7-$I4)+IF($I4<Paramètres!$C$8,Paramètres!$C$21,0)+IF($F4="Oui",Paramètres!$C$22,0)+IF($AL4<>"Vérifié",Paramètres!$C$23,0)+IF(AND($O4<>"Oui",OR($AJ4="PDF libre",$AJ4="PDF libre (dépôt)")),Paramètres!$C$24,0))) -> 130 | O4: =IF($BB4="","Non",HYPERLINK(DossierPDF&$BB4,"Oui")) -> Oui | P4: Non | Q4: Non | T4: RPRT | U4: =IF($B4="","",IFERROR(INDEX(Paramètres!$N$6:$N$13,MATCH($T4,Paramètres!$M$6:$M$13,0)),$T4)) -> Rapport | V4: Tielking, J. T. | W4: 1989 | AB4: Air Force Engineering & Services Center, Tyndall AFB (Texas Transportation Institute, Texas A&M University) | AD4: ESL-TR-89-01 ; DTIC ADA279100 ; 53 p. | AE4: Texte intégral libre | AF4: https://apps.dtic.mil/sti/pdfs/ADA279100.pdf | AG4: =IF($AC4="","",HYPERLINK("https://doi.org/"&$AC4,"doi.org")) | AH4: =IF($AZ4="","",HYPERLINK($AZ4,"Scholar")) -> Scholar | AI4: Libre | AJ4: PDF libre | AK4: PDF public sur DTIC (diffusion libre). | AL4: Vérifié | AM4: Page de documentation du rapport (DTIC) | AN4: 22/09/2026 | AO4: Pressions de contact pneu-chaussée calculées pour sept pneus d'avion différents, dans un rapport pour l'US Air Force. Lien avec ta thèse : une des rares sources publiques sur la distribution sous pneu d'avion ; point de comparaison pour ta transposition du pneu de camion au pneu d'avion. | AP4: Tielking (1989) ; Airbus S.A.S. (2010) | AQ4: Oui | AR4: =IF($B4="","",IFERROR(INDEX(Paramètres!$Q$6:$Q$13,MATCH($G4,Paramètres!$P$6:$P$13,0)),"")) -> Mesure de la pression de contact pneu-chaussée | AS4: =IF($B4="","",IFERROR(INDEX(Paramètres!$T$6:$T$11,MATCH($I4,Paramètres!$S$6:$S$11,0)),"")) -> octobre 2026 | AT4: =IF($B4="","",IFERROR(INDEX(Paramètres!$C$27:$C$29,MATCH($H4,Paramètres!$B$27:$B$29,0)),0)) -> 6 | AW4: =IF($B4="","",$B4&".md") -> tielking1989afesc.md | AX4: =IF($B4="","",COUNTIF($I$2:I4,$I4)) -> 3 | AY4: =IF($B4="","",$I4&"-"&$AX4) -> 1-3 | AZ4: https://scholar.google.com/scholar?q=%22Aircraft+tire%2Fpavement+pressure+distribution%22 | BA4: =IF($B4="","",$M4+(1000-ROW())/100000) -> 130.00996 | BB4: BIB-003_Tielking_1989_Aircraft-tire-pavement-pressure-distribution.pdf
A5: BIB-004 | B5: sadoun2022topdown | C5: =IF($B5="","",IFERROR(LEFT(LEFT($V5,FIND(";",$V5&";")-1),FIND(",",LEFT($V5,FIND(";",$V5&";")-1))-1),LEFT($V5,FIND(";",$V5&";")-1))&IF((LEN($V5)-LEN(SUBSTITUTE($V5,";",""))+1)=1,"",IF((LEN($V5)-LEN(SUBSTITUTE($V5,";",""))+1)=2," & "&IFERROR(LEFT(TRIM(MID($V5,FIND(";",$V5)+1,FIND(";",$V5&";",FIND(";",$V5)+1)-FIND(";",$V5)-1)),FIND(",",TRIM(MID($V5,FIND(";",$V5)+1,FIND(";",$V5&";",FIND(";",$V5)+1)-FIND(";",$V5)-1)))-1),TRIM(MID($V5,FIND(";",$V5)+1,FIND(";",$V5&";",FIND(";",$V5)+1)-FIND(";",$V5)-1)))," et al."))&" ("&$W5&")") -> Sadoun et al. (2022) | D5: Top-down cracking in airfield pavement structures—An in-situ test survey | E5: =IF(OR($B5="",$AF5=""),"",HYPERLINK(IF(AND(Paramètres!$C$13<>"",$AJ5="Éditeur (abonnement)"),Paramètres!$C$13&$AF5,$AF5),"Ouvrir : "&$AE5)) -> Ouvrir : Page éditeur (DOI) | F5: Oui | G5: 6 | H5: INCONTOURNABLE | I5: 1 | J5: À lire | K5: =IF($B5="","",IF($J5="Lu","Lu",IF($J5="Écarté","Écarté",IF($I5<Paramètres!$C$8,"EN RETARD",IF($I5=Paramètres!$C$8,"Ce mois-ci",IF($I5=Paramètres!$C$8+1,"Mois prochain","À venir")))))) -> Ce mois-ci | L5: =IF($B5="","",IF($AL5="Non vérifié","Ne pas citer en l'état : métadonnées non vérifiées",IF($AL5="Partiel","Vérification à compléter avant de citer",IF($O5="Oui","",IF(OR($AJ5="PDF libre",$AJ5="PDF libre (dépôt)"),"PDF libre à télécharger",IF($AJ5="Éditeur (abonnement)","À télécharger via l'accès ENTPE",IF($AJ5="Payant (boutique)","À consulter via l'abonnement de l'école",IF($AJ5="Non diffusé (à demander)","Document à demander (feuille Demandes)","Texte intégral à localiser")))))))) | M5: =IF($B5="","",IF(OR($J5="Lu",$J5="Écarté"),0,IFERROR(INDEX(Paramètres!$C$17:$C$19,MATCH($H5,Paramètres!$B$17:$B$19,0)),0)+Paramètres!$C$20*(7-$I5)+IF($I5<Paramètres!$C$8,Paramètres!$C$21,0)+IF($F5="Oui",Paramètres!$C$22,0)+IF($AL5<>"Vérifié",Paramètres!$C$23,0)+IF(AND($O5<>"Oui",OR($AJ5="PDF libre",$AJ5="PDF libre (dépôt)")),Paramètres!$C$24,0))) -> 140 | O5: =IF($BB5="","Non",HYPERLINK(DossierPDF&$BB5,"Oui")) -> Oui | P5: Non | Q5: Non | T5: CONF | U5: =IF($B5="","",IFERROR(INDEX(Paramètres!$N$6:$N$13,MATCH($T5,Paramètres!$M$6:$M$13,0)),$T5)) -> Communication (actes) | V5: Sadoun, A.; Broutin, M.; Boulkhemair, I.; Duprey, A.; Mazars, A.; Huault, M. | W5: 2022 | X5: Proceedings of the RILEM International Symposium on Bituminous Materials (ISBM Lyon 2020) | Y5: 27 | AA5: 1861-1867 | AB5: Springer | AC5: 10.1007/978-3-030-46455-4_236 | AD5: RILEM Bookseries, vol. 27 | AE5: Page éditeur (DOI) | AF5: https://doi.org/10.1007/978-3-030-46455-4_236 | AG5: =IF($AC5="","",HYPERLINK("https://doi.org/"&$AC5,"doi.org")) -> doi.org | AH5: =IF($AZ5="","",HYPERLINK($AZ5,"Scholar")) -> Scholar | AI5: Payant | AJ5: Éditeur (abonnement) | AK5: SpringerLink : abonnement ENTPE ; sinon demander le texte à M. Broutin (co-auteur). | AL5: Vérifié | AM5: OpenAlex (DOI) ; chapitre mis en ligne en 2021, volume daté 2022 | AN5: 22/09/2026 | AO5: Fissuration descendante observée sur des chaussées aéronautiques françaises ; expérimentation sur la piste 14R-32L de Toulouse-Blagnac, chaussée rigide renforcée par une couche bitumineuse (aéroport, Cerema, Airbus, STAC) : ovalisation, inclinomètres, déplacements des dalles sous A319, essais HWD, modèle éléments finis 2D avec enrobés viscoélastiques. Lien avec ta thèse : c'est l'observation de terrain de ton TFE (Fig. 1-27) qui justifie un critère de surface ; la structure étant composite, la comparaison avec ta chaussée souple reste qualitative. | AP5: Canestrari & Ingrassia (2020) ; Wang & Al-Qadi (2010) ; Cardoso da Silva et al. (2025) | AQ5: Oui | AR5: =IF($B5="","",IFERROR(INDEX(Paramètres!$Q$6:$Q$13,MATCH($G5,Paramètres!$P$6:$P$13,0)),"")) -> Fatigue et endommagement | AS5: =IF($B5="","",IFERROR(INDEX(Paramètres!$T$6:$T$11,MATCH($I5,Paramètres!$S$6:$S$11,0)),"")) -> octobre 2026 | AT5: =IF($B5="","",IFERROR(INDEX(Paramètres!$C$27:$C$29,MATCH($H5,Paramètres!$B$27:$B$29,0)),0)) -> 6 | AW5: =IF($B5="","",$B5&".md") -> sadoun2022topdown.md | AX5: =IF($B5="","",COUNTIF($I$2:I5,$I5)) -> 4 | AY5: =IF($B5="","",$I5&"-"&$AX5) -> 1-4 | AZ5: https://scholar.google.com/scholar?q=%22Top-down+cracking+in+airfield+pavement+structures%E2%80%94An+in-situ+test+survey%22 | BA5: =IF($B5="","",$M5+(1000-ROW())/100000) -> 140.00995 | BB5: BIB-004_Sadoun-etal_2022_Top-down-cracking-airfield-pavements.pdf
A6: BIB-005 | B6: airbus2010htpt | C6: =IF($B6="","",IFERROR(LEFT(LEFT($V6,FIND(";",$V6&";")-1),FIND(",",LEFT($V6,FIND(";",$V6&";")-1))-1),LEFT($V6,FIND(";",$V6&";")-1))&IF((LEN($V6)-LEN(SUBSTITUTE($V6,";",""))+1)=1,"",IF((LEN($V6)-LEN(SUBSTITUTE($V6,";",""))+1)=2," & "&IFERROR(LEFT(TRIM(MID($V6,FIND(";",$V6)+1,FIND(";",$V6&";",FIND(";",$V6)+1)-FIND(";",$V6)-1)),FIND(",",TRIM(MID($V6,FIND(";",$V6)+1,FIND(";",$V6&";",FIND(";",$V6)+1)-FIND(";",$V6)-1)))-1),TRIM(MID($V6,FIND(";",$V6)+1,FIND(";",$V6&";",FIND(";",$V6)+1)-FIND(";",$V6)-1)))," et al."))&" ("&$W6&")") -> Airbus S.A.S. (2010) | D6: High Tire Pressure Test (HTPT) — Final report | E6: =IF(OR($B6="",$AF6=""),"",HYPERLINK(IF(AND(Paramètres!$C$13<>"",$AJ6="Éditeur (abonnement)"),Paramètres!$C$13&$AF6,$AF6),"Ouvrir : "&$AE6)) -> Ouvrir : Texte intégral libre | F6: Oui | G6: 7 | H6: INCONTOURNABLE | I6: 1 | J6: À lire | K6: =IF($B6="","",IF($J6="Lu","Lu",IF($J6="Écarté","Écarté",IF($I6<Paramètres!$C$8,"EN RETARD",IF($I6=Paramètres!$C$8,"Ce mois-ci",IF($I6=Paramètres!$C$8+1,"Mois prochain","À venir")))))) -> Ce mois-ci | L6: =IF($B6="","",IF($AL6="Non vérifié","Ne pas citer en l'état : métadonnées non vérifiées",IF($AL6="Partiel","Vérification à compléter avant de citer",IF($O6="Oui","",IF(OR($AJ6="PDF libre",$AJ6="PDF libre (dépôt)"),"PDF libre à télécharger",IF($AJ6="Éditeur (abonnement)","À télécharger via l'accès ENTPE",IF($AJ6="Payant (boutique)","À consulter via l'abonnement de l'école",IF($AJ6="Non diffusé (à demander)","Document à demander (feuille Demandes)","Texte intégral à localiser")))))))) | M6: =IF($B6="","",IF(OR($J6="Lu",$J6="Écarté"),0,IFERROR(INDEX(Paramètres!$C$17:$C$19,MATCH($H6,Paramètres!$B$17:$B$19,0)),0)+Paramètres!$C$20*(7-$I6)+IF($I6<Paramètres!$C$8,Paramètres!$C$21,0)+IF($F6="Oui",Paramètres!$C$22,0)+IF($AL6<>"Vérifié",Paramètres!$C$23,0)+IF(AND($O6<>"Oui",OR($AJ6="PDF libre",$AJ6="PDF libre (dépôt)")),Paramètres!$C$24,0))) -> 140 | O6: =IF($BB6="","Non",HYPERLINK(DossierPDF&$BB6,"Oui")) -> Oui | P6: Non | Q6: Non | T6: RPRT | U6: =IF($B6="","",IFERROR(INDEX(Paramètres!$N$6:$N$13,MATCH($T6,Paramètres!$M$6:$M$13,0)),$T6)) -> Rapport | V6: Airbus S.A.S. | W6: 2010 | AB6: Airbus S.A.S., Airport Operations | AD6: X32RP0926801, Issue 2.0 | AE6: Texte intégral libre | AF6: https://www.aircraft.airbus.com/sites/g/files/jlcbta126/files/2023-02/Airbus-Commercial-Aircraft-HTPT-final-report-31-Aug-2010.pdf | AG6: =IF($AC6="","",HYPERLINK("https://doi.org/"&$AC6,"doi.org")) | AH6: =IF($AZ6="","",HYPERLINK($AZ6,"Scholar")) -> Scholar | AI6: Libre | AJ6: PDF libre | AK6: Rapport public sur le site d'Airbus. | AL6: Vérifié | AM6: PDF Airbus (page de titre, §3.4.2, Fig. 26) | AN6: 22/09/2026 | AO6: Rapport final de l'essai HTPT mené par Airbus avec le STAC, le LCPC, le LRPC de Toulouse, Michelin et Vancouver2 : chaussées souples en vraie grandeur à 15 et 17,5 bars, avec une partie consacrée à la mécanique du pneu (cartes de pression calculées pour le 1400x530R23 à 32 % de déflexion, §3.4.2, p. 44-50). Lien avec ta thèse : source de la déflexion de 32 % et des cartes sur lesquelles tu lis un rapport Pmax/Pgonflage de 1,7 à 2,1 (valeur non écrite dans les pages lues). Document public ; ta Fig. 1-23 montre des pressions calculées, non mesurées. | AP6: STAC (2011) ; Tielking (1989) | AQ6: Oui | AR6: =IF($B6="","",IFERROR(INDEX(Paramètres!$Q$6:$Q$13,MATCH($G6,Paramètres!$P$6:$P$13,0)),"")) -> Chaussées aéronautiques | AS6: =IF($B6="","",IFERROR(INDEX(Paramètres!$T$6:$T$11,MATCH($I6,Paramètres!$S$6:$S$11,0)),"")) -> octobre 2026 | AT6: =IF($B6="","",IFERROR(INDEX(Paramètres!$C$27:$C$29,MATCH($H6,Paramètres!$B$27:$B$29,0)),0)) -> 6 | AW6: =IF($B6="","",$B6&".md") -> airbus2010htpt.md | AX6: =IF($B6="","",COUNTIF($I$2:I6,$I6)) -> 5 | AY6: =IF($B6="","",$I6&"-"&$AX6) -> 1-5 | AZ6: https://scholar.google.com/scholar?q=%22High+Tire+Pressure+Test+%28HTPT%29+%E2%80%94+Final+report%22 | BA6: =IF($B6="","",$M6+(1000-ROW())/100000) -> 140.00994 | BB6: BIB-005_Airbus_2010_HTPT-final-report.pdf
A7: BIB-006 | B7: petitjean2001pep | C7: =IF($B7="","",IFERROR(LEFT(LEFT($V7,FIND(";",$V7&";")-1),FIND(",",LEFT($V7,FIND(";",$V7&";")-1))-1),LEFT($V7,FIND(";",$V7&";")-1))&IF((LEN($V7)-LEN(SUBSTITUTE($V7,";",""))+1)=1,"",IF((LEN($V7)-LEN(SUBSTITUTE($V7,";",""))+1)=2," & "&IFERROR(LEFT(TRIM(MID($V7,FIND(";",$V7)+1,FIND(";",$V7&";",FIND(";",$V7)+1)-FIND(";",$V7)-1)),FIND(",",TRIM(MID($V7,FIND(";",$V7)+1,FIND(";",$V7&";",FIND(";",$V7)+1)-FIND(";",$V7)-1)))-1),TRIM(MID($V7,FIND(";",$V7)+1,FIND(";",$V7&";",FIND(";",$V7)+1)-FIND(";",$V7)-1)))," et al."))&" ("&$W7&")") -> Petitjean et al. (2001) | D7: LCPC / Airbus / STBA A380 Pavement Experimental Programme | E7: =IF(OR($B7="",$AF7=""),"",HYPERLINK(IF(AND(Paramètres!$C$13<>"",$AJ7="Éditeur (abonnement)"),Paramètres!$C$13&$AF7,$AF7),"Ouvrir : "&$AE7)) -> Ouvrir : Texte intégral libre | F7: Oui | G7: 7 | H7: INCONTOURNABLE | I7: 1 | J7: À lire | K7: =IF($B7="","",IF($J7="Lu","Lu",IF($J7="Écarté","Écarté",IF($I7<Paramètres!$C$8,"EN RETARD",IF($I7=Paramètres!$C$8,"Ce mois-ci",IF($I7=Paramètres!$C$8+1,"Mois prochain","À venir")))))) -> Ce mois-ci | L7: =IF($B7="","",IF($AL7="Non vérifié","Ne pas citer en l'état : métadonnées non vérifiées",IF($AL7="Partiel","Vérification à compléter avant de citer",IF($O7="Oui","",IF(OR($AJ7="PDF libre",$AJ7="PDF libre (dépôt)"),"PDF libre à télécharger",IF($AJ7="Éditeur (abonnement)","À télécharger via l'accès ENTPE",IF($AJ7="Payant (boutique)","À consulter via l'abonnement de l'école",IF($AJ7="Non diffusé (à demander)","Document à demander (feuille Demandes)","Texte intégral à localiser")))))))) | M7: =IF($B7="","",IF(OR($J7="Lu",$J7="Écarté"),0,IFERROR(INDEX(Paramètres!$C$17:$C$19,MATCH($H7,Paramètres!$B$17:$B$19,0)),0)+Paramètres!$C$20*(7-$I7)+IF($I7<Paramètres!$C$8,Paramètres!$C$21,0)+IF($F7="Oui",Paramètres!$C$22,0)+IF($AL7<>"Vérifié",Paramètres!$C$23,0)+IF(AND($O7<>"Oui",OR($AJ7="PDF libre",$AJ7="PDF libre (dépôt)")),Paramètres!$C$24,0))) -> 140 | O7: =IF($BB7="","Non",HYPERLINK(DossierPDF&$BB7,"Oui")) -> Oui | P7: Non | Q7: Non | T7: RPRT | U7: =IF($B7="","",IFERROR(INDEX(Paramètres!$N$6:$N$13,MATCH($T7,Paramètres!$M$6:$M$13,0)),$T7)) -> Rapport | V7: Petitjean, J.; Fabre, C.; Martin, J.; Bezavada, V.; Piau, J.-M.; Balay, J.; Albin, A.; Albin, C. | W7: 2001 | AB7: Airbus Industrie / LCPC / STBA / Aéroports de Paris | AD7: Rapport d'étude STBA, 173 p. | AE7: Texte intégral libre | AF7: https://www.stac.aviation-civile.gouv.fr/sites/default/files/rapportPEP.pdf | AG7: =IF($AC7="","",HYPERLINK("https://doi.org/"&$AC7,"doi.org")) | AH7: =IF($AZ7="","",HYPERLINK($AZ7,"Scholar")) -> Scholar | AI7: Libre | AJ7: PDF libre | AK7: PDF public sur le site du STAC (aussi diffusé par Airbus). | AL7: Vérifié | AM7: Page STAC + page d'auteurs du PDF | AN7: 22/09/2026 | AO7: Programme expérimental A380 sur chaussées souples instrumentées à Toulouse sous simulateur de train d'atterrissage. Lien avec ta thèse : données de validation de ta simulation (déformations en base de couche bitumineuse) et source des modules des couches. | AP7: Airbus S.A.S. (2010) | AQ7: Oui | AR7: =IF($B7="","",IFERROR(INDEX(Paramètres!$Q$6:$Q$13,MATCH($G7,Paramètres!$P$6:$P$13,0)),"")) -> Chaussées aéronautiques | AS7: =IF($B7="","",IFERROR(INDEX(Paramètres!$T$6:$T$11,MATCH($I7,Paramètres!$S$6:$S$11,0)),"")) -> octobre 2026 | AT7: =IF($B7="","",IFERROR(INDEX(Paramètres!$C$27:$C$29,MATCH($H7,Paramètres!$B$27:$B$29,0)),0)) -> 6 | AW7: =IF($B7="","",$B7&".md") -> petitjean2001pep.md | AX7: =IF($B7="","",COUNTIF($I$2:I7,$I7)) -> 6 | AY7: =IF($B7="","",$I7&"-"&$AX7) -> 1-6 | AZ7: https://scholar.google.com/scholar?q=%22LCPC+%2F+Airbus+%2F+STBA+A380+Pavement+Experimental+Programme%22 | BA7: =IF($B7="","",$M7+(1000-ROW())/100000) -> 140.00993 | BB7: BIB-006_Petitjean-etal_2001_A380-pavement-experimental-programme.pdf
A8: BIB-007 | B8: stac2011htpt | C8: =IF($B8="","",IFERROR(LEFT(LEFT($V8,FIND(";",$V8&";")-1),FIND(",",LEFT($V8,FIND(";",$V8&";")-1))-1),LEFT($V8,FIND(";",$V8&";")-1))&IF((LEN($V8)-LEN(SUBSTITUTE($V8,";",""))+1)=1,"",IF((LEN($V8)-LEN(SUBSTITUTE($V8,";",""))+1)=2," & "&IFERROR(LEFT(TRIM(MID($V8,FIND(";",$V8)+1,FIND(";",$V8&";",FIND(";",$V8)+1)-FIND(";",$V8)-1)),FIND(",",TRIM(MID($V8,FIND(";",$V8)+1,FIND(";",$V8&";",FIND(";",$V8)+1)-FIND(";",$V8)-1)))-1),TRIM(MID($V8,FIND(";",$V8)+1,FIND(";",$V8&";",FIND(";",$V8)+1)-FIND(";",$V8)-1)))," et al."))&" ("&$W8&")") -> STAC (2011) | D8: High tire pressure test — Rapport d'étude (version 1) | E8: =IF(OR($B8="",$AF8=""),"",HYPERLINK(IF(AND(Paramètres!$C$13<>"",$AJ8="Éditeur (abonnement)"),Paramètres!$C$13&$AF8,$AF8),"Ouvrir : "&$AE8)) -> Ouvrir : Texte intégral libre | F8: Non | G8: 7 | H8: INCONTOURNABLE | I8: 1 | J8: À lire | K8: =IF($B8="","",IF($J8="Lu","Lu",IF($J8="Écarté","Écarté",IF($I8<Paramètres!$C$8,"EN RETARD",IF($I8=Paramètres!$C$8,"Ce mois-ci",IF($I8=Paramètres!$C$8+1,"Mois prochain","À venir")))))) -> Ce mois-ci | L8: =IF($B8="","",IF($AL8="Non vérifié","Ne pas citer en l'état : métadonnées non vérifiées",IF($AL8="Partiel","Vérification à compléter avant de citer",IF($O8="Oui","",IF(OR($AJ8="PDF libre",$AJ8="PDF libre (dépôt)"),"PDF libre à télécharger",IF($AJ8="Éditeur (abonnement)","À télécharger via l'accès ENTPE",IF($AJ8="Payant (boutique)","À consulter via l'abonnement de l'école",IF($AJ8="Non diffusé (à demander)","Document à demander (feuille Demandes)","Texte intégral à localiser")))))))) | M8: =IF($B8="","",IF(OR($J8="Lu",$J8="Écarté"),0,IFERROR(INDEX(Paramètres!$C$17:$C$19,MATCH($H8,Paramètres!$B$17:$B$19,0)),0)+Paramètres!$C$20*(7-$I8)+IF($I8<Paramètres!$C$8,Paramètres!$C$21,0)+IF($F8="Oui",Paramètres!$C$22,0)+IF($AL8<>"Vérifié",Paramètres!$C$23,0)+IF(AND($O8<>"Oui",OR($AJ8="PDF libre",$AJ8="PDF libre (dépôt)")),Paramètres!$C$24,0))) -> 130 | O8: =IF($BB8="","Non",HYPERLINK(DossierPDF&$BB8,"Oui")) -> Oui | P8: Non | Q8: Non | T8: RPRT | U8: =IF($B8="","",IFERROR(INDEX(Paramètres!$N$6:$N$13,MATCH($T8,Paramètres!$M$6:$M$13,0)),$T8)) -> Rapport | V8: STAC | W8: 2011 | AB8: DGAC, Service technique de l'Aviation civile | AD8: Rapport d'étude STAC, 120 p. | AE8: Texte intégral libre | AF8: https://www.stac.aviation-civile.gouv.fr/en/publications/high-tire-pressure-test | AG8: =IF($AC8="","",HYPERLINK("https://doi.org/"&$AC8,"doi.org")) | AH8: =IF($AZ8="","",HYPERLINK($AZ8,"Scholar")) -> Scholar | AI8: Libre | AJ8: PDF libre | AK8: Lecture en ligne gratuite depuis la page du STAC (liseuse Calaméo). | AL8: Vérifié | AM8: Page de publication du STAC | AN8: 22/09/2026 | AO8: Version STAC de la campagne HTPT à Toulouse-Blagnac : sept sections souples, pressions de 15 et 17,5 bars, charges de 28,7 et 33,2 t par roue, mesures de déformations et d'orniérage. Lien avec ta thèse : complément public du rapport Airbus, côté partenaire ; une version 2 était annoncée. | AP8: Airbus S.A.S. (2010) | AQ8: Oui | AR8: =IF($B8="","",IFERROR(INDEX(Paramètres!$Q$6:$Q$13,MATCH($G8,Paramètres!$P$6:$P$13,0)),"")) -> Chaussées aéronautiques | AS8: =IF($B8="","",IFERROR(INDEX(Paramètres!$T$6:$T$11,MATCH($I8,Paramètres!$S$6:$S$11,0)),"")) -> octobre 2026 | AT8: =IF($B8="","",IFERROR(INDEX(Paramètres!$C$27:$C$29,MATCH($H8,Paramètres!$B$27:$B$29,0)),0)) -> 6 | AW8: =IF($B8="","",$B8&".md") -> stac2011htpt.md | AX8: =IF($B8="","",COUNTIF($I$2:I8,$I8)) -> 7 | AY8: =IF($B8="","",$I8&"-"&$AX8) -> 1-7 | AZ8: https://scholar.google.com/scholar?q=%22High+tire+pressure+test+%E2%80%94+Rapport+d%27%C3%A9tude+%28version+1%29%22 | BA8: =IF($B8="","",$M8+(1000-ROW())/100000) -> 130.00992 | BB8: BIB-007_STAC_2011_High-tire-pressure-test-rapport-etude.pdf
A9: BIB-008 | B9: debeer2000cr99012 | C9: =IF($B9="","",IFERROR(LEFT(LEFT($V9,FIND(";",$V9&";")-1),FIND(",",LEFT($V9,FIND(";",$V9&";")-1))-1),LEFT($V9,FIND(";",$V9&";")-1))&IF((LEN($V9)-LEN(SUBSTITUTE($V9,";",""))+1)=1,"",IF((LEN($V9)-LEN(SUBSTITUTE($V9,";",""))+1)=2," & "&IFERROR(LEFT(TRIM(MID($V9,FIND(";",$V9)+1,FIND(";",$V9&";",FIND(";",$V9)+1)-FIND(";",$V9)-1)),FIND(",",TRIM(MID($V9,FIND(";",$V9)+1,FIND(";",$V9&";",FIND(";",$V9)+1)-FIND(";",$V9)-1)))-1),TRIM(MID($V9,FIND(";",$V9)+1,FIND(";",$V9&";",FIND(";",$V9)+1)-FIND(";",$V9)-1)))," et al."))&" ("&$W9&")") -> De Beer & Fisher (2000) | D9: Contact stresses of the 11.00-R22.5 pneumatic radial tyres on the Gautrans Heavy Vehicle Simulator (HVS) measured with the Vehicle-Road Pressure Transducer Array (VRSPTA) system | E9: =IF(OR($B9="",$AF9=""),"",HYPERLINK(IF(AND(Paramètres!$C$13<>"",$AJ9="Éditeur (abonnement)"),Paramètres!$C$13&$AF9,$AF9),"Ouvrir : "&$AE9)) -> Ouvrir : Recherche Google Scholar | F9: Oui | G9: 1 | H9: Important | I9: 1 | J9: À lire | K9: =IF($B9="","",IF($J9="Lu","Lu",IF($J9="Écarté","Écarté",IF($I9<Paramètres!$C$8,"EN RETARD",IF($I9=Paramètres!$C$8,"Ce mois-ci",IF($I9=Paramètres!$C$8+1,"Mois prochain","À venir")))))) -> Ce mois-ci | L9: =IF($B9="","",IF($AL9="Non vérifié","Ne pas citer en l'état : métadonnées non vérifiées",IF($AL9="Partiel","Vérification à compléter avant de citer",IF($O9="Oui","",IF(OR($AJ9="PDF libre",$AJ9="PDF libre (dépôt)"),"PDF libre à télécharger",IF($AJ9="Éditeur (abonnement)","À télécharger via l'accès ENTPE",IF($AJ9="Payant (boutique)","À consulter via l'abonnement de l'école",IF($AJ9="Non diffusé (à demander)","Document à demander (feuille Demandes)","Texte intégral à localiser")))))))) -> Ne pas citer en l'état : métadonnées non vérifiées | M9: =IF($B9="","",IF(OR($J9="Lu",$J9="Écarté"),0,IFERROR(INDEX(Paramètres!$C$17:$C$19,MATCH($H9,Paramètres!$B$17:$B$19,0)),0)+Paramètres!$C$20*(7-$I9)+IF($I9<Paramètres!$C$8,Paramètres!$C$21,0)+IF($F9="Oui",Paramètres!$C$22,0)+IF($AL9<>"Vérifié",Paramètres!$C$23,0)+IF(AND($O9<>"Oui",OR($AJ9="PDF libre",$AJ9="PDF libre (dépôt)")),Paramètres!$C$24,0))) -> 115 | O9: =IF($BB9="","Non",HYPERLINK(DossierPDF&$BB9,"Oui")) -> Non | P9: Non | Q9: Non | T9: RPRT | U9: =IF($B9="","",IFERROR(INDEX(Paramètres!$N$6:$N$13,MATCH($T9,Paramètres!$M$6:$M$13,0)),$T9)) -> Rapport | V9: De Beer, M.; Fisher, C. | W9: 2000 | AB9: CSIR Transportek | AD9: Confidential Contract Report CR-99/012 | AE9: Recherche Google Scholar | AF9: https://scholar.google.com/scholar?q=%22Contact+stresses+of+the+11.00-R22.5+pneumatic+radial+tyres+on+the+Gautrans+Heavy+Vehicle+Simulator+%28HVS%29+measured+with+the+Vehicle-Road+Pressure+Transducer+Array+%28VRSPTA%29+system%22 | AG9: =IF($AC9="","",HYPERLINK("https://doi.org/"&$AC9,"doi.org")) | AH9: =IF($AZ9="","",HYPERLINK($AZ9,"Scholar")) -> Scholar | AI9: Restreint | AJ9: Non diffusé (à demander) | AK9: Rapport confidentiel du CSIR : retrouver la copie utilisée pour le TFE (LTDS), sinon demander au STAC. | AL9: Non vérifié | AM9: Citation du rapport par ses auteurs (De Beer, Fisher & Kannemeyer 2004, CSIR ResearchSpace) | AN9: 22/09/2026 | AO9: Matrice charge × pression de gonflage mesurée au VRSPTA sur le simulateur HVS de Gautrans pour des pneus radiaux de camion. Lien avec ta thèse : source directe de ton empreinte hétérogène (Fig. 1-22, 3-6 et annexe II). NON VÉRIFIÉ : rapport à diffusion restreinte, jamais consulté sur source primaire ; titre, numéro et date (mars 2000) relevés dans une citation des auteurs. La désignation du pneu (11.00-R22.5) diffère de celle de ton texte (11R22.5). | AP9: De Beer et al. (2004) ; De Beer et al. (2002) | AQ9: Oui | AR9: =IF($B9="","",IFERROR(INDEX(Paramètres!$Q$6:$Q$13,MATCH($G9,Paramètres!$P$6:$P$13,0)),"")) -> Mesure de la pression de contact pneu-chaussée | AS9: =IF($B9="","",IFERROR(INDEX(Paramètres!$T$6:$T$11,MATCH($I9,Paramètres!$S$6:$S$11,0)),"")) -> octobre 2026 | AT9: =IF($B9="","",IFERROR(INDEX(Paramètres!$C$27:$C$29,MATCH($H9,Paramètres!$B$27:$B$29,0)),0)) -> 3 | AW9: =IF($B9="","",$B9&".md") -> debeer2000cr99012.md | AX9: =IF($B9="","",COUNTIF($I$2:I9,$I9)) -> 8 | AY9: =IF($B9="","",$I9&"-"&$AX9) -> 1-8 | AZ9: https://scholar.google.com/scholar?q=%22Contact+stresses+of+the+11.00-R22.5+pneumatic+radial+tyres+on+the+Gautrans+Heavy+Vehicle+Simulator+%28HVS%29+measured+with+the+Vehicle-Road+Pressure+Transducer+Array+%28VRSPTA%29+system%22 | BA9: =IF($B9="","",$M9+(1000-ROW())/100000) -> 115.00991
A10: BIB-009 | B10: debeer2004hvtt | C10: =IF($B10="","",IFERROR(LEFT(LEFT($V10,FIND(";",$V10&";")-1),FIND(",",LEFT($V10,FIND(";",$V10&";")-1))-1),LEFT($V10,FIND(";",$V10&";")-1))&IF((LEN($V10)-LEN(SUBSTITUTE($V10,";",""))+1)=1,"",IF((LEN($V10)-LEN(SUBSTITUTE($V10,";",""))+1)=2," & "&IFERROR(LEFT(TRIM(MID($V10,FIND(";",$V10)+1,FIND(";",$V10&";",FIND(";",$V10)+1)-FIND(";",$V10)-1)),FIND(",",TRIM(MID($V10,FIND(";",$V10)+1,FIND(";",$V10&";",FIND(";",$V10)+1)-FIND(";",$V10)-1)))-1),TRIM(MID($V10,FIND(";",$V10)+1,FIND(";",$V10&";",FIND(";",$V10)+1)-FIND(";",$V10)-1)))," et al."))&" ("&$W10&")") -> De Beer et al. (2004) | D10: Towards the application of Stress-In-Motion (SIM) results in pavement design and infrastructure protection | E10: =IF(OR($B10="",$AF10=""),"",HYPERLINK(IF(AND(Paramètres!$C$13<>"",$AJ10="Éditeur (abonnement)"),Paramètres!$C$13&$AF10,$AF10),"Ouvrir : "&$AE10)) -> Ouvrir : Texte intégral (dépôt) | F10: Non | G10: 1 | H10: Important | I10: 1 | J10: À lire | K10: =IF($B10="","",IF($J10="Lu","Lu",IF($J10="Écarté","Écarté",IF($I10<Paramètres!$C$8,"EN RETARD",IF($I10=Paramètres!$C$8,"Ce mois-ci",IF($I10=Paramètres!$C$8+1,"Mois prochain","À venir")))))) -> Ce mois-ci | L10: =IF($B10="","",IF($AL10="Non vérifié","Ne pas citer en l'état : métadonnées non vérifiées",IF($AL10="Partiel","Vérification à compléter avant de citer",IF($O10="Oui","",IF(OR($AJ10="PDF libre",$AJ10="PDF libre (dépôt)"),"PDF libre à télécharger",IF($AJ10="Éditeur (abonnement)","À télécharger via l'accès ENTPE",IF($AJ10="Payant (boutique)","À consulter via l'abonnement de l'école",IF($AJ10="Non diffusé (à demander)","Document à demander (feuille Demandes)","Texte intégral à localiser")))))))) | M10: =IF($B10="","",IF(OR($J10="Lu",$J10="Écarté"),0,IFERROR(INDEX(Paramètres!$C$17:$C$19,MATCH($H10,Paramètres!$B$17:$B$19,0)),0)+Paramètres!$C$20*(7-$I10)+IF($I10<Paramètres!$C$8,Paramètres!$C$21,0)+IF($F10="Oui",Paramètres!$C$22,0)+IF($AL10<>"Vérifié",Paramètres!$C$23,0)+IF(AND($O10<>"Oui",OR($AJ10="PDF libre",$AJ10="PDF libre (dépôt)")),Paramètres!$C$24,0))) -> 90 | O10: =IF($BB10="","Non",HYPERLINK(DossierPDF&$BB10,"Oui")) -> Oui | P10: Non | Q10: Non | T10: CONF | U10: =IF($B10="","",IFERROR(INDEX(Paramètres!$N$6:$N$13,MATCH($T10,Paramètres!$M$6:$M$13,0)),$T10)) -> Communication (actes) | V10: De Beer, M.; Fisher, C.; Kannemeyer, L. | W10: 2004 | X10: 8th International Symposium on Heavy Vehicle Weights and Dimensions, Johannesburg, 14-18 March 2004 | AD10: CSIR ResearchSpace | AE10: Texte intégral (dépôt) | AF10: https://researchspace.csir.co.za/server/api/core/bitstreams/78155ecc-6d57-4492-a4dc-e32e2d93602a/content | AG10: =IF($AC10="","",HYPERLINK("https://doi.org/"&$AC10,"doi.org")) | AH10: =IF($AZ10="","",HYPERLINK($AZ10,"Scholar")) -> Scholar | AI10: Libre | AJ10: PDF libre (dépôt) | AK10: PDF en libre accès sur le dépôt institutionnel du CSIR. | AL10: Vérifié | AM10: PDF du dépôt CSIR (page de titre et références) | AN10: 22/09/2026 | AO10: Synthèse des résultats SIM et de leur usage en dimensionnement : formes de distribution selon la charge et le gonflage, contrainte de contact normalisée par la pression de gonflage. Lien avec ta thèse : meilleure entrée gratuite sur le passage du profil en n au profil en M, et sa liste de références cite précisément le rapport CR-99/012. | AP10: De Beer & Fisher (2000) ; De Beer et al. (2012) | AQ10: Oui | AR10: =IF($B10="","",IFERROR(INDEX(Paramètres!$Q$6:$Q$13,MATCH($G10,Paramètres!$P$6:$P$13,0)),"")) -> Mesure de la pression de contact pneu-chaussée | AS10: =IF($B10="","",IFERROR(INDEX(Paramètres!$T$6:$T$11,MATCH($I10,Paramètres!$S$6:$S$11,0)),"")) -> octobre 2026 | AT10: =IF($B10="","",IFERROR(INDEX(Paramètres!$C$27:$C$29,MATCH($H10,Paramètres!$B$27:$B$29,0)),0)) -> 3 | AW10: =IF($B10="","",$B10&".md") -> debeer2004hvtt.md | AX10: =IF($B10="","",COUNTIF($I$2:I10,$I10)) -> 9 | AY10: =IF($B10="","",$I10&"-"&$AX10) -> 1-9 | AZ10: https://scholar.google.com/scholar?q=%22Towards+the+application+of+Stress-In-Motion+%28SIM%29+results+in+pavement+design+and+infrastructure+protection%22 | BA10: =IF($B10="","",$M10+(1000-ROW())/100000) -> 90.0099 | BB10: BIB-009_DeBeer-etal_2004_Application-SIM-pavement-design.pdf
A11: BIB-010 | B11: gong2024review | C11: =IF($B11="","",IFERROR(LEFT(LEFT($V11,FIND(";",$V11&";")-1),FIND(",",LEFT($V11,FIND(";",$V11&";")-1))-1),LEFT($V11,FIND(";",$V11&";")-1))&IF((LEN($V11)-LEN(SUBSTITUTE($V11,";",""))+1)=1,"",IF((LEN($V11)-LEN(SUBSTITUTE($V11,";",""))+1)=2," & "&IFERROR(LEFT(TRIM(MID($V11,FIND(";",$V11)+1,FIND(";",$V11&";",FIND(";",$V11)+1)-FIND(";",$V11)-1)),FIND(",",TRIM(MID($V11,FIND(";",$V11)+1,FIND(";",$V11&";",FIND(";",$V11)+1)-FIND(";",$V11)-1)))-1),TRIM(MID($V11,FIND(";",$V11)+1,FIND(";",$V11&";",FIND(";",$V11)+1)-FIND(";",$V11)-1)))," et al."))&" ("&$W11&")") -> Gong et al. (2024) | D11: Review of research on tire–pavement contact behavior | E11: =IF(OR($B11="",$AF11=""),"",HYPERLINK(IF(AND(Paramètres!$C$13<>"",$AJ11="Éditeur (abonnement)"),Paramètres!$C$13&$AF11,$AF11),"Ouvrir : "&$AE11)) -> Ouvrir : Texte intégral libre | F11: Oui | G11: 1 | H11: Important | I11: 1 | J11: À lire | K11: =IF($B11="","",IF($J11="Lu","Lu",IF($J11="Écarté","Écarté",IF($I11<Paramètres!$C$8,"EN RETARD",IF($I11=Paramètres!$C$8,"Ce mois-ci",IF($I11=Paramètres!$C$8+1,"Mois prochain","À venir")))))) -> Ce mois-ci | L11: =IF($B11="","",IF($AL11="Non vérifié","Ne pas citer en l'état : métadonnées non vérifiées",IF($AL11="Partiel","Vérification à compléter avant de citer",IF($O11="Oui","",IF(OR($AJ11="PDF libre",$AJ11="PDF libre (dépôt)"),"PDF libre à télécharger",IF($AJ11="Éditeur (abonnement)","À télécharger via l'accès ENTPE",IF($AJ11="Payant (boutique)","À consulter via l'abonnement de l'école",IF($AJ11="Non diffusé (à demander)","Document à demander (feuille Demandes)","Texte intégral à localiser")))))))) | M11: =IF($B11="","",IF(OR($J11="Lu",$J11="Écarté"),0,IFERROR(INDEX(Paramètres!$C$17:$C$19,MATCH($H11,Paramètres!$B$17:$B$19,0)),0)+Paramètres!$C$20*(7-$I11)+IF($I11<Paramètres!$C$8,Paramètres!$C$21,0)+IF($F11="Oui",Paramètres!$C$22,0)+IF($AL11<>"Vérifié",Paramètres!$C$23,0)+IF(AND($O11<>"Oui",OR($AJ11="PDF libre",$AJ11="PDF libre (dépôt)")),Paramètres!$C$24,0))) -> 100 | O11: =IF($BB11="","Non",HYPERLINK(DossierPDF&$BB11,"Oui")) -> Oui | P11: Non | Q11: Non | T11: JOUR | U11: =IF($B11="","",IFERROR(INDEX(Paramètres!$N$6:$N$13,MATCH($T11,Paramètres!$M$6:$M$13,0)),$T11)) -> Article de revue | V11: Gong, Z.; Miao, Y.; Lantieri, C. | W11: 2024 | X11: Coatings | Y11: 14 | Z11: 2 | AA11: 157 | AC11: 10.3390/coatings14020157 | AE11: Texte intégral libre | AF11: https://www.mdpi.com/2079-6412/14/2/157/pdf?version=1706522583 | AG11: =IF($AC11="","",HYPERLINK("https://doi.org/"&$AC11,"doi.org")) -> doi.org | AH11: =IF($AZ11="","",HYPERLINK($AZ11,"Scholar")) -> Scholar | AI11: Libre | AJ11: PDF libre | AK11: Article en libre accès (MDPI, CC BY). | AL11: Vérifié | AM11: Page MDPI | AN11: 22/09/2026 | AO11: Revue des travaux sur le contact pneu-chaussée : géométrie de l'empreinte, méthodes de mesure, modèles. Lien avec ta thèse : base de ton §1.3.5, et bonne carte du domaine pour la thèse. | AQ11: Non | AR11: =IF($B11="","",IFERROR(INDEX(Paramètres!$Q$6:$Q$13,MATCH($G11,Paramètres!$P$6:$P$13,0)),"")) -> Mesure de la pression de contact pneu-chaussée | AS11: =IF($B11="","",IFERROR(INDEX(Paramètres!$T$6:$T$11,MATCH($I11,Paramètres!$S$6:$S$11,0)),"")) -> octobre 2026 | AT11: =IF($B11="","",IFERROR(INDEX(Paramètres!$C$27:$C$29,MATCH($H11,Paramètres!$B$27:$B$29,0)),0)) -> 3 | AW11: =IF($B11="","",$B11&".md") -> gong2024review.md | AX11: =IF($B11="","",COUNTIF($I$2:I11,$I11)) -> 10 | AY11: =IF($B11="","",$I11&"-"&$AX11) -> 1-10 | AZ11: https://scholar.google.com/scholar?q=%22Review+of+research+on+tire%E2%80%93pavement+contact+behavior%22 | BA11: =IF($B11="","",$M11+(1000-ROW())/100000) -> 100.00989 | BB11: BIB-010_Gong-etal_2024_Review-tire-pavement-contact.pdf
A12: BIB-011 | B12: hansen1989truck | C12: =IF($B12="","",IFERROR(LEFT(LEFT($V12,FIND(";",$V12&";")-1),FIND(",",LEFT($V12,FIND(";",$V12&";")-1))-1),LEFT($V12,FIND(";",$V12&";")-1))&IF((LEN($V12)-LEN(SUBSTITUTE($V12,";",""))+1)=1,"",IF((LEN($V12)-LEN(SUBSTITUTE($V12,";",""))+1)=2," & "&IFERROR(LEFT(TRIM(MID($V12,FIND(";",$V12)+1,FIND(";",$V12&";",FIND(";",$V12)+1)-FIND(";",$V12)-1)),FIND(",",TRIM(MID($V12,FIND(";",$V12)+1,FIND(";",$V12&";",FIND(";",$V12)+1)-FIND(";",$V12)-1)))-1),TRIM(MID($V12,FIND(";",$V12)+1,FIND(";",$V12&";",FIND(";",$V12)+1)-FIND(";",$V12)-1)))," et al."))&" ("&$W12&")") -> Hansen et al. (1989) | D12: Truck tire pavement contact pressure distribution characteristics for super single 18-22.5 and smooth 11R24.5 tires | E12: =IF(OR($B12="",$AF12=""),"",HYPERLINK(IF(AND(Paramètres!$C$13<>"",$AJ12="Éditeur (abonnement)"),Paramètres!$C$13&$AF12,$AF12),"Ouvrir : "&$AE12)) -> Ouvrir : Texte intégral libre | F12: Oui | G12: 1 | H12: Important | I12: 1 | J12: À lire | K12: =IF($B12="","",IF($J12="Lu","Lu",IF($J12="Écarté","Écarté",IF($I12<Paramètres!$C$8,"EN RETARD",IF($I12=Paramètres!$C$8,"Ce mois-ci",IF($I12=Paramètres!$C$8+1,"Mois prochain","À venir")))))) -> Ce mois-ci | L12: =IF($B12="","",IF($AL12="Non vérifié","Ne pas citer en l'état : métadonnées non vérifiées",IF($AL12="Partiel","Vérification à compléter avant de citer",IF($O12="Oui","",IF(OR($AJ12="PDF libre",$AJ12="PDF libre (dépôt)"),"PDF libre à télécharger",IF($AJ12="Éditeur (abonnement)","À télécharger via l'accès ENTPE",IF($AJ12="Payant (boutique)","À consulter via l'abonnement de l'école",IF($AJ12="Non diffusé (à demander)","Document à demander (feuille Demandes)","Texte intégral à localiser")))))))) | M12: =IF($B12="","",IF(OR($J12="Lu",$J12="Écarté"),0,IFERROR(INDEX(Paramètres!$C$17:$C$19,MATCH($H12,Paramètres!$B$17:$B$19,0)),0)+Paramètres!$C$20*(7-$I12)+IF($I12<Paramètres!$C$8,Paramètres!$C$21,0)+IF($F12="Oui",Paramètres!$C$22,0)+IF($AL12<>"Vérifié",Paramètres!$C$23,0)+IF(AND($O12<>"Oui",OR($AJ12="PDF libre",$AJ12="PDF libre (dépôt)")),Paramètres!$C$24,0))) -> 100 | O12: =IF($BB12="","Non",HYPERLINK(DossierPDF&$BB12,"Oui")) -> Oui | P12: Non | Q12: Non | T12: RPRT | U12: =IF($B12="","",IFERROR(INDEX(Paramètres!$N$6:$N$13,MATCH($T12,Paramètres!$M$6:$M$13,0)),$T12)) -> Rapport | V12: Hansen, R. W.; Bertrand, C.; Marshek, K. M.; Hudson, W. R. | W12: 1989 | AB12: Center for Transportation Research, The University of Texas at Austin | AD12: Research Report 1190-1 (FHWA/TX-90+1190-1), 88 p. | AE12: Texte intégral libre | AF12: https://library.ctr.utexas.edu/digitized/texasarchive/phase2/1190-1.pdf | AG12: =IF($AC12="","",HYPERLINK("https://doi.org/"&$AC12,"doi.org")) | AH12: =IF($AZ12="","",HYPERLINK($AZ12,"Scholar")) -> Scholar | AI12: Libre | AJ12: PDF libre | AK12: PDF numérisé en libre accès par la bibliothèque du CTR. | AL12: Vérifié | AM12: Notice TRID 310697 + lien CTR | AN12: 22/09/2026 | AO12: Mesures de distribution de pression de contact sous pneus de camion (super single et pneu lisse), en fonction de la charge et du gonflage. Lien avec ta thèse : jeu de données historique cité avec De Beer (1997) pour établir l'hétérogénéité ; ajouter W. R. Hudson et le numéro de rapport. | AP12: Tielking & Roberts (1987) | AQ12: Oui | AR12: =IF($B12="","",IFERROR(INDEX(Paramètres!$Q$6:$Q$13,MATCH($G12,Paramètres!$P$6:$P$13,0)),"")) -> Mesure de la pression de contact pneu-chaussée | AS12: =IF($B12="","",IFERROR(INDEX(Paramètres!$T$6:$T$11,MATCH($I12,Paramètres!$S$6:$S$11,0)),"")) -> octobre 2026 | AT12: =IF($B12="","",IFERROR(INDEX(Paramètres!$C$27:$C$29,MATCH($H12,Paramètres!$B$27:$B$29,0)),0)) -> 3 | AW12: =IF($B12="","",$B12&".md") -> hansen1989truck.md | AX12: =IF($B12="","",COUNTIF($I$2:I12,$I12)) -> 11 | AY12: =IF($B12="","",$I12&"-"&$AX12) -> 1-11 | AZ12: https://scholar.google.com/scholar?q=%22Truck+tire+pavement+contact+pressure+distribution+characteristics+for+super+single+18-22.5+and+smooth+11R24.5+tires%22 | BA12: =IF($B12="","",$M12+(1000-ROW())/100000) -> 100.00988 | BB12: BIB-011_Hansen-etal_1989_Truck-tire-contact-pressure-super-single.pdf
A13: BIB-012 | B13: tielking1987roberts | C13: =IF($B13="","",IFERROR(LEFT(LEFT($V13,FIND(";",$V13&";")-1),FIND(",",LEFT($V13,FIND(";",$V13&";")-1))-1),LEFT($V13,FIND(";",$V13&";")-1))&IF((LEN($V13)-LEN(SUBSTITUTE($V13,";",""))+1)=1,"",IF((LEN($V13)-LEN(SUBSTITUTE($V13,";",""))+1)=2," & "&IFERROR(LEFT(TRIM(MID($V13,FIND(";",$V13)+1,FIND(";",$V13&";",FIND(";",$V13)+1)-FIND(";",$V13)-1)),FIND(",",TRIM(MID($V13,FIND(";",$V13)+1,FIND(";",$V13&";",FIND(";",$V13)+1)-FIND(";",$V13)-1)))-1),TRIM(MID($V13,FIND(";",$V13)+1,FIND(";",$V13&";",FIND(";",$V13)+1)-FIND(";",$V13)-1)))," et al."))&" ("&$W13&")") -> Tielking & Roberts (1987) | D13: Tire contact pressure and its effect on pavement strain | E13: =IF(OR($B13="",$AF13=""),"",HYPERLINK(IF(AND(Paramètres!$C$13<>"",$AJ13="Éditeur (abonnement)"),Paramètres!$C$13&$AF13,$AF13),"Ouvrir : "&$AE13)) -> Ouvrir : Page éditeur (DOI) | F13: Non | G13: 1 | H13: Important | I13: 1 | J13: À lire | K13: =IF($B13="","",IF($J13="Lu","Lu",IF($J13="Écarté","Écarté",IF($I13<Paramètres!$C$8,"EN RETARD",IF($I13=Paramètres!$C$8,"Ce mois-ci",IF($I13=Paramètres!$C$8+1,"Mois prochain","À venir")))))) -> Ce mois-ci | L13: =IF($B13="","",IF($AL13="Non vérifié","Ne pas citer en l'état : métadonnées non vérifiées",IF($AL13="Partiel","Vérification à compléter avant de citer",IF($O13="Oui","",IF(OR($AJ13="PDF libre",$AJ13="PDF libre (dépôt)"),"PDF libre à télécharger",IF($AJ13="Éditeur (abonnement)","À télécharger via l'accès ENTPE",IF($AJ13="Payant (boutique)","À consulter via l'abonnement de l'école",IF($AJ13="Non diffusé (à demander)","Document à demander (feuille Demandes)","Texte intégral à localiser")))))))) | M13: =IF($B13="","",IF(OR($J13="Lu",$J13="Écarté"),0,IFERROR(INDEX(Paramètres!$C$17:$C$19,MATCH($H13,Paramètres!$B$17:$B$19,0)),0)+Paramètres!$C$20*(7-$I13)+IF($I13<Paramètres!$C$8,Paramètres!$C$21,0)+IF($F13="Oui",Paramètres!$C$22,0)+IF($AL13<>"Vérifié",Paramètres!$C$23,0)+IF(AND($O13<>"Oui",OR($AJ13="PDF libre",$AJ13="PDF libre (dépôt)")),Paramètres!$C$24,0))) -> 90 | O13: =IF($BB13="","Non",HYPERLINK(DossierPDF&$BB13,"Oui")) -> Oui | P13: Non | Q13: Non | T13: JOUR | U13: =IF($B13="","",IFERROR(INDEX(Paramètres!$N$6:$N$13,MATCH($T13,Paramètres!$M$6:$M$13,0)),$T13)) -> Article de revue | V13: Tielking, J. T.; Roberts, F. L. | W13: 1987 | X13: Journal of Transportation Engineering | Y13: 113 | Z13: 1 | AA13: 56-71 | AC13: 10.1061/(ASCE)0733-947X(1987)113:1(56) | AE13: Page éditeur (DOI) | AF13: https://doi.org/10.1061/(ASCE)0733-947X(1987)113:1(56) | AG13: =IF($AC13="","",HYPERLINK("https://doi.org/"&$AC13,"doi.org")) -> doi.org | AH13: =IF($AZ13="","",HYPERLINK($AZ13,"Scholar")) -> Scholar | AI13: Payant | AJ13: Éditeur (abonnement) | AK13: ASCE Library : accès par l'abonnement de l'ENTPE. | AL13: Vérifié | AM13: OpenAlex (DOI) | AN13: 22/09/2026 | AO13: Modèle éléments finis de pneu calculant la pression de contact, puis son effet sur les déformations de la chaussée. Lien avec ta thèse : référence classique du lien entre forme de la pression de contact et déformations près de la surface ; elle fonde les « paramètres de profil » de Tielking. | AP13: Tielking (1989) | AQ13: Non | AR13: =IF($B13="","",IFERROR(INDEX(Paramètres!$Q$6:$Q$13,MATCH($G13,Paramètres!$P$6:$P$13,0)),"")) -> Mesure de la pression de contact pneu-chaussée | AS13: =IF($B13="","",IFERROR(INDEX(Paramètres!$T$6:$T$11,MATCH($I13,Paramètres!$S$6:$S$11,0)),"")) -> octobre 2026 | AT13: =IF($B13="","",IFERROR(INDEX(Paramètres!$C$27:$C$29,MATCH($H13,Paramètres!$B$27:$B$29,0)),0)) -> 3 | AW13: =IF($B13="","",$B13&".md") -> tielking1987roberts.md | AX13: =IF($B13="","",COUNTIF($I$2:I13,$I13)) -> 12 | AY13: =IF($B13="","",$I13&"-"&$AX13) -> 1-12 | AZ13: https://scholar.google.com/scholar?q=%22Tire+contact+pressure+and+its+effect+on+pavement+strain%22 | BA13: =IF($B13="","",$M13+(1000-ROW())/100000) -> 90.00987 | BB13: BIB-012_Tielking-Roberts_1987_Tire-contact-pressure-pavement-strain.pdf
A14: BIB-013 | B14: guan2023triaxial | C14: =IF($B14="","",IFERROR(LEFT(LEFT($V14,FIND(";",$V14&";")-1),FIND(",",LEFT($V14,FIND(";",$V14&";")-1))-1),LEFT($V14,FIND(";",$V14&";")-1))&IF((LEN($V14)-LEN(SUBSTITUTE($V14,";",""))+1)=1,"",IF((LEN($V14)-LEN(SUBSTITUTE($V14,";",""))+1)=2," & "&IFERROR(LEFT(TRIM(MID($V14,FIND(";",$V14)+1,FIND(";",$V14&";",FIND(";",$V14)+1)-FIND(";",$V14)-1)),FIND(",",TRIM(MID($V14,FIND(";",$V14)+1,FIND(";",$V14&";",FIND(";",$V14)+1)-FIND(";",$V14)-1)))-1),TRIM(MID($V14,FIND(";",$V14)+1,FIND(";",$V14&";",FIND(";",$V14)+1)-FIND(";",$V14)-1)))," et al."))&" ("&$W14&")") -> Guan et al. (2023) | D14: Measurement of tire-pavement contact tri-axial stress distribution based on sensor array | E14: =IF(OR($B14="",$AF14=""),"",HYPERLINK(IF(AND(Paramètres!$C$13<>"",$AJ14="Éditeur (abonnement)"),Paramètres!$C$13&$AF14,$AF14),"Ouvrir : "&$AE14)) -> Ouvrir : Texte intégral libre | F14: Non | G14: 1 | H14: A consulter | I14: 1 | J14: À lire | K14: =IF($B14="","",IF($J14="Lu","Lu",IF($J14="Écarté","Écarté",IF($I14<Paramètres!$C$8,"EN RETARD",IF($I14=Paramètres!$C$8,"Ce mois-ci",IF($I14=Paramètres!$C$8+1,"Mois prochain","À venir")))))) -> Ce mois-ci | L14: =IF($B14="","",IF($AL14="Non vérifié","Ne pas citer en l'état : métadonnées non vérifiées",IF($AL14="Partiel","Vérification à compléter avant de citer",IF($O14="Oui","",IF(OR($AJ14="PDF libre",$AJ14="PDF libre (dépôt)"),"PDF libre à télécharger",IF($AJ14="Éditeur (abonnement)","À télécharger via l'accès ENTPE",IF($AJ14="Payant (boutique)","À consulter via l'abonnement de l'école",IF($AJ14="Non diffusé (à demander)","Document à demander (feuille Demandes)","Texte intégral à localiser")))))))) | M14: =IF($B14="","",IF(OR($J14="Lu",$J14="Écarté"),0,IFERROR(INDEX(Paramètres!$C$17:$C$19,MATCH($H14,Paramètres!$B$17:$B$19,0)),0)+Paramètres!$C$20*(7-$I14)+IF($I14<Paramètres!$C$8,Paramètres!$C$21,0)+IF($F14="Oui",Paramètres!$C$22,0)+IF($AL14<>"Vérifié",Paramètres!$C$23,0)+IF(AND($O14<>"Oui",OR($AJ14="PDF libre",$AJ14="PDF libre (dépôt)")),Paramètres!$C$24,0))) -> 60 | O14: =IF($BB14="","Non",HYPERLINK(DossierPDF&$BB14,"Oui")) -> Oui | P14: Non | Q14: Non | T14: JOUR | U14: =IF($B14="","",IFERROR(INDEX(Paramètres!$N$6:$N$13,MATCH($T14,Paramètres!$M$6:$M$13,0)),$T14)) -> Article de revue | V14: Guan, J.; Zhou, X.; Liu, L.; Ran, M. | W14: 2023 | X14: Coatings | Y14: 13 | Z14: 2 | AA14: 416 | AC14: 10.3390/coatings13020416 | AE14: Texte intégral libre | AF14: https://www.mdpi.com/2079-6412/13/2/416/pdf?version=1676191118 | AG14: =IF($AC14="","",HYPERLINK("https://doi.org/"&$AC14,"doi.org")) -> doi.org | AH14: =IF($AZ14="","",HYPERLINK($AZ14,"Scholar")) -> Scholar | AI14: Libre | AJ14: PDF libre | AK14: Article en libre accès (MDPI). | AL14: Vérifié | AM14: OpenAlex (DOI) | AN14: 22/09/2026 | AO14: Mesure des contraintes de contact dans les trois directions par un réseau de capteurs. Lien avec ta thèse : dispositif récent de la famille SIM, utile pour concevoir des mesures dédiées (perspective n° 1). | AP14: De Beer & Fisher (2013) | AQ14: Non | AR14: =IF($B14="","",IFERROR(INDEX(Paramètres!$Q$6:$Q$13,MATCH($G14,Paramètres!$P$6:$P$13,0)),"")) -> Mesure de la pression de contact pneu-chaussée | AS14: =IF($B14="","",IFERROR(INDEX(Paramètres!$T$6:$T$11,MATCH($I14,Paramètres!$S$6:$S$11,0)),"")) -> octobre 2026 | AT14: =IF($B14="","",IFERROR(INDEX(Paramètres!$C$27:$C$29,MATCH($H14,Paramètres!$B$27:$B$29,0)),0)) -> 1 | AW14: =IF($B14="","",$B14&".md") -> guan2023triaxial.md | AX14: =IF($B14="","",COUNTIF($I$2:I14,$I14)) -> 13 | AY14: =IF($B14="","",$I14&"-"&$AX14) -> 1-13 | AZ14: https://scholar.google.com/scholar?q=%22Measurement+of+tire-pavement+contact+tri-axial+stress+distribution+based+on+sensor+array%22 | BA14: =IF($B14="","",$M14+(1000-ROW())/100000) -> 60.00986 | BB14: BIB-013_Guan-etal_2023_Tri-axial-contact-stress-sensor-array.pdf
A15: BIB-014 | B15: luo2025simplified | C15: =IF($B15="","",IFERROR(LEFT(LEFT($V15,FIND(";",$V15&";")-1),FIND(",",LEFT($V15,FIND(";",$V15&";")-1))-1),LEFT($V15,FIND(";",$V15&";")-1))&IF((LEN($V15)-LEN(SUBSTITUTE($V15,";",""))+1)=1,"",IF((LEN($V15)-LEN(SUBSTITUTE($V15,";",""))+1)=2," & "&IFERROR(LEFT(TRIM(MID($V15,FIND(";",$V15)+1,FIND(";",$V15&";",FIND(";",$V15)+1)-FIND(";",$V15)-1)),FIND(",",TRIM(MID($V15,FIND(";",$V15)+1,FIND(";",$V15&";",FIND(";",$V15)+1)-FIND(";",$V15)-1)))-1),TRIM(MID($V15,FIND(";",$V15)+1,FIND(";",$V15&";",FIND(";",$V15)+1)-FIND(";",$V15)-1)))," et al."))&" ("&$W15&")") -> Luo et al. (2025) | D15: Tire-pavement contact behavior: A simplified model for predictive surface contact analysis | E15: =IF(OR($B15="",$AF15=""),"",HYPERLINK(IF(AND(Paramètres!$C$13<>"",$AJ15="Éditeur (abonnement)"),Paramètres!$C$13&$AF15,$AF15),"Ouvrir : "&$AE15)) -> Ouvrir : Page éditeur (DOI) | F15: Oui | G15: 1 | H15: A consulter | I15: 1 | J15: À lire | K15: =IF($B15="","",IF($J15="Lu","Lu",IF($J15="Écarté","Écarté",IF($I15<Paramètres!$C$8,"EN RETARD",IF($I15=Paramètres!$C$8,"Ce mois-ci",IF($I15=Paramètres!$C$8+1,"Mois prochain","À venir")))))) -> Ce mois-ci | L15: =IF($B15="","",IF($AL15="Non vérifié","Ne pas citer en l'état : métadonnées non vérifiées",IF($AL15="Partiel","Vérification à compléter avant de citer",IF($O15="Oui","",IF(OR($AJ15="PDF libre",$AJ15="PDF libre (dépôt)"),"PDF libre à télécharger",IF($AJ15="Éditeur (abonnement)","À télécharger via l'accès ENTPE",IF($AJ15="Payant (boutique)","À consulter via l'abonnement de l'école",IF($AJ15="Non diffusé (à demander)","Document à demander (feuille Demandes)","Texte intégral à localiser")))))))) | M15: =IF($B15="","",IF(OR($J15="Lu",$J15="Écarté"),0,IFERROR(INDEX(Paramètres!$C$17:$C$19,MATCH($H15,Paramètres!$B$17:$B$19,0)),0)+Paramètres!$C$20*(7-$I15)+IF($I15<Paramètres!$C$8,Paramètres!$C$21,0)+IF($F15="Oui",Paramètres!$C$22,0)+IF($AL15<>"Vérifié",Paramètres!$C$23,0)+IF(AND($O15<>"Oui",OR($AJ15="PDF libre",$AJ15="PDF libre (dépôt)")),Paramètres!$C$24,0))) -> 70 | O15: =IF($BB15="","Non",HYPERLINK(DossierPDF&$BB15,"Oui")) -> Oui | P15: Non | Q15: Non | T15: JOUR | U15: =IF($B15="","",IFERROR(INDEX(Paramètres!$N$6:$N$13,MATCH($T15,Paramètres!$M$6:$M$13,0)),$T15)) -> Article de revue | V15: Luo, Y.; Xu, Y.; Sun, Z.; Wang, L.; Li, Y.; Wang, H. | W15: 2025 | X15: Construction and Building Materials | Y15: 491 | AA15: 142649 | AC15: 10.1016/j.conbuildmat.2025.142649 | AE15: Page éditeur (DOI) | AF15: https://doi.org/10.1016/j.conbuildmat.2025.142649 | AG15: =IF($AC15="","",HYPERLINK("https://doi.org/"&$AC15,"doi.org")) -> doi.org | AH15: =IF($AZ15="","",HYPERLINK($AZ15,"Scholar")) -> Scholar | AI15: Payant | AJ15: Éditeur (abonnement) | AK15: Elsevier : abonnement ENTPE. | AL15: Vérifié | AM15: OpenAlex (DOI) | AN15: 22/09/2026 | AO15: Modèle simplifié du contact pneu-chaussée à l'échelle de la texture (théorie de Persson et élasticité), calé sur des films sensibles à la pression et un relevé laser de texture, pour l'adhérence ; profondeur de contact selon l'enrobé et la température. Lien avec ta thèse : cité dans le TFE pour les films sensibles ; il traite la micro-échelle de la texture, pas l'empreinte à l'échelle du pneu. | AQ15: Non | AR15: =IF($B15="","",IFERROR(INDEX(Paramètres!$Q$6:$Q$13,MATCH($G15,Paramètres!$P$6:$P$13,0)),"")) -> Mesure de la pression de contact pneu-chaussée | AS15: =IF($B15="","",IFERROR(INDEX(Paramètres!$T$6:$T$11,MATCH($I15,Paramètres!$S$6:$S$11,0)),"")) -> octobre 2026 | AT15: =IF($B15="","",IFERROR(INDEX(Paramètres!$C$27:$C$29,MATCH($H15,Paramètres!$B$27:$B$29,0)),0)) -> 1 | AW15: =IF($B15="","",$B15&".md") -> luo2025simplified.md | AX15: =IF($B15="","",COUNTIF($I$2:I15,$I15)) -> 14 | AY15: =IF($B15="","",$I15&"-"&$AX15) -> 1-14 | AZ15: https://scholar.google.com/scholar?q=%22Tire-pavement+contact+behavior%3A+A+simplified+model+for+predictive+surface+contact+analysis%22 | BA15: =IF($B15="","",$M15+(1000-ROW())/100000) -> 70.00985 | BB15: BIB-014_Luo-etal_2025_Simplified-tire-pavement-contact-model.pdf
A16: BIB-015 | B16: song2025normalstress | C16: =IF($B16="","",IFERROR(LEFT(LEFT($V16,FIND(";",$V16&";")-1),FIND(",",LEFT($V16,FIND(";",$V16&";")-1))-1),LEFT($V16,FIND(";",$V16&";")-1))&IF((LEN($V16)-LEN(SUBSTITUTE($V16,";",""))+1)=1,"",IF((LEN($V16)-LEN(SUBSTITUTE($V16,";",""))+1)=2," & "&IFERROR(LEFT(TRIM(MID($V16,FIND(";",$V16)+1,FIND(";",$V16&";",FIND(";",$V16)+1)-FIND(";",$V16)-1)),FIND(",",TRIM(MID($V16,FIND(";",$V16)+1,FIND(";",$V16&";",FIND(";",$V16)+1)-FIND(";",$V16)-1)))-1),TRIM(MID($V16,FIND(";",$V16)+1,FIND(";",$V16&";",FIND(";",$V16)+1)-FIND(";",$V16)-1)))," et al."))&" ("&$W16&")") -> Song et al. (2025) | D16: High-precision normal stress measurement methods for tire–road contact and its spatial and frequency domain distribution characteristics | E16: =IF(OR($B16="",$AF16=""),"",HYPERLINK(IF(AND(Paramètres!$C$13<>"",$AJ16="Éditeur (abonnement)"),Paramètres!$C$13&$AF16,$AF16),"Ouvrir : "&$AE16)) -> Ouvrir : Texte intégral libre | F16: Oui | G16: 1 | H16: A consulter | I16: 1 | J16: À lire | K16: =IF($B16="","",IF($J16="Lu","Lu",IF($J16="Écarté","Écarté",IF($I16<Paramètres!$C$8,"EN RETARD",IF($I16=Paramètres!$C$8,"Ce mois-ci",IF($I16=Paramètres!$C$8+1,"Mois prochain","À venir")))))) -> Ce mois-ci | L16: =IF($B16="","",IF($AL16="Non vérifié","Ne pas citer en l'état : métadonnées non vérifiées",IF($AL16="Partiel","Vérification à compléter avant de citer",IF($O16="Oui","",IF(OR($AJ16="PDF libre",$AJ16="PDF libre (dépôt)"),"PDF libre à télécharger",IF($AJ16="Éditeur (abonnement)","À télécharger via l'accès ENTPE",IF($AJ16="Payant (boutique)","À consulter via l'abonnement de l'école",IF($AJ16="Non diffusé (à demander)","Document à demander (feuille Demandes)","Texte intégral à localiser")))))))) | M16: =IF($B16="","",IF(OR($J16="Lu",$J16="Écarté"),0,IFERROR(INDEX(Paramètres!$C$17:$C$19,MATCH($H16,Paramètres!$B$17:$B$19,0)),0)+Paramètres!$C$20*(7-$I16)+IF($I16<Paramètres!$C$8,Paramètres!$C$21,0)+IF($F16="Oui",Paramètres!$C$22,0)+IF($AL16<>"Vérifié",Paramètres!$C$23,0)+IF(AND($O16<>"Oui",OR($AJ16="PDF libre",$AJ16="PDF libre (dépôt)")),Paramètres!$C$24,0))) -> 70 | O16: =IF($BB16="","Non",HYPERLINK(DossierPDF&$BB16,"Oui")) -> Oui | P16: Non | Q16: Non | T16: JOUR | U16: =IF($B16="","",IFERROR(INDEX(Paramètres!$N$6:$N$13,MATCH($T16,Paramètres!$M$6:$M$13,0)),$T16)) -> Article de revue | V16: Song, L.; Wu, X.; Xie, Z.; Gao, J.; Yun, D.; Lei, Z. | W16: 2025 | X16: Lubricants | Y16: 13 | Z16: 7 | AA16: 309 | AC16: 10.3390/lubricants13070309 | AE16: Texte intégral libre | AF16: https://doi.org/10.3390/lubricants13070309 | AG16: =IF($AC16="","",HYPERLINK("https://doi.org/"&$AC16,"doi.org")) -> doi.org | AH16: =IF($AZ16="","",HYPERLINK($AZ16,"Scholar")) -> Scholar | AI16: Libre | AJ16: PDF libre | AK16: Article en libre accès (MDPI). | AL16: Vérifié | AM16: OpenAlex (DOI) | AN16: 22/09/2026 | AO16: Mesure de la contrainte normale pneu-route à l'échelle de la texture par scan 3D et courbe de portance, analysée dans l'espace et en fréquence spatiale. Lien avec ta thèse : cité dans le TFE avec les films sensibles superposés, alors que le résumé décrit une autre méthode (à vérifier) ; l'analyse fréquentielle porte sur la texture, pas sur l'empreinte. | AQ16: Non | AR16: =IF($B16="","",IFERROR(INDEX(Paramètres!$Q$6:$Q$13,MATCH($G16,Paramètres!$P$6:$P$13,0)),"")) -> Mesure de la pression de contact pneu-chaussée | AS16: =IF($B16="","",IFERROR(INDEX(Paramètres!$T$6:$T$11,MATCH($I16,Paramètres!$S$6:$S$11,0)),"")) -> octobre 2026 | AT16: =IF($B16="","",IFERROR(INDEX(Paramètres!$C$27:$C$29,MATCH($H16,Paramètres!$B$27:$B$29,0)),0)) -> 1 | AW16: =IF($B16="","",$B16&".md") -> song2025normalstress.md | AX16: =IF($B16="","",COUNTIF($I$2:I16,$I16)) -> 15 | AY16: =IF($B16="","",$I16&"-"&$AX16) -> 1-15 | AZ16: https://scholar.google.com/scholar?q=%22High-precision+normal+stress+measurement+methods+for+tire%E2%80%93road+contact+and+its+spatial+and+frequency+domain+distribution+characteristics%22 | BA16: =IF($B16="","",$M16+(1000-ROW())/100000) -> 70.00984 | BB16: BIB-015_Song-etal_2025_Normal-stress-measurement-tire-road.pdf
A17: BIB-016 | B17: tielking1989sae | C17: =IF($B17="","",IFERROR(LEFT(LEFT($V17,FIND(";",$V17&";")-1),FIND(",",LEFT($V17,FIND(";",$V17&";")-1))-1),LEFT($V17,FIND(";",$V17&";")-1))&IF((LEN($V17)-LEN(SUBSTITUTE($V17,";",""))+1)=1,"",IF((LEN($V17)-LEN(SUBSTITUTE($V17,";",""))+1)=2," & "&IFERROR(LEFT(TRIM(MID($V17,FIND(";",$V17)+1,FIND(";",$V17&";",FIND(";",$V17)+1)-FIND(";",$V17)-1)),FIND(",",TRIM(MID($V17,FIND(";",$V17)+1,FIND(";",$V17&";",FIND(";",$V17)+1)-FIND(";",$V17)-1)))-1),TRIM(MID($V17,FIND(";",$V17)+1,FIND(";",$V17&";",FIND(";",$V17)+1)-FIND(";",$V17)-1)))," et al."))&" ("&$W17&")") -> Tielking (1989) | D17: Aircraft tire/pavement pressure distributions | E17: =IF(OR($B17="",$AF17=""),"",HYPERLINK(IF(AND(Paramètres!$C$13<>"",$AJ17="Éditeur (abonnement)"),Paramètres!$C$13&$AF17,$AF17),"Ouvrir : "&$AE17)) -> Ouvrir : Page éditeur (DOI) | F17: Non | G17: 1 | H17: A consulter | I17: 1 | J17: À lire | K17: =IF($B17="","",IF($J17="Lu","Lu",IF($J17="Écarté","Écarté",IF($I17<Paramètres!$C$8,"EN RETARD",IF($I17=Paramètres!$C$8,"Ce mois-ci",IF($I17=Paramètres!$C$8+1,"Mois prochain","À venir")))))) -> Ce mois-ci | L17: =IF($B17="","",IF($AL17="Non vérifié","Ne pas citer en l'état : métadonnées non vérifiées",IF($AL17="Partiel","Vérification à compléter avant de citer",IF($O17="Oui","",IF(OR($AJ17="PDF libre",$AJ17="PDF libre (dépôt)"),"PDF libre à télécharger",IF($AJ17="Éditeur (abonnement)","À télécharger via l'accès ENTPE",IF($AJ17="Payant (boutique)","À consulter via l'abonnement de l'école",IF($AJ17="Non diffusé (à demander)","Document à demander (feuille Demandes)","Texte intégral à localiser")))))))) | M17: =IF($B17="","",IF(OR($J17="Lu",$J17="Écarté"),0,IFERROR(INDEX(Paramètres!$C$17:$C$19,MATCH($H17,Paramètres!$B$17:$B$19,0)),0)+Paramètres!$C$20*(7-$I17)+IF($I17<Paramètres!$C$8,Paramètres!$C$21,0)+IF($F17="Oui",Paramètres!$C$22,0)+IF($AL17<>"Vérifié",Paramètres!$C$23,0)+IF(AND($O17<>"Oui",OR($AJ17="PDF libre",$AJ17="PDF libre (dépôt)")),Paramètres!$C$24,0))) -> 60 | O17: =IF($BB17="","Non",HYPERLINK(DossierPDF&$BB17,"Oui")) -> Oui | P17: Non | Q17: Non | T17: CONF | U17: =IF($B17="","",IFERROR(INDEX(Paramètres!$N$6:$N$13,MATCH($T17,Paramètres!$M$6:$M$13,0)),$T17)) -> Communication (actes) | V17: Tielking, J. T. | W17: 1989 | X17: SAE Aerospace Technology Conference and Exposition, Anaheim, 25 September 1989 | AB17: SAE International | AC17: 10.4271/892351 | AD17: SAE Technical Paper 892351 | AE17: Page éditeur (DOI) | AF17: https://doi.org/10.4271/892351 | AG17: =IF($AC17="","",HYPERLINK("https://doi.org/"&$AC17,"doi.org")) -> doi.org | AH17: =IF($AZ17="","",HYPERLINK($AZ17,"Scholar")) -> Scholar | AI17: Payant | AJ17: Payant (boutique) | AK17: Payant chez SAE ; le rapport AFESC ESL-TR-89-01 (même travail, plus détaillé) est en accès libre. | AL17: Vérifié | AM17: SAE Mobilus | AN17: 22/09/2026 | AO17: Version conférence du travail de Tielking sur la pression de contact des pneus d'avion chargés statiquement. Lien avec ta thèse : à citer si tu veux une version publiée ; lis plutôt le rapport AFESC. | AP17: Tielking (1989) | AQ17: Oui | AR17: =IF($B17="","",IFERROR(INDEX(Paramètres!$Q$6:$Q$13,MATCH($G17,Paramètres!$P$6:$P$13,0)),"")) -> Mesure de la pression de contact pneu-chaussée | AS17: =IF($B17="","",IFERROR(INDEX(Paramètres!$T$6:$T$11,MATCH($I17,Paramètres!$S$6:$S$11,0)),"")) -> octobre 2026 | AT17: =IF($B17="","",IFERROR(INDEX(Paramètres!$C$27:$C$29,MATCH($H17,Paramètres!$B$27:$B$29,0)),0)) -> 1 | AW17: =IF($B17="","",$B17&".md") -> tielking1989sae.md | AX17: =IF($B17="","",COUNTIF($I$2:I17,$I17)) -> 16 | AY17: =IF($B17="","",$I17&"-"&$AX17) -> 1-16 | AZ17: https://scholar.google.com/scholar?q=%22Aircraft+tire%2Fpavement+pressure+distributions%22 | BA17: =IF($B17="","",$M17+(1000-ROW())/100000) -> 60.00983 | BB17: BIB-016_Tielking_1989_Aircraft-tire-pavement-pressure-SAE-892351.pdf
A18: BIB-017 | B18: wang2021alt | C18: =IF($B18="","",IFERROR(LEFT(LEFT($V18,FIND(";",$V18&";")-1),FIND(",",LEFT($V18,FIND(";",$V18&";")-1))-1),LEFT($V18,FIND(";",$V18&";")-1))&IF((LEN($V18)-LEN(SUBSTITUTE($V18,";",""))+1)=1,"",IF((LEN($V18)-LEN(SUBSTITUTE($V18,";",""))+1)=2," & "&IFERROR(LEFT(TRIM(MID($V18,FIND(";",$V18)+1,FIND(";",$V18&";",FIND(";",$V18)+1)-FIND(";",$V18)-1)),FIND(",",TRIM(MID($V18,FIND(";",$V18)+1,FIND(";",$V18&";",FIND(";",$V18)+1)-FIND(";",$V18)-1)))-1),TRIM(MID($V18,FIND(";",$V18)+1,FIND(";",$V18&";",FIND(";",$V18)+1)-FIND(";",$V18)-1)))," et al."))&" ("&$W18&")") -> Wang et al. (2021) | D18: Characterization of dynamic response of asphalt pavement in dry and saturated conditions using the full-scale accelerated loading test | E18: =IF(OR($B18="",$AF18=""),"",HYPERLINK(IF(AND(Paramètres!$C$13<>"",$AJ18="Éditeur (abonnement)"),Paramètres!$C$13&$AF18,$AF18),"Ouvrir : "&$AE18)) -> Ouvrir : Page éditeur (DOI) | F18: Oui | G18: 1 | H18: A consulter | I18: 1 | J18: À lire | K18: =IF($B18="","",IF($J18="Lu","Lu",IF($J18="Écarté","Écarté",IF($I18<Paramètres!$C$8,"EN RETARD",IF($I18=Paramètres!$C$8,"Ce mois-ci",IF($I18=Paramètres!$C$8+1,"Mois prochain","À venir")))))) -> Ce mois-ci | L18: =IF($B18="","",IF($AL18="Non vérifié","Ne pas citer en l'état : métadonnées non vérifiées",IF($AL18="Partiel","Vérification à compléter avant de citer",IF($O18="Oui","",IF(OR($AJ18="PDF libre",$AJ18="PDF libre (dépôt)"),"PDF libre à télécharger",IF($AJ18="Éditeur (abonnement)","À télécharger via l'accès ENTPE",IF($AJ18="Payant (boutique)","À consulter via l'abonnement de l'école",IF($AJ18="Non diffusé (à demander)","Document à demander (feuille Demandes)","Texte intégral à localiser")))))))) | M18: =IF($B18="","",IF(OR($J18="Lu",$J18="Écarté"),0,IFERROR(INDEX(Paramètres!$C$17:$C$19,MATCH($H18,Paramètres!$B$17:$B$19,0)),0)+Paramètres!$C$20*(7-$I18)+IF($I18<Paramètres!$C$8,Paramètres!$C$21,0)+IF($F18="Oui",Paramètres!$C$22,0)+IF($AL18<>"Vérifié",Paramètres!$C$23,0)+IF(AND($O18<>"Oui",OR($AJ18="PDF libre",$AJ18="PDF libre (dépôt)")),Paramètres!$C$24,0))) -> 70 | O18: =IF($BB18="","Non",HYPERLINK(DossierPDF&$BB18,"Oui")) -> Oui | P18: Non | Q18: Non | T18: JOUR | U18: =IF($B18="","",IFERROR(INDEX(Paramètres!$N$6:$N$13,MATCH($T18,Paramètres!$M$6:$M$13,0)),$T18)) -> Article de revue | V18: Wang, W.; Zhao, K.; Li, J.; Luo, R.; Wang, L. | W18: 2021 | X18: Construction and Building Materials | Y18: 312 | AA18: 125355 | AC18: 10.1016/j.conbuildmat.2021.125355 | AE18: Page éditeur (DOI) | AF18: https://doi.org/10.1016/j.conbuildmat.2021.125355 | AG18: =IF($AC18="","",HYPERLINK("https://doi.org/"&$AC18,"doi.org")) -> doi.org | AH18: =IF($AZ18="","",HYPERLINK($AZ18,"Scholar")) -> Scholar | AI18: Payant | AJ18: Éditeur (abonnement) | AK18: Elsevier : abonnement ENTPE. | AL18: Vérifié | AM18: OpenAlex (DOI) | AN18: 22/09/2026 | AO18: Réponse dynamique d'une chaussée bitumineuse en conditions sèche et saturée sous chargement accéléré en vraie grandeur. Lien avec ta thèse : cité dans le TFE pour la mesure d'aire de contact (Fig. 1-25) ; pertinence faible au-delà de cette figure. | AQ18: Non | AR18: =IF($B18="","",IFERROR(INDEX(Paramètres!$Q$6:$Q$13,MATCH($G18,Paramètres!$P$6:$P$13,0)),"")) -> Mesure de la pression de contact pneu-chaussée | AS18: =IF($B18="","",IFERROR(INDEX(Paramètres!$T$6:$T$11,MATCH($I18,Paramètres!$S$6:$S$11,0)),"")) -> octobre 2026 | AT18: =IF($B18="","",IFERROR(INDEX(Paramètres!$C$27:$C$29,MATCH($H18,Paramètres!$B$27:$B$29,0)),0)) -> 1 | AW18: =IF($B18="","",$B18&".md") -> wang2021alt.md | AX18: =IF($B18="","",COUNTIF($I$2:I18,$I18)) -> 17 | AY18: =IF($B18="","",$I18&"-"&$AX18) -> 1-17 | AZ18: https://scholar.google.com/scholar?q=%22Characterization+of+dynamic+response+of+asphalt+pavement+in+dry+and+saturated+conditions+using+the+full-scale+accelerated+loading+test%22 | BA18: =IF($B18="","",$M18+(1000-ROW())/100000) -> 70.00982 | BB18: BIB-017_Wang-etal_2021_Dynamic-response-asphalt-accelerated-loading.pdf
A19: BIB-018 | B19: wesolowski2020aircraft | C19: =IF($B19="","",IFERROR(LEFT(LEFT($V19,FIND(";",$V19&";")-1),FIND(",",LEFT($V19,FIND(";",$V19&";")-1))-1),LEFT($V19,FIND(";",$V19&";")-1))&IF((LEN($V19)-LEN(SUBSTITUTE($V19,";",""))+1)=1,"",IF((LEN($V19)-LEN(SUBSTITUTE($V19,";",""))+1)=2," & "&IFERROR(LEFT(TRIM(MID($V19,FIND(";",$V19)+1,FIND(";",$V19&";",FIND(";",$V19)+1)-FIND(";",$V19)-1)),FIND(",",TRIM(MID($V19,FIND(";",$V19)+1,FIND(";",$V19&";",FIND(";",$V19)+1)-FIND(";",$V19)-1)))-1),TRIM(MID($V19,FIND(";",$V19)+1,FIND(";",$V19&";",FIND(";",$V19)+1)-FIND(";",$V19)-1)))," et al."))&" ("&$W19&")") -> Wesołowski et al. (2020) | D19: Analysis of the actual contact surface of selected aircraft tires with the airport pavement as a function of pressure and vertical load | E19: =IF(OR($B19="",$AF19=""),"",HYPERLINK(IF(AND(Paramètres!$C$13<>"",$AJ19="Éditeur (abonnement)"),Paramètres!$C$13&$AF19,$AF19),"Ouvrir : "&$AE19)) -> Ouvrir : Texte intégral libre | F19: Non | G19: 1 | H19: A consulter | I19: 1 | J19: À lire | K19: =IF($B19="","",IF($J19="Lu","Lu",IF($J19="Écarté","Écarté",IF($I19<Paramètres!$C$8,"EN RETARD",IF($I19=Paramètres!$C$8,"Ce mois-ci",IF($I19=Paramètres!$C$8+1,"Mois prochain","À venir")))))) -> Ce mois-ci | L19: =IF($B19="","",IF($AL19="Non vérifié","Ne pas citer en l'état : métadonnées non vérifiées",IF($AL19="Partiel","Vérification à compléter avant de citer",IF($O19="Oui","",IF(OR($AJ19="PDF libre",$AJ19="PDF libre (dépôt)"),"PDF libre à télécharger",IF($AJ19="Éditeur (abonnement)","À télécharger via l'accès ENTPE",IF($AJ19="Payant (boutique)","À consulter via l'abonnement de l'école",IF($AJ19="Non diffusé (à demander)","Document à demander (feuille Demandes)","Texte intégral à localiser")))))))) | M19: =IF($B19="","",IF(OR($J19="Lu",$J19="Écarté"),0,IFERROR(INDEX(Paramètres!$C$17:$C$19,MATCH($H19,Paramètres!$B$17:$B$19,0)),0)+Paramètres!$C$20*(7-$I19)+IF($I19<Paramètres!$C$8,Paramètres!$C$21,0)+IF($F19="Oui",Paramètres!$C$22,0)+IF($AL19<>"Vérifié",Paramètres!$C$23,0)+IF(AND($O19<>"Oui",OR($AJ19="PDF libre",$AJ19="PDF libre (dépôt)")),Paramètres!$C$24,0))) -> 60 | O19: =IF($BB19="","Non",HYPERLINK(DossierPDF&$BB19,"Oui")) -> Oui | P19: Non | Q19: Non | T19: JOUR | U19: =IF($B19="","",IFERROR(INDEX(Paramètres!$N$6:$N$13,MATCH($T19,Paramètres!$M$6:$M$13,0)),$T19)) -> Article de revue | V19: Wesołowski, M.; Blacha, K.; Pietruszewski, P.; Iwanowski, P. | W19: 2020 | X19: Coatings | Y19: 10 | Z19: 6 | AA19: 591 | AC19: 10.3390/coatings10060591 | AE19: Texte intégral libre | AF19: https://www.mdpi.com/2079-6412/10/6/591/pdf | AG19: =IF($AC19="","",HYPERLINK("https://doi.org/"&$AC19,"doi.org")) -> doi.org | AH19: =IF($AZ19="","",HYPERLINK($AZ19,"Scholar")) -> Scholar | AI19: Libre | AJ19: PDF libre | AK19: Article en libre accès (MDPI). | AL19: Vérifié | AM19: OpenAlex (DOI) | AN19: 22/09/2026 | AO19: Mesure de la surface de contact réelle de pneus d'avion sur chaussée aéroportuaire en fonction de la pression de gonflage et de la charge verticale. Lien avec ta thèse : l'une des rares données expérimentales publiées sur pneus d'avion ; noter à la lecture les appareils et les pneus testés pour juger de la transposition aux gros porteurs. | AQ19: Non | AR19: =IF($B19="","",IFERROR(INDEX(Paramètres!$Q$6:$Q$13,MATCH($G19,Paramètres!$P$6:$P$13,0)),"")) -> Mesure de la pression de contact pneu-chaussée | AS19: =IF($B19="","",IFERROR(INDEX(Paramètres!$T$6:$T$11,MATCH($I19,Paramètres!$S$6:$S$11,0)),"")) -> octobre 2026 | AT19: =IF($B19="","",IFERROR(INDEX(Paramètres!$C$27:$C$29,MATCH($H19,Paramètres!$B$27:$B$29,0)),0)) -> 1 | AW19: =IF($B19="","",$B19&".md") -> wesolowski2020aircraft.md | AX19: =IF($B19="","",COUNTIF($I$2:I19,$I19)) -> 18 | AY19: =IF($B19="","",$I19&"-"&$AX19) -> 1-18 | AZ19: https://scholar.google.com/scholar?q=%22Analysis+of+the+actual+contact+surface+of+selected+aircraft+tires+with+the+airport+pavement+as+a+function+of+pressure+and+vertical+load%22 | BA19: =IF($B19="","",$M19+(1000-ROW())/100000) -> 60.00981 | BB19: BIB-018_Wesolowski-etal_2020_Aircraft-tire-contact-surface.pdf
A20: BIB-019 | B20: dibenedetto2004lve | C20: =IF($B20="","",IFERROR(LEFT(LEFT($V20,FIND(";",$V20&";")-1),FIND(",",LEFT($V20,FIND(";",$V20&";")-1))-1),LEFT($V20,FIND(";",$V20&";")-1))&IF((LEN($V20)-LEN(SUBSTITUTE($V20,";",""))+1)=1,"",IF((LEN($V20)-LEN(SUBSTITUTE($V20,";",""))+1)=2," & "&IFERROR(LEFT(TRIM(MID($V20,FIND(";",$V20)+1,FIND(";",$V20&";",FIND(";",$V20)+1)-FIND(";",$V20)-1)),FIND(",",TRIM(MID($V20,FIND(";",$V20)+1,FIND(";",$V20&";",FIND(";",$V20)+1)-FIND(";",$V20)-1)))-1),TRIM(MID($V20,FIND(";",$V20)+1,FIND(";",$V20&";",FIND(";",$V20)+1)-FIND(";",$V20)-1)))," et al."))&" ("&$W20&")") -> Di Benedetto et al. (2004) | D20: Linear viscoelastic behaviour of bituminous materials: From binders to mixes | E20: =IF(OR($B20="",$AF20=""),"",HYPERLINK(IF(AND(Paramètres!$C$13<>"",$AJ20="Éditeur (abonnement)"),Paramètres!$C$13&$AF20,$AF20),"Ouvrir : "&$AE20)) -> Ouvrir : Page éditeur (DOI) | F20: Non | G20: 3 | H20: INCONTOURNABLE | I20: 2 | J20: À lire | K20: =IF($B20="","",IF($J20="Lu","Lu",IF($J20="Écarté","Écarté",IF($I20<Paramètres!$C$8,"EN RETARD",IF($I20=Paramètres!$C$8,"Ce mois-ci",IF($I20=Paramètres!$C$8+1,"Mois prochain","À venir")))))) -> Mois prochain | L20: =IF($B20="","",IF($AL20="Non vérifié","Ne pas citer en l'état : métadonnées non vérifiées",IF($AL20="Partiel","Vérification à compléter avant de citer",IF($O20="Oui","",IF(OR($AJ20="PDF libre",$AJ20="PDF libre (dépôt)"),"PDF libre à télécharger",IF($AJ20="Éditeur (abonnement)","À télécharger via l'accès ENTPE",IF($AJ20="Payant (boutique)","À consulter via l'abonnement de l'école",IF($AJ20="Non diffusé (à demander)","Document à demander (feuille Demandes)","Texte intégral à localiser")))))))) | M20: =IF($B20="","",IF(OR($J20="Lu",$J20="Écarté"),0,IFERROR(INDEX(Paramètres!$C$17:$C$19,MATCH($H20,Paramètres!$B$17:$B$19,0)),0)+Paramètres!$C$20*(7-$I20)+IF($I20<Paramètres!$C$8,Paramètres!$C$21,0)+IF($F20="Oui",Paramètres!$C$22,0)+IF($AL20<>"Vérifié",Paramètres!$C$23,0)+IF(AND($O20<>"Oui",OR($AJ20="PDF libre",$AJ20="PDF libre (dépôt)")),Paramètres!$C$24,0))) -> 125 | O20: =IF($BB20="","Non",HYPERLINK(DossierPDF&$BB20,"Oui")) -> Oui | P20: Non | Q20: Non | T20: JOUR | U20: =IF($B20="","",IFERROR(INDEX(Paramètres!$N$6:$N$13,MATCH($T20,Paramètres!$M$6:$M$13,0)),$T20)) -> Article de revue | V20: Di Benedetto, H.; Olard, F.; Sauzéat, C.; Delaporte, B. | W20: 2004 | X20: Road Materials and Pavement Design | Y20: 5 | Z20: sup1 | AA20: 163-202 | AC20: 10.1080/14680629.2004.9689992 | AE20: Page éditeur (DOI) | AF20: https://doi.org/10.1080/14680629.2004.9689992 | AG20: =IF($AC20="","",HYPERLINK("https://doi.org/"&$AC20,"doi.org")) -> doi.org | AH20: =IF($AZ20="","",HYPERLINK($AZ20,"Scholar")) -> Scholar | AI20: Payant | AJ20: Éditeur (abonnement) | AK20: Taylor & Francis : abonnement ENTPE. | AL20: Vérifié | AM20: Crossref | AN20: 22/09/2026 | AO20: Synthèse sur le comportement viscoélastique linéaire des matériaux bitumineux, des liants aux enrobés, avec le 2S2P1D. Lien avec ta thèse : cadre théorique de ton §1.2. | AP20: Olard & Di Benedetto (2003) | AQ20: Non | AR20: =IF($B20="","",IFERROR(INDEX(Paramètres!$Q$6:$Q$13,MATCH($G20,Paramètres!$P$6:$P$13,0)),"")) -> Viscoélasticité des enrobés | AS20: =IF($B20="","",IFERROR(INDEX(Paramètres!$T$6:$T$11,MATCH($I20,Paramètres!$S$6:$S$11,0)),"")) -> novembre 2026 | AT20: =IF($B20="","",IFERROR(INDEX(Paramètres!$C$27:$C$29,MATCH($H20,Paramètres!$B$27:$B$29,0)),0)) -> 6 | AW20: =IF($B20="","",$B20&".md") -> dibenedetto2004lve.md | AX20: =IF($B20="","",COUNTIF($I$2:I20,$I20)) -> 1 | AY20: =IF($B20="","",$I20&"-"&$AX20) -> 2-1 | AZ20: https://scholar.google.com/scholar?q=%22Linear+viscoelastic+behaviour+of+bituminous+materials%3A+From+binders+to+mixes%22 | BA20: =IF($B20="","",$M20+(1000-ROW())/100000) -> 125.0098 | BB20: BIB-019_DiBenedetto-etal_2004_Linear-viscoelastic-behaviour-binders-to-mixes.pdf
A21: BIB-020 | B21: olard20032s2p1d | C21: =IF($B21="","",IFERROR(LEFT(LEFT($V21,FIND(";",$V21&";")-1),FIND(",",LEFT($V21,FIND(";",$V21&";")-1))-1),LEFT($V21,FIND(";",$V21&";")-1))&IF((LEN($V21)-LEN(SUBSTITUTE($V21,";",""))+1)=1,"",IF((LEN($V21)-LEN(SUBSTITUTE($V21,";",""))+1)=2," & "&IFERROR(LEFT(TRIM(MID($V21,FIND(";",$V21)+1,FIND(";",$V21&";",FIND(";",$V21)+1)-FIND(";",$V21)-1)),FIND(",",TRIM(MID($V21,FIND(";",$V21)+1,FIND(";",$V21&";",FIND(";",$V21)+1)-FIND(";",$V21)-1)))-1),TRIM(MID($V21,FIND(";",$V21)+1,FIND(";",$V21&";",FIND(";",$V21)+1)-FIND(";",$V21)-1)))," et al."))&" ("&$W21&")") -> Olard & Di Benedetto (2003) | D21: General "2S2P1D" model and relation between the linear viscoelastic behaviours of bituminous binders and mixes | E21: =IF(OR($B21="",$AF21=""),"",HYPERLINK(IF(AND(Paramètres!$C$13<>"",$AJ21="Éditeur (abonnement)"),Paramètres!$C$13&$AF21,$AF21),"Ouvrir : "&$AE21)) -> Ouvrir : Page éditeur (DOI) | F21: Oui | G21: 3 | H21: INCONTOURNABLE | I21: 2 | J21: À lire | K21: =IF($B21="","",IF($J21="Lu","Lu",IF($J21="Écarté","Écarté",IF($I21<Paramètres!$C$8,"EN RETARD",IF($I21=Paramètres!$C$8,"Ce mois-ci",IF($I21=Paramètres!$C$8+1,"Mois prochain","À venir")))))) -> Mois prochain | L21: =IF($B21="","",IF($AL21="Non vérifié","Ne pas citer en l'état : métadonnées non vérifiées",IF($AL21="Partiel","Vérification à compléter avant de citer",IF($O21="Oui","",IF(OR($AJ21="PDF libre",$AJ21="PDF libre (dépôt)"),"PDF libre à télécharger",IF($AJ21="Éditeur (abonnement)","À télécharger via l'accès ENTPE",IF($AJ21="Payant (boutique)","À consulter via l'abonnement de l'école",IF($AJ21="Non diffusé (à demander)","Document à demander (feuille Demandes)","Texte intégral à localiser")))))))) | M21: =IF($B21="","",IF(OR($J21="Lu",$J21="Écarté"),0,IFERROR(INDEX(Paramètres!$C$17:$C$19,MATCH($H21,Paramètres!$B$17:$B$19,0)),0)+Paramètres!$C$20*(7-$I21)+IF($I21<Paramètres!$C$8,Paramètres!$C$21,0)+IF($F21="Oui",Paramètres!$C$22,0)+IF($AL21<>"Vérifié",Paramètres!$C$23,0)+IF(AND($O21<>"Oui",OR($AJ21="PDF libre",$AJ21="PDF libre (dépôt)")),Paramètres!$C$24,0))) -> 135 | O21: =IF($BB21="","Non",HYPERLINK(DossierPDF&$BB21,"Oui")) -> Oui | P21: Non | Q21: Non | T21: JOUR | U21: =IF($B21="","",IFERROR(INDEX(Paramètres!$N$6:$N$13,MATCH($T21,Paramètres!$M$6:$M$13,0)),$T21)) -> Article de revue | V21: Olard, F.; Di Benedetto, H. | W21: 2003 | X21: Road Materials and Pavement Design | Y21: 4 | Z21: 2 | AA21: 185-224 | AC21: 10.1080/14680629.2003.9689946 | AE21: Page éditeur (DOI) | AF21: https://doi.org/10.1080/14680629.2003.9689946 | AG21: =IF($AC21="","",HYPERLINK("https://doi.org/"&$AC21,"doi.org")) -> doi.org | AH21: =IF($AZ21="","",HYPERLINK($AZ21,"Scholar")) -> Scholar | AI21: Payant | AJ21: Éditeur (abonnement) | AK21: Taylor & Francis : abonnement ENTPE. Un second DOI Lavoisier (10.3166/…) peut exister pour les anciens numéros de la revue : garder celui de Taylor & Francis. | AL21: Vérifié | AM21: OpenAlex (DOI) | AN21: 22/09/2026 | AO21: Propose le modèle 2S2P1D (Huet-Sayegh complété par un amortisseur linéaire) et les relations entre comportements du liant et de l'enrobé. Lien avec ta thèse : c'est ton modèle de calage (chapitre 2). | AP21: Olard (2003) ; Tiouajni et al. (2011) | AQ21: Non | AR21: =IF($B21="","",IFERROR(INDEX(Paramètres!$Q$6:$Q$13,MATCH($G21,Paramètres!$P$6:$P$13,0)),"")) -> Viscoélasticité des enrobés | AS21: =IF($B21="","",IFERROR(INDEX(Paramètres!$T$6:$T$11,MATCH($I21,Paramètres!$S$6:$S$11,0)),"")) -> novembre 2026 | AT21: =IF($B21="","",IFERROR(INDEX(Paramètres!$C$27:$C$29,MATCH($H21,Paramètres!$B$27:$B$29,0)),0)) -> 6 | AW21: =IF($B21="","",$B21&".md") -> olard20032s2p1d.md | AX21: =IF($B21="","",COUNTIF($I$2:I21,$I21)) -> 2 | AY21: =IF($B21="","",$I21&"-"&$AX21) -> 2-2 | AZ21: https://scholar.google.com/scholar?q=%22General+%222S2P1D%22+model+and+relation+between+the+linear+viscoelastic+behaviours+of+bituminous+binders+and+mixes%22 | BA21: =IF($B21="","",$M21+(1000-ROW())/100000) -> 135.00979 | BB21: BIB-020_Olard-DiBenedetto_2003_General-2S2P1D-model.pdf
A22: BIB-021 | B22: tiouajni2011approximation | C22: =IF($B22="","",IFERROR(LEFT(LEFT($V22,FIND(";",$V22&";")-1),FIND(",",LEFT($V22,FIND(";",$V22&";")-1))-1),LEFT($V22,FIND(";",$V22&";")-1))&IF((LEN($V22)-LEN(SUBSTITUTE($V22,";",""))+1)=1,"",IF((LEN($V22)-LEN(SUBSTITUTE($V22,";",""))+1)=2," & "&IFERROR(LEFT(TRIM(MID($V22,FIND(";",$V22)+1,FIND(";",$V22&";",FIND(";",$V22)+1)-FIND(";",$V22)-1)),FIND(",",TRIM(MID($V22,FIND(";",$V22)+1,FIND(";",$V22&";",FIND(";",$V22)+1)-FIND(";",$V22)-1)))-1),TRIM(MID($V22,FIND(";",$V22)+1,FIND(";",$V22&";",FIND(";",$V22)+1)-FIND(";",$V22)-1)))," et al."))&" ("&$W22&")") -> Tiouajni et al. (2011) | D22: Approximation of linear viscoelastic model in the 3 dimensional case with mechanical analogues of finite size: Application to bituminous materials | E22: =IF(OR($B22="",$AF22=""),"",HYPERLINK(IF(AND(Paramètres!$C$13<>"",$AJ22="Éditeur (abonnement)"),Paramètres!$C$13&$AF22,$AF22),"Ouvrir : "&$AE22)) -> Ouvrir : Page éditeur (DOI) | F22: Oui | G22: 3 | H22: INCONTOURNABLE | I22: 2 | J22: À lire | K22: =IF($B22="","",IF($J22="Lu","Lu",IF($J22="Écarté","Écarté",IF($I22<Paramètres!$C$8,"EN RETARD",IF($I22=Paramètres!$C$8,"Ce mois-ci",IF($I22=Paramètres!$C$8+1,"Mois prochain","À venir")))))) -> Mois prochain | L22: =IF($B22="","",IF($AL22="Non vérifié","Ne pas citer en l'état : métadonnées non vérifiées",IF($AL22="Partiel","Vérification à compléter avant de citer",IF($O22="Oui","",IF(OR($AJ22="PDF libre",$AJ22="PDF libre (dépôt)"),"PDF libre à télécharger",IF($AJ22="Éditeur (abonnement)","À télécharger via l'accès ENTPE",IF($AJ22="Payant (boutique)","À consulter via l'abonnement de l'école",IF($AJ22="Non diffusé (à demander)","Document à demander (feuille Demandes)","Texte intégral à localiser")))))))) | M22: =IF($B22="","",IF(OR($J22="Lu",$J22="Écarté"),0,IFERROR(INDEX(Paramètres!$C$17:$C$19,MATCH($H22,Paramètres!$B$17:$B$19,0)),0)+Paramètres!$C$20*(7-$I22)+IF($I22<Paramètres!$C$8,Paramètres!$C$21,0)+IF($F22="Oui",Paramètres!$C$22,0)+IF($AL22<>"Vérifié",Paramètres!$C$23,0)+IF(AND($O22<>"Oui",OR($AJ22="PDF libre",$AJ22="PDF libre (dépôt)")),Paramètres!$C$24,0))) -> 135 | O22: =IF($BB22="","Non",HYPERLINK(DossierPDF&$BB22,"Oui")) -> Oui | P22: Non | Q22: Non | T22: JOUR | U22: =IF($B22="","",IFERROR(INDEX(Paramètres!$N$6:$N$13,MATCH($T22,Paramètres!$M$6:$M$13,0)),$T22)) -> Article de revue | V22: Tiouajni, S.; Di Benedetto, H.; Sauzéat, C.; Pouget, S. | W22: 2011 | X22: Road Materials and Pavement Design | Y22: 12 | Z22: 4 | AA22: 897-930 | AC22: 10.1080/14680629.2011.9713899 | AE22: Page éditeur (DOI) | AF22: https://doi.org/10.1080/14680629.2011.9713899 | AG22: =IF($AC22="","",HYPERLINK("https://doi.org/"&$AC22,"doi.org")) -> doi.org | AH22: =IF($AZ22="","",HYPERLINK($AZ22,"Scholar")) -> Scholar | AI22: Payant | AJ22: Éditeur (abonnement) | AK22: Taylor & Francis : abonnement ENTPE. | AL22: Vérifié | AM22: OpenAlex (DOI) | AN22: 22/09/2026 | AO22: Méthode d'approximation d'un modèle à spectre continu (2S2P1D) par des analogues mécaniques de taille finie, en 3D. Lien avec ta thèse : méthode que tu as appliquée pour obtenir ton Kelvin-Voigt généralisé à 9 branches. | AP22: Olard & Di Benedetto (2003) ; Park & Schapery (1999) | AQ22: Non | AR22: =IF($B22="","",IFERROR(INDEX(Paramètres!$Q$6:$Q$13,MATCH($G22,Paramètres!$P$6:$P$13,0)),"")) -> Viscoélasticité des enrobés | AS22: =IF($B22="","",IFERROR(INDEX(Paramètres!$T$6:$T$11,MATCH($I22,Paramètres!$S$6:$S$11,0)),"")) -> novembre 2026 | AT22: =IF($B22="","",IFERROR(INDEX(Paramètres!$C$27:$C$29,MATCH($H22,Paramètres!$B$27:$B$29,0)),0)) -> 6 | AW22: =IF($B22="","",$B22&".md") -> tiouajni2011approximation.md | AX22: =IF($B22="","",COUNTIF($I$2:I22,$I22)) -> 3 | AY22: =IF($B22="","",$I22&"-"&$AX22) -> 2-3 | AZ22: https://scholar.google.com/scholar?q=%22Approximation+of+linear+viscoelastic+model+in+the+3+dimensional+case+with+mechanical+analogues+of+finite+size%3A+Application+to+bituminous+materials%22 | BA22: =IF($B22="","",$M22+(1000-ROW())/100000) -> 135.00978 | BB22: BIB-021_Tiouajni-etal_2011_3D-linear-viscoelastic-model-analogues.pdf
A23: BIB-022 | B23: debeer1997interface | C23: =IF($B23="","",IFERROR(LEFT(LEFT($V23,FIND(";",$V23&";")-1),FIND(",",LEFT($V23,FIND(";",$V23&";")-1))-1),LEFT($V23,FIND(";",$V23&";")-1))&IF((LEN($V23)-LEN(SUBSTITUTE($V23,";",""))+1)=1,"",IF((LEN($V23)-LEN(SUBSTITUTE($V23,";",""))+1)=2," & "&IFERROR(LEFT(TRIM(MID($V23,FIND(";",$V23)+1,FIND(";",$V23&";",FIND(";",$V23)+1)-FIND(";",$V23)-1)),FIND(",",TRIM(MID($V23,FIND(";",$V23)+1,FIND(";",$V23&";",FIND(";",$V23)+1)-FIND(";",$V23)-1)))-1),TRIM(MID($V23,FIND(";",$V23)+1,FIND(";",$V23&";",FIND(";",$V23)+1)-FIND(";",$V23)-1)))," et al."))&" ("&$W23&")") -> De Beer et al. (1997) | D23: Determination of pneumatic tyre/pavement interface contact stresses under moving loads and some effects on pavements with thin asphalt surfacing layers | E23: =IF(OR($B23="",$AF23=""),"",HYPERLINK(IF(AND(Paramètres!$C$13<>"",$AJ23="Éditeur (abonnement)"),Paramètres!$C$13&$AF23,$AF23),"Ouvrir : "&$AE23)) -> Ouvrir : Recherche Google Scholar | F23: Oui | G23: 1 | H23: Important | I23: 2 | J23: À lire | K23: =IF($B23="","",IF($J23="Lu","Lu",IF($J23="Écarté","Écarté",IF($I23<Paramètres!$C$8,"EN RETARD",IF($I23=Paramètres!$C$8,"Ce mois-ci",IF($I23=Paramètres!$C$8+1,"Mois prochain","À venir")))))) -> Mois prochain | L23: =IF($B23="","",IF($AL23="Non vérifié","Ne pas citer en l'état : métadonnées non vérifiées",IF($AL23="Partiel","Vérification à compléter avant de citer",IF($O23="Oui","",IF(OR($AJ23="PDF libre",$AJ23="PDF libre (dépôt)"),"PDF libre à télécharger",IF($AJ23="Éditeur (abonnement)","À télécharger via l'accès ENTPE",IF($AJ23="Payant (boutique)","À consulter via l'abonnement de l'école",IF($AJ23="Non diffusé (à demander)","Document à demander (feuille Demandes)","Texte intégral à localiser")))))))) -> Vérification à compléter avant de citer | M23: =IF($B23="","",IF(OR($J23="Lu",$J23="Écarté"),0,IFERROR(INDEX(Paramètres!$C$17:$C$19,MATCH($H23,Paramètres!$B$17:$B$19,0)),0)+Paramètres!$C$20*(7-$I23)+IF($I23<Paramètres!$C$8,Paramètres!$C$21,0)+IF($F23="Oui",Paramètres!$C$22,0)+IF($AL23<>"Vérifié",Paramètres!$C$23,0)+IF(AND($O23<>"Oui",OR($AJ23="PDF libre",$AJ23="PDF libre (dépôt)")),Paramètres!$C$24,0))) -> 110 | O23: =IF($BB23="","Non",HYPERLINK(DossierPDF&$BB23,"Oui")) -> Oui | P23: Non | Q23: Non | T23: CONF | U23: =IF($B23="","",IFERROR(INDEX(Paramètres!$N$6:$N$13,MATCH($T23,Paramètres!$M$6:$M$13,0)),$T23)) -> Communication (actes) | V23: De Beer, M.; Fisher, C.; Jooste, F. J. | W23: 1997 | X23: Proceedings of the 8th International Conference on Asphalt Pavements (ICAP '97), Seattle, 10-14 August 1997 | Y23: 1 | AA23: 179-227 | AB23: University of Washington / ISAP | AD23: Actes ICAP 1997, vol. 1 | AE23: Recherche Google Scholar | AF23: https://scholar.google.com/scholar?q=%22Determination+of+pneumatic+tyre%2Fpavement+interface+contact+stresses+under+moving+loads+and+some+effects+on+pavements+with+thin+asphalt+surfacing+layers%22 | AG23: =IF($AC23="","",HYPERLINK("https://doi.org/"&$AC23,"doi.org")) | AH23: =IF($AZ23="","",HYPERLINK($AZ23,"Scholar")) -> Scholar | AI23: Restreint | AJ23: Non diffusé (à demander) | AK23: Actes ICAP 1997 non diffusés en ligne : prêt entre bibliothèques (PEB) par la documentation de l'ENTPE. | AL23: Partiel | AM23: Citations des auteurs (De Beer, Fisher & Kannemeyer 2004 ; De Beer & Fisher 2013) | AN23: 22/09/2026 | AO23: Article fondateur du dispositif VRSPTA : mesure des trois composantes de contrainte à l'interface pneu-chaussée sous charge roulante lente, et premiers effets sur des chaussées à revêtement mince. Lien avec ta thèse : origine des cartographies en n et en M que tu as transposées ; à lire pour le principe de mesure et ses limites (vitesse, plots). NON VÉRIFIÉ (partiel) : lieu, date, volume et pages relevés dans les citations des auteurs eux-mêmes ; les actes ICAP 1997 n'ont pas été consultés (pagination 179-227 à constater). | AP23: De Beer & Fisher (2013) ; De Beer et al. (2002) | AQ23: Oui | AR23: =IF($B23="","",IFERROR(INDEX(Paramètres!$Q$6:$Q$13,MATCH($G23,Paramètres!$P$6:$P$13,0)),"")) -> Mesure de la pression de contact pneu-chaussée | AS23: =IF($B23="","",IFERROR(INDEX(Paramètres!$T$6:$T$11,MATCH($I23,Paramètres!$S$6:$S$11,0)),"")) -> novembre 2026 | AT23: =IF($B23="","",IFERROR(INDEX(Paramètres!$C$27:$C$29,MATCH($H23,Paramètres!$B$27:$B$29,0)),0)) -> 3 | AW23: =IF($B23="","",$B23&".md") -> debeer1997interface.md | AX23: =IF($B23="","",COUNTIF($I$2:I23,$I23)) -> 4 | AY23: =IF($B23="","",$I23&"-"&$AX23) -> 2-4 | AZ23: https://scholar.google.com/scholar?q=%22Determination+of+pneumatic+tyre%2Fpavement+interface+contact+stresses+under+moving+loads+and+some+effects+on+pavements+with+thin+asphalt+surfacing+layers%22 | BA23: =IF($B23="","",$M23+(1000-ROW())/100000) -> 110.00977 | BB23: BIB-022_DeBeer-etal_1997_Tyre-pavement-contact-stresses-moving-loads.pdf
A24: BIB-023 | B24: debeer2002nonuniform | C24: =IF($B24="","",IFERROR(LEFT(LEFT($V24,FIND(";",$V24&";")-1),FIND(",",LEFT($V24,FIND(";",$V24&";")-1))-1),LEFT($V24,FIND(";",$V24&";")-1))&IF((LEN($V24)-LEN(SUBSTITUTE($V24,";",""))+1)=1,"",IF((LEN($V24)-LEN(SUBSTITUTE($V24,";",""))+1)=2," & "&IFERROR(LEFT(TRIM(MID($V24,FIND(";",$V24)+1,FIND(";",$V24&";",FIND(";",$V24)+1)-FIND(";",$V24)-1)),FIND(",",TRIM(MID($V24,FIND(";",$V24)+1,FIND(";",$V24&";",FIND(";",$V24)+1)-FIND(";",$V24)-1)))-1),TRIM(MID($V24,FIND(";",$V24)+1,FIND(";",$V24&";",FIND(";",$V24)+1)-FIND(";",$V24)-1)))," et al."))&" ("&$W24&")") -> De Beer et al. (2002) | D24: Evaluation of non-uniform tyre contact stresses on thin asphalt pavements | E24: =IF(OR($B24="",$AF24=""),"",HYPERLINK(IF(AND(Paramètres!$C$13<>"",$AJ24="Éditeur (abonnement)"),Paramètres!$C$13&$AF24,$AF24),"Ouvrir : "&$AE24)) -> Ouvrir : Notice (document à demander) | F24: Oui | G24: 1 | H24: Important | I24: 2 | J24: À lire | K24: =IF($B24="","",IF($J24="Lu","Lu",IF($J24="Écarté","Écarté",IF($I24<Paramètres!$C$8,"EN RETARD",IF($I24=Paramètres!$C$8,"Ce mois-ci",IF($I24=Paramètres!$C$8+1,"Mois prochain","À venir")))))) -> Mois prochain | L24: =IF($B24="","",IF($AL24="Non vérifié","Ne pas citer en l'état : métadonnées non vérifiées",IF($AL24="Partiel","Vérification à compléter avant de citer",IF($O24="Oui","",IF(OR($AJ24="PDF libre",$AJ24="PDF libre (dépôt)"),"PDF libre à télécharger",IF($AJ24="Éditeur (abonnement)","À télécharger via l'accès ENTPE",IF($AJ24="Payant (boutique)","À consulter via l'abonnement de l'école",IF($AJ24="Non diffusé (à demander)","Document à demander (feuille Demandes)","Texte intégral à localiser")))))))) | M24: =IF($B24="","",IF(OR($J24="Lu",$J24="Écarté"),0,IFERROR(INDEX(Paramètres!$C$17:$C$19,MATCH($H24,Paramètres!$B$17:$B$19,0)),0)+Paramètres!$C$20*(7-$I24)+IF($I24<Paramètres!$C$8,Paramètres!$C$21,0)+IF($F24="Oui",Paramètres!$C$22,0)+IF($AL24<>"Vérifié",Paramètres!$C$23,0)+IF(AND($O24<>"Oui",OR($AJ24="PDF libre",$AJ24="PDF libre (dépôt)")),Paramètres!$C$24,0))) -> 95 | O24: =IF($BB24="","Non",HYPERLINK(DossierPDF&$BB24,"Oui")) -> Oui | P24: Non | Q24: Non | T24: CONF | U24: =IF($B24="","",IFERROR(INDEX(Paramètres!$N$6:$N$13,MATCH($T24,Paramètres!$M$6:$M$13,0)),$T24)) -> Communication (actes) | V24: De Beer, M.; Fisher, C.; Jooste, F. J. | W24: 2002 | X24: Proceedings of the 9th International Conference on Asphalt Pavements (ICAP 2002), Copenhagen, 17-22 August 2002 | AB24: International Society for Asphalt Pavements | AD24: TRID 00936330 ; actes sur CD, 30 p. | AE24: Notice (document à demander) | AF24: https://trid.trb.org/view.aspx?id=732149 | AG24: =IF($AC24="","",HYPERLINK("https://doi.org/"&$AC24,"doi.org")) | AH24: =IF($AZ24="","",HYPERLINK($AZ24,"Scholar")) -> Scholar | AI24: Restreint | AJ24: Non diffusé (à demander) | AK24: Texte complet dans les actes sur CD : PEB. Une fiche ResearchGate existe (publication 255670814). Le serveur « SIM web » du CSIR (asphalt.csir.co.za), qui diffusait un PDF de la présentation, était injoignable le 22/09/2026. | AL24: Vérifié | AM24: Notice TRID (ISAP) + citation des auteurs | AN24: 22/09/2026 | AO24: Montre, à partir de contraintes de contact mesurées, l'importance des données d'entrée de charge pour le dimensionnement des chaussées à revêtement mince. Lien avec ta thèse : référence citée au §3.1 pour l'empreinte hétérogène ; ajouter F. J. Jooste comme troisième auteur. | AP24: De Beer & Fisher (2000) ; De Beer et al. (1997) | AQ24: Oui | AR24: =IF($B24="","",IFERROR(INDEX(Paramètres!$Q$6:$Q$13,MATCH($G24,Paramètres!$P$6:$P$13,0)),"")) -> Mesure de la pression de contact pneu-chaussée | AS24: =IF($B24="","",IFERROR(INDEX(Paramètres!$T$6:$T$11,MATCH($I24,Paramètres!$S$6:$S$11,0)),"")) -> novembre 2026 | AT24: =IF($B24="","",IFERROR(INDEX(Paramètres!$C$27:$C$29,MATCH($H24,Paramètres!$B$27:$B$29,0)),0)) -> 3 | AW24: =IF($B24="","",$B24&".md") -> debeer2002nonuniform.md | AX24: =IF($B24="","",COUNTIF($I$2:I24,$I24)) -> 5 | AY24: =IF($B24="","",$I24&"-"&$AX24) -> 2-5 | AZ24: https://scholar.google.com/scholar?q=%22Evaluation+of+non-uniform+tyre+contact+stresses+on+thin+asphalt+pavements%22 | BA24: =IF($B24="","",$M24+(1000-ROW())/100000) -> 95.00976 | BB24: BIB-023_DeBeer-etal_2002_Non-uniform-tyre-contact-stresses-thin-asphalt.pdf
A25: BIB-024 | B25: daugherty2003radial | C25: =IF($B25="","",IFERROR(LEFT(LEFT($V25,FIND(";",$V25&";")-1),FIND(",",LEFT($V25,FIND(";",$V25&";")-1))-1),LEFT($V25,FIND(";",$V25&";")-1))&IF((LEN($V25)-LEN(SUBSTITUTE($V25,";",""))+1)=1,"",IF((LEN($V25)-LEN(SUBSTITUTE($V25,";",""))+1)=2," & "&IFERROR(LEFT(TRIM(MID($V25,FIND(";",$V25)+1,FIND(";",$V25&";",FIND(";",$V25)+1)-FIND(";",$V25)-1)),FIND(",",TRIM(MID($V25,FIND(";",$V25)+1,FIND(";",$V25&";",FIND(";",$V25)+1)-FIND(";",$V25)-1)))-1),TRIM(MID($V25,FIND(";",$V25)+1,FIND(";",$V25&";",FIND(";",$V25)+1)-FIND(";",$V25)-1)))," et al."))&" ("&$W25&")") -> Daugherty (2003) | D25: A study of the mechanical properties of modern radial aircraft tires | E25: =IF(OR($B25="",$AF25=""),"",HYPERLINK(IF(AND(Paramètres!$C$13<>"",$AJ25="Éditeur (abonnement)"),Paramètres!$C$13&$AF25,$AF25),"Ouvrir : "&$AE25)) -> Ouvrir : Texte intégral libre | F25: Non | G25: 2 | H25: Important | I25: 2 | J25: À lire | K25: =IF($B25="","",IF($J25="Lu","Lu",IF($J25="Écarté","Écarté",IF($I25<Paramètres!$C$8,"EN RETARD",IF($I25=Paramètres!$C$8,"Ce mois-ci",IF($I25=Paramètres!$C$8+1,"Mois prochain","À venir")))))) -> Mois prochain | L25: =IF($B25="","",IF($AL25="Non vérifié","Ne pas citer en l'état : métadonnées non vérifiées",IF($AL25="Partiel","Vérification à compléter avant de citer",IF($O25="Oui","",IF(OR($AJ25="PDF libre",$AJ25="PDF libre (dépôt)"),"PDF libre à télécharger",IF($AJ25="Éditeur (abonnement)","À télécharger via l'accès ENTPE",IF($AJ25="Payant (boutique)","À consulter via l'abonnement de l'école",IF($AJ25="Non diffusé (à demander)","Document à demander (feuille Demandes)","Texte intégral à localiser")))))))) | M25: =IF($B25="","",IF(OR($J25="Lu",$J25="Écarté"),0,IFERROR(INDEX(Paramètres!$C$17:$C$19,MATCH($H25,Paramètres!$B$17:$B$19,0)),0)+Paramètres!$C$20*(7-$I25)+IF($I25<Paramètres!$C$8,Paramètres!$C$21,0)+IF($F25="Oui",Paramètres!$C$22,0)+IF($AL25<>"Vérifié",Paramètres!$C$23,0)+IF(AND($O25<>"Oui",OR($AJ25="PDF libre",$AJ25="PDF libre (dépôt)")),Paramètres!$C$24,0))) -> 85 | O25: =IF($BB25="","Non",HYPERLINK(DossierPDF&$BB25,"Oui")) -> Oui | P25: Non | Q25: Non | T25: RPRT | U25: =IF($B25="","",IFERROR(INDEX(Paramètres!$N$6:$N$13,MATCH($T25,Paramètres!$M$6:$M$13,0)),$T25)) -> Rapport | V25: Daugherty, R. H. | W25: 2003 | AB25: NASA Langley Research Center | AD25: NASA/TM-2003-212415 ; 74 p. | AE25: Texte intégral libre | AF25: https://www.cs.odu.edu/~mln/ltrs-pdfs/NASA-2003-tm212415.pdf | AG25: =IF($AC25="","",HYPERLINK("https://doi.org/"&$AC25,"doi.org")) | AH25: =IF($AZ25="","",HYPERLINK($AZ25,"Scholar")) -> Scholar | AI25: Libre | AJ25: PDF libre | AK25: PDF public (archive des rapports techniques de NASA Langley). | AL25: Vérifié | AM25: PDF du rapport (page de documentation) | AN25: 22/09/2026 | AO25: Campagne expérimentale NASA sur les propriétés mécaniques de pneus d'avion radiaux modernes de la flotte commerciale, selon la charge et le gonflage. Lien avec ta thèse : données de référence sur les pneus radiaux d'avions de ligne, pour documenter la déflexion et l'empreinte. | AQ25: Oui | AR25: =IF($B25="","",IFERROR(INDEX(Paramètres!$Q$6:$Q$13,MATCH($G25,Paramètres!$P$6:$P$13,0)),"")) -> Modélisation du pneu et du contact | AS25: =IF($B25="","",IFERROR(INDEX(Paramètres!$T$6:$T$11,MATCH($I25,Paramètres!$S$6:$S$11,0)),"")) -> novembre 2026 | AT25: =IF($B25="","",IFERROR(INDEX(Paramètres!$C$27:$C$29,MATCH($H25,Paramètres!$B$27:$B$29,0)),0)) -> 3 | AW25: =IF($B25="","",$B25&".md") -> daugherty2003radial.md | AX25: =IF($B25="","",COUNTIF($I$2:I25,$I25)) -> 6 | AY25: =IF($B25="","",$I25&"-"&$AX25) -> 2-6 | AZ25: https://scholar.google.com/scholar?q=%22A+study+of+the+mechanical+properties+of+modern+radial+aircraft+tires%22 | BA25: =IF($B25="","",$M25+(1000-ROW())/100000) -> 85.00975 | BB25: BIB-024_Daugherty_2003_Mechanical-properties-radial-aircraft-tires.pdf
A26: BIB-025 | B26: he2021maneuvering | C26: =IF($B26="","",IFERROR(LEFT(LEFT($V26,FIND(";",$V26&";")-1),FIND(",",LEFT($V26,FIND(";",$V26&";")-1))-1),LEFT($V26,FIND(";",$V26&";")-1))&IF((LEN($V26)-LEN(SUBSTITUTE($V26,";",""))+1)=1,"",IF((LEN($V26)-LEN(SUBSTITUTE($V26,";",""))+1)=2," & "&IFERROR(LEFT(TRIM(MID($V26,FIND(";",$V26)+1,FIND(";",$V26&";",FIND(";",$V26)+1)-FIND(";",$V26)-1)),FIND(",",TRIM(MID($V26,FIND(";",$V26)+1,FIND(";",$V26&";",FIND(";",$V26)+1)-FIND(";",$V26)-1)))-1),TRIM(MID($V26,FIND(";",$V26)+1,FIND(";",$V26&";",FIND(";",$V26)+1)-FIND(";",$V26)-1)))," et al."))&" ("&$W26&")") -> He et al. (2021) | D26: Analysis of the tire-pavement contact stress characteristics during vehicle maneuvering | E26: =IF(OR($B26="",$AF26=""),"",HYPERLINK(IF(AND(Paramètres!$C$13<>"",$AJ26="Éditeur (abonnement)"),Paramètres!$C$13&$AF26,$AF26),"Ouvrir : "&$AE26)) -> Ouvrir : Texte intégral libre | F26: Oui | G26: 2 | H26: Important | I26: 2 | J26: À lire | K26: =IF($B26="","",IF($J26="Lu","Lu",IF($J26="Écarté","Écarté",IF($I26<Paramètres!$C$8,"EN RETARD",IF($I26=Paramètres!$C$8,"Ce mois-ci",IF($I26=Paramètres!$C$8+1,"Mois prochain","À venir")))))) -> Mois prochain | L26: =IF($B26="","",IF($AL26="Non vérifié","Ne pas citer en l'état : métadonnées non vérifiées",IF($AL26="Partiel","Vérification à compléter avant de citer",IF($O26="Oui","",IF(OR($AJ26="PDF libre",$AJ26="PDF libre (dépôt)"),"PDF libre à télécharger",IF($AJ26="Éditeur (abonnement)","À télécharger via l'accès ENTPE",IF($AJ26="Payant (boutique)","À consulter via l'abonnement de l'école",IF($AJ26="Non diffusé (à demander)","Document à demander (feuille Demandes)","Texte intégral à localiser")))))))) | M26: =IF($B26="","",IF(OR($J26="Lu",$J26="Écarté"),0,IFERROR(INDEX(Paramètres!$C$17:$C$19,MATCH($H26,Paramètres!$B$17:$B$19,0)),0)+Paramètres!$C$20*(7-$I26)+IF($I26<Paramètres!$C$8,Paramètres!$C$21,0)+IF($F26="Oui",Paramètres!$C$22,0)+IF($AL26<>"Vérifié",Paramètres!$C$23,0)+IF(AND($O26<>"Oui",OR($AJ26="PDF libre",$AJ26="PDF libre (dépôt)")),Paramètres!$C$24,0))) -> 95 | O26: =IF($BB26="","Non",HYPERLINK(DossierPDF&$BB26,"Oui")) -> Oui | P26: Non | Q26: Non | T26: JOUR | U26: =IF($B26="","",IFERROR(INDEX(Paramètres!$N$6:$N$13,MATCH($T26,Paramètres!$M$6:$M$13,0)),$T26)) -> Article de revue | V26: He, H.; Li, R.; Yang, Q.; Pei, J.; Guo, F. | W26: 2021 | X26: KSCE Journal of Civil Engineering | Y26: 25 | Z26: 7 | AA26: 2451-2463 | AC26: 10.1007/s12205-021-1306-0 | AE26: Texte intégral libre | AF26: https://doi.org/10.1007/s12205-021-1306-0 | AG26: =IF($AC26="","",HYPERLINK("https://doi.org/"&$AC26,"doi.org")) -> doi.org | AH26: =IF($AZ26="","",HYPERLINK($AZ26,"Scholar")) -> Scholar | AI26: Libre | AJ26: PDF libre | AK26: Libre accès (licence CC BY-NC-ND) chez Springer. | AL26: Vérifié | AM26: OpenAlex (DOI) | AN26: 22/09/2026 | AO26: Modèle éléments finis 3D (ABAQUS) d'un pneu radial de tourisme 205/55 R16 sculpté : contraintes de contact à l'arrêt, en roulement libre, en accélération et en freinage. Lien avec ta thèse : efforts tangentiels et dissymétries, ta perspective n° 2 ; attention, pneu de tourisme et pas de virage dans le résumé. | AQ26: Non | AR26: =IF($B26="","",IFERROR(INDEX(Paramètres!$Q$6:$Q$13,MATCH($G26,Paramètres!$P$6:$P$13,0)),"")) -> Modélisation du pneu et du contact | AS26: =IF($B26="","",IFERROR(INDEX(Paramètres!$T$6:$T$11,MATCH($I26,Paramètres!$S$6:$S$11,0)),"")) -> novembre 2026 | AT26: =IF($B26="","",IFERROR(INDEX(Paramètres!$C$27:$C$29,MATCH($H26,Paramètres!$B$27:$B$29,0)),0)) -> 3 | AW26: =IF($B26="","",$B26&".md") -> he2021maneuvering.md | AX26: =IF($B26="","",COUNTIF($I$2:I26,$I26)) -> 7 | AY26: =IF($B26="","",$I26&"-"&$AX26) -> 2-7 | AZ26: https://scholar.google.com/scholar?q=%22Analysis+of+the+tire-pavement+contact+stress+characteristics+during+vehicle+maneuvering%22 | BA26: =IF($B26="","",$M26+(1000-ROW())/100000) -> 95.00974 | BB26: BIB-025_He-etal_2021_Tire-pavement-contact-stress-maneuvering.pdf
A27: BIB-026 | B27: kongokonde2013aircraft | C27: =IF($B27="","",IFERROR(LEFT(LEFT($V27,FIND(";",$V27&";")-1),FIND(",",LEFT($V27,FIND(";",$V27&";")-1))-1),LEFT($V27,FIND(";",$V27&";")-1))&IF((LEN($V27)-LEN(SUBSTITUTE($V27,";",""))+1)=1,"",IF((LEN($V27)-LEN(SUBSTITUTE($V27,";",""))+1)=2," & "&IFERROR(LEFT(TRIM(MID($V27,FIND(";",$V27)+1,FIND(";",$V27&";",FIND(";",$V27)+1)-FIND(";",$V27)-1)),FIND(",",TRIM(MID($V27,FIND(";",$V27)+1,FIND(";",$V27&";",FIND(";",$V27)+1)-FIND(";",$V27)-1)))-1),TRIM(MID($V27,FIND(";",$V27)+1,FIND(";",$V27&";",FIND(";",$V27)+1)-FIND(";",$V27)-1)))," et al."))&" ("&$W27&")") -> Kongo Kondé et al. (2013) | D27: On the modeling of aircraft tire | E27: =IF(OR($B27="",$AF27=""),"",HYPERLINK(IF(AND(Paramètres!$C$13<>"",$AJ27="Éditeur (abonnement)"),Paramètres!$C$13&$AF27,$AF27),"Ouvrir : "&$AE27)) -> Ouvrir : Page éditeur (DOI) | F27: Non | G27: 2 | H27: Important | I27: 2 | J27: À lire | K27: =IF($B27="","",IF($J27="Lu","Lu",IF($J27="Écarté","Écarté",IF($I27<Paramètres!$C$8,"EN RETARD",IF($I27=Paramètres!$C$8,"Ce mois-ci",IF($I27=Paramètres!$C$8+1,"Mois prochain","À venir")))))) -> Mois prochain | L27: =IF($B27="","",IF($AL27="Non vérifié","Ne pas citer en l'état : métadonnées non vérifiées",IF($AL27="Partiel","Vérification à compléter avant de citer",IF($O27="Oui","",IF(OR($AJ27="PDF libre",$AJ27="PDF libre (dépôt)"),"PDF libre à télécharger",IF($AJ27="Éditeur (abonnement)","À télécharger via l'accès ENTPE",IF($AJ27="Payant (boutique)","À consulter via l'abonnement de l'école",IF($AJ27="Non diffusé (à demander)","Document à demander (feuille Demandes)","Texte intégral à localiser")))))))) | M27: =IF($B27="","",IF(OR($J27="Lu",$J27="Écarté"),0,IFERROR(INDEX(Paramètres!$C$17:$C$19,MATCH($H27,Paramètres!$B$17:$B$19,0)),0)+Paramètres!$C$20*(7-$I27)+IF($I27<Paramètres!$C$8,Paramètres!$C$21,0)+IF($F27="Oui",Paramètres!$C$22,0)+IF($AL27<>"Vérifié",Paramètres!$C$23,0)+IF(AND($O27<>"Oui",OR($AJ27="PDF libre",$AJ27="PDF libre (dépôt)")),Paramètres!$C$24,0))) -> 85 | O27: =IF($BB27="","Non",HYPERLINK(DossierPDF&$BB27,"Oui")) -> Oui | P27: Non | Q27: Non | T27: JOUR | U27: =IF($B27="","",IFERROR(INDEX(Paramètres!$N$6:$N$13,MATCH($T27,Paramètres!$M$6:$M$13,0)),$T27)) -> Article de revue | V27: Kongo Kondé, A.; Rosu, I.; Lebon, F.; Brardo, O.; Devésa, B. | W27: 2013 | X27: Aerospace Science and Technology | Y27: 27 | Z27: 1 | AA27: 67-75 | AC27: 10.1016/j.ast.2012.06.008 | AE27: Page éditeur (DOI) | AF27: https://doi.org/10.1016/j.ast.2012.06.008 | AG27: =IF($AC27="","",HYPERLINK("https://doi.org/"&$AC27,"doi.org")) -> doi.org | AH27: =IF($AZ27="","",HYPERLINK($AZ27,"Scholar")) -> Scholar | AI27: Payant | AJ27: Éditeur (abonnement) | AK27: Elsevier : abonnement ENTPE ; notice HAL hal-00833556 (texte intégral à vérifier). | AL27: Vérifié | AM27: Crossref | AN27: 22/09/2026 | AO27: Modélisation éléments finis d'un pneu d'avion (grandes déformations, renforts composites) confrontée à des essais. Lien avec ta thèse : référence directe pour les spécificités aéronautiques de l'axe 2 (gonflage élevé, forte déflexion). | AP27: Kongo Kondé (2011) ; Rosu et al. (2018) | AQ27: Non | AR27: =IF($B27="","",IFERROR(INDEX(Paramètres!$Q$6:$Q$13,MATCH($G27,Paramètres!$P$6:$P$13,0)),"")) -> Modélisation du pneu et du contact | AS27: =IF($B27="","",IFERROR(INDEX(Paramètres!$T$6:$T$11,MATCH($I27,Paramètres!$S$6:$S$11,0)),"")) -> novembre 2026 | AT27: =IF($B27="","",IFERROR(INDEX(Paramètres!$C$27:$C$29,MATCH($H27,Paramètres!$B$27:$B$29,0)),0)) -> 3 | AW27: =IF($B27="","",$B27&".md") -> kongokonde2013aircraft.md | AX27: =IF($B27="","",COUNTIF($I$2:I27,$I27)) -> 8 | AY27: =IF($B27="","",$I27&"-"&$AX27) -> 2-8 | AZ27: https://scholar.google.com/scholar?q=%22On+the+modeling+of+aircraft+tire%22 | BA27: =IF($B27="","",$M27+(1000-ROW())/100000) -> 85.00973 | BB27: BIB-026_KongoKonde-etal_2013_Modeling-aircraft-tire.pdf
A28: BIB-027 | B28: wang2012tyre | C28: =IF($B28="","",IFERROR(LEFT(LEFT($V28,FIND(";",$V28&";")-1),FIND(",",LEFT($V28,FIND(";",$V28&";")-1))-1),LEFT($V28,FIND(";",$V28&";")-1))&IF((LEN($V28)-LEN(SUBSTITUTE($V28,";",""))+1)=1,"",IF((LEN($V28)-LEN(SUBSTITUTE($V28,";",""))+1)=2," & "&IFERROR(LEFT(TRIM(MID($V28,FIND(";",$V28)+1,FIND(";",$V28&";",FIND(";",$V28)+1)-FIND(";",$V28)-1)),FIND(",",TRIM(MID($V28,FIND(";",$V28)+1,FIND(";",$V28&";",FIND(";",$V28)+1)-FIND(";",$V28)-1)))-1),TRIM(MID($V28,FIND(";",$V28)+1,FIND(";",$V28&";",FIND(";",$V28)+1)-FIND(";",$V28)-1)))," et al."))&" ("&$W28&")") -> Wang et al. (2012) | D28: Simulation of tyre–pavement interaction for predicting contact stresses at static and various rolling conditions | E28: =IF(OR($B28="",$AF28=""),"",HYPERLINK(IF(AND(Paramètres!$C$13<>"",$AJ28="Éditeur (abonnement)"),Paramètres!$C$13&$AF28,$AF28),"Ouvrir : "&$AE28)) -> Ouvrir : Page éditeur (DOI) | F28: Non | G28: 2 | H28: Important | I28: 2 | J28: À lire | K28: =IF($B28="","",IF($J28="Lu","Lu",IF($J28="Écarté","Écarté",IF($I28<Paramètres!$C$8,"EN RETARD",IF($I28=Paramètres!$C$8,"Ce mois-ci",IF($I28=Paramètres!$C$8+1,"Mois prochain","À venir")))))) -> Mois prochain | L28: =IF($B28="","",IF($AL28="Non vérifié","Ne pas citer en l'état : métadonnées non vérifiées",IF($AL28="Partiel","Vérification à compléter avant de citer",IF($O28="Oui","",IF(OR($AJ28="PDF libre",$AJ28="PDF libre (dépôt)"),"PDF libre à télécharger",IF($AJ28="Éditeur (abonnement)","À télécharger via l'accès ENTPE",IF($AJ28="Payant (boutique)","À consulter via l'abonnement de l'école",IF($AJ28="Non diffusé (à demander)","Document à demander (feuille Demandes)","Texte intégral à localiser")))))))) | M28: =IF($B28="","",IF(OR($J28="Lu",$J28="Écarté"),0,IFERROR(INDEX(Paramètres!$C$17:$C$19,MATCH($H28,Paramètres!$B$17:$B$19,0)),0)+Paramètres!$C$20*(7-$I28)+IF($I28<Paramètres!$C$8,Paramètres!$C$21,0)+IF($F28="Oui",Paramètres!$C$22,0)+IF($AL28<>"Vérifié",Paramètres!$C$23,0)+IF(AND($O28<>"Oui",OR($AJ28="PDF libre",$AJ28="PDF libre (dépôt)")),Paramètres!$C$24,0))) -> 85 | O28: =IF($BB28="","Non",HYPERLINK(DossierPDF&$BB28,"Oui")) -> Oui | P28: Non | Q28: Non | T28: JOUR | U28: =IF($B28="","",IFERROR(INDEX(Paramètres!$N$6:$N$13,MATCH($T28,Paramètres!$M$6:$M$13,0)),$T28)) -> Article de revue | V28: Wang, H.; Al-Qadi, I. L.; Stanciulescu, I. | W28: 2012 | X28: International Journal of Pavement Engineering | Y28: 13 | Z28: 4 | AA28: 310-321 | AC28: 10.1080/10298436.2011.565767 | AE28: Page éditeur (DOI) | AF28: https://doi.org/10.1080/10298436.2011.565767 | AG28: =IF($AC28="","",HYPERLINK("https://doi.org/"&$AC28,"doi.org")) -> doi.org | AH28: =IF($AZ28="","",HYPERLINK($AZ28,"Scholar")) -> Scholar | AI28: Payant | AJ28: Éditeur (abonnement) | AK28: Taylor & Francis : abonnement ENTPE. | AL28: Vérifié | AM28: Crossref | AN28: 22/09/2026 | AO28: Modèle éléments finis pneu-chaussée prédisant les contraintes de contact en statique et en roulement (libre, freinage, accélération, virage). Lien avec ta thèse : référence méthodologique pour construire un modèle de pneu couplé à la chaussée. | AP28: Wang & Al-Qadi (2009) | AQ28: Non | AR28: =IF($B28="","",IFERROR(INDEX(Paramètres!$Q$6:$Q$13,MATCH($G28,Paramètres!$P$6:$P$13,0)),"")) -> Modélisation du pneu et du contact | AS28: =IF($B28="","",IFERROR(INDEX(Paramètres!$T$6:$T$11,MATCH($I28,Paramètres!$S$6:$S$11,0)),"")) -> novembre 2026 | AT28: =IF($B28="","",IFERROR(INDEX(Paramètres!$C$27:$C$29,MATCH($H28,Paramètres!$B$27:$B$29,0)),0)) -> 3 | AW28: =IF($B28="","",$B28&".md") -> wang2012tyre.md | AX28: =IF($B28="","",COUNTIF($I$2:I28,$I28)) -> 9 | AY28: =IF($B28="","",$I28&"-"&$AX28) -> 2-9 | AZ28: https://scholar.google.com/scholar?q=%22Simulation+of+tyre%E2%80%93pavement+interaction+for+predicting+contact+stresses+at+static+and+various+rolling+conditions%22 | BA28: =IF($B28="","",$M28+(1000-ROW())/100000) -> 85.00972 | BB28: BIB-027_Wang-etal_2012_Tyre-pavement-interaction-contact-stresses.pdf
A29: BIB-028 | B29: xie2019tyretypes | C29: =IF($B29="","",IFERROR(LEFT(LEFT($V29,FIND(";",$V29&";")-1),FIND(",",LEFT($V29,FIND(";",$V29&";")-1))-1),LEFT($V29,FIND(";",$V29&";")-1))&IF((LEN($V29)-LEN(SUBSTITUTE($V29,";",""))+1)=1,"",IF((LEN($V29)-LEN(SUBSTITUTE($V29,";",""))+1)=2," & "&IFERROR(LEFT(TRIM(MID($V29,FIND(";",$V29)+1,FIND(";",$V29&";",FIND(";",$V29)+1)-FIND(";",$V29)-1)),FIND(",",TRIM(MID($V29,FIND(";",$V29)+1,FIND(";",$V29&";",FIND(";",$V29)+1)-FIND(";",$V29)-1)))-1),TRIM(MID($V29,FIND(";",$V29)+1,FIND(";",$V29&";",FIND(";",$V29)+1)-FIND(";",$V29)-1)))," et al."))&" ("&$W29&")") -> Xie & Yang (2019) | D29: Tyre–pavement contact stress distribution considering tyre types | E29: =IF(OR($B29="",$AF29=""),"",HYPERLINK(IF(AND(Paramètres!$C$13<>"",$AJ29="Éditeur (abonnement)"),Paramètres!$C$13&$AF29,$AF29),"Ouvrir : "&$AE29)) -> Ouvrir : Page éditeur (DOI) | F29: Oui | G29: 2 | H29: Important | I29: 2 | J29: À lire | K29: =IF($B29="","",IF($J29="Lu","Lu",IF($J29="Écarté","Écarté",IF($I29<Paramètres!$C$8,"EN RETARD",IF($I29=Paramètres!$C$8,"Ce mois-ci",IF($I29=Paramètres!$C$8+1,"Mois prochain","À venir")))))) -> Mois prochain | L29: =IF($B29="","",IF($AL29="Non vérifié","Ne pas citer en l'état : métadonnées non vérifiées",IF($AL29="Partiel","Vérification à compléter avant de citer",IF($O29="Oui","",IF(OR($AJ29="PDF libre",$AJ29="PDF libre (dépôt)"),"PDF libre à télécharger",IF($AJ29="Éditeur (abonnement)","À télécharger via l'accès ENTPE",IF($AJ29="Payant (boutique)","À consulter via l'abonnement de l'école",IF($AJ29="Non diffusé (à demander)","Document à demander (feuille Demandes)","Texte intégral à localiser")))))))) | M29: =IF($B29="","",IF(OR($J29="Lu",$J29="Écarté"),0,IFERROR(INDEX(Paramètres!$C$17:$C$19,MATCH($H29,Paramètres!$B$17:$B$19,0)),0)+Paramètres!$C$20*(7-$I29)+IF($I29<Paramètres!$C$8,Paramètres!$C$21,0)+IF($F29="Oui",Paramètres!$C$22,0)+IF($AL29<>"Vérifié",Paramètres!$C$23,0)+IF(AND($O29<>"Oui",OR($AJ29="PDF libre",$AJ29="PDF libre (dépôt)")),Paramètres!$C$24,0))) -> 95 | O29: =IF($BB29="","Non",HYPERLINK(DossierPDF&$BB29,"Oui")) -> Oui | P29: Non | Q29: Non | T29: JOUR | U29: =IF($B29="","",IFERROR(INDEX(Paramètres!$N$6:$N$13,MATCH($T29,Paramètres!$M$6:$M$13,0)),$T29)) -> Article de revue | V29: Xie, Y.; Yang, Q. | W29: 2019 | X29: Road Materials and Pavement Design | Y29: 20 | Z29: 8 | AA29: 1899-1911 | AC29: 10.1080/14680629.2018.1473285 | AE29: Page éditeur (DOI) | AF29: https://doi.org/10.1080/14680629.2018.1473285 | AG29: =IF($AC29="","",HYPERLINK("https://doi.org/"&$AC29,"doi.org")) -> doi.org | AH29: =IF($AZ29="","",HYPERLINK($AZ29,"Scholar")) -> Scholar | AI29: Payant | AJ29: Éditeur (abonnement) | AK29: Taylor & Francis : abonnement ENTPE. | AL29: Vérifié | AM29: OpenAlex (DOI) | AN29: 22/09/2026 | AO29: Modélisation par éléments finis de pneus de camion diagonal et radial : distribution de la contrainte verticale selon la charge, avec passage du profil en n au profil en M pour le pneu diagonal. Lien avec ta thèse : base de ton §1.3.3 (caoutchouc élastique linéaire, charges limitées à 37,5 kN). Année : volume 20 (2019), mise en ligne en 2018. | AQ29: Non | AR29: =IF($B29="","",IFERROR(INDEX(Paramètres!$Q$6:$Q$13,MATCH($G29,Paramètres!$P$6:$P$13,0)),"")) -> Modélisation du pneu et du contact | AS29: =IF($B29="","",IFERROR(INDEX(Paramètres!$T$6:$T$11,MATCH($I29,Paramètres!$S$6:$S$11,0)),"")) -> novembre 2026 | AT29: =IF($B29="","",IFERROR(INDEX(Paramètres!$C$27:$C$29,MATCH($H29,Paramètres!$B$27:$B$29,0)),0)) -> 3 | AW29: =IF($B29="","",$B29&".md") -> xie2019tyretypes.md | AX29: =IF($B29="","",COUNTIF($I$2:I29,$I29)) -> 10 | AY29: =IF($B29="","",$I29&"-"&$AX29) -> 2-10 | AZ29: https://scholar.google.com/scholar?q=%22Tyre%E2%80%93pavement+contact+stress+distribution+considering+tyre+types%22 | BA29: =IF($B29="","",$M29+(1000-ROW())/100000) -> 95.00971 | BB29: BIB-028_Xie-Yang_2019_Contact-stress-distribution-tyre-types.pdf
A30: BIB-029 | B30: huet1963impedance | C30: =IF($B30="","",IFERROR(LEFT(LEFT($V30,FIND(";",$V30&";")-1),FIND(",",LEFT($V30,FIND(";",$V30&";")-1))-1),LEFT($V30,FIND(";",$V30&";")-1))&IF((LEN($V30)-LEN(SUBSTITUTE($V30,";",""))+1)=1,"",IF((LEN($V30)-LEN(SUBSTITUTE($V30,";",""))+1)=2," & "&IFERROR(LEFT(TRIM(MID($V30,FIND(";",$V30)+1,FIND(";",$V30&";",FIND(";",$V30)+1)-FIND(";",$V30)-1)),FIND(",",TRIM(MID($V30,FIND(";",$V30)+1,FIND(";",$V30&";",FIND(";",$V30)+1)-FIND(";",$V30)-1)))-1),TRIM(MID($V30,FIND(";",$V30)+1,FIND(";",$V30&";",FIND(";",$V30)+1)-FIND(";",$V30)-1)))," et al."))&" ("&$W30&")") -> Huet (1963) | D30: Étude par une méthode d'impédance du comportement viscoélastique des matériaux hydrocarbonés | E30: =IF(OR($B30="",$AF30=""),"",HYPERLINK(IF(AND(Paramètres!$C$13<>"",$AJ30="Éditeur (abonnement)"),Paramètres!$C$13&$AF30,$AF30),"Ouvrir : "&$AE30)) -> Ouvrir : Recherche Google Scholar | F30: Oui | G30: 3 | H30: Important | I30: 2 | J30: À lire | K30: =IF($B30="","",IF($J30="Lu","Lu",IF($J30="Écarté","Écarté",IF($I30<Paramètres!$C$8,"EN RETARD",IF($I30=Paramètres!$C$8,"Ce mois-ci",IF($I30=Paramètres!$C$8+1,"Mois prochain","À venir")))))) -> Mois prochain | L30: =IF($B30="","",IF($AL30="Non vérifié","Ne pas citer en l'état : métadonnées non vérifiées",IF($AL30="Partiel","Vérification à compléter avant de citer",IF($O30="Oui","",IF(OR($AJ30="PDF libre",$AJ30="PDF libre (dépôt)"),"PDF libre à télécharger",IF($AJ30="Éditeur (abonnement)","À télécharger via l'accès ENTPE",IF($AJ30="Payant (boutique)","À consulter via l'abonnement de l'école",IF($AJ30="Non diffusé (à demander)","Document à demander (feuille Demandes)","Texte intégral à localiser")))))))) -> Vérification à compléter avant de citer | M30: =IF($B30="","",IF(OR($J30="Lu",$J30="Écarté"),0,IFERROR(INDEX(Paramètres!$C$17:$C$19,MATCH($H30,Paramètres!$B$17:$B$19,0)),0)+Paramètres!$C$20*(7-$I30)+IF($I30<Paramètres!$C$8,Paramètres!$C$21,0)+IF($F30="Oui",Paramètres!$C$22,0)+IF($AL30<>"Vérifié",Paramètres!$C$23,0)+IF(AND($O30<>"Oui",OR($AJ30="PDF libre",$AJ30="PDF libre (dépôt)")),Paramètres!$C$24,0))) -> 110 | O30: =IF($BB30="","Non",HYPERLINK(DossierPDF&$BB30,"Oui")) -> Oui | P30: Non | Q30: Non | T30: THES | U30: =IF($B30="","",IFERROR(INDEX(Paramètres!$N$6:$N$13,MATCH($T30,Paramètres!$M$6:$M$13,0)),$T30)) -> Thèse | V30: Huet, C. | W30: 1963 | AB30: Faculté des sciences de l'Université de Paris | AD30: Thèse de docteur-ingénieur | AE30: Recherche Google Scholar | AF30: https://scholar.google.com/scholar?q=%22%C3%89tude+par+une+m%C3%A9thode+d%27imp%C3%A9dance+du+comportement+visco%C3%A9lastique+des+mat%C3%A9riaux+hydrocarbon%C3%A9s%22 | AG30: =IF($AC30="","",HYPERLINK("https://doi.org/"&$AC30,"doi.org")) | AH30: =IF($AZ30="","",HYPERLINK($AZ30,"Scholar")) -> Scholar | AI30: Restreint | AJ30: Non diffusé (à demander) | AK30: Aucune version numérique connue : PEB ou bibliothèque de l'Université Gustave Eiffel. | AL30: Partiel | AM30: Citations secondaires concordantes (aucune notice de catalogue consultable en ligne) | AN30: 22/09/2026 | AO30: Thèse fondatrice : modèle à deux éléments paraboliques en série avec un ressort, identifié par une méthode d'impédance. Lien avec ta thèse : origine du modèle de Huet de ton chapitre 1. NON VÉRIFIÉ (partiel) : titre, grade, faculté et année relevés dans plusieurs citations concordantes ; aucune notice de catalogue ni exemplaire consultés. | AP30: Sayegh (1965) ; Olard & Di Benedetto (2003) | AQ30: Oui | AR30: =IF($B30="","",IFERROR(INDEX(Paramètres!$Q$6:$Q$13,MATCH($G30,Paramètres!$P$6:$P$13,0)),"")) -> Viscoélasticité des enrobés | AS30: =IF($B30="","",IFERROR(INDEX(Paramètres!$T$6:$T$11,MATCH($I30,Paramètres!$S$6:$S$11,0)),"")) -> novembre 2026 | AT30: =IF($B30="","",IFERROR(INDEX(Paramètres!$C$27:$C$29,MATCH($H30,Paramètres!$B$27:$B$29,0)),0)) -> 3 | AW30: =IF($B30="","",$B30&".md") -> huet1963impedance.md | AX30: =IF($B30="","",COUNTIF($I$2:I30,$I30)) -> 11 | AY30: =IF($B30="","",$I30&"-"&$AX30) -> 2-11 | AZ30: https://scholar.google.com/scholar?q=%22%C3%89tude+par+une+m%C3%A9thode+d%27imp%C3%A9dance+du+comportement+visco%C3%A9lastique+des+mat%C3%A9riaux+hydrocarbon%C3%A9s%22 | BA30: =IF($B30="","",$M30+(1000-ROW())/100000) -> 110.0097 | BB30: BIB-029_Huet_1963_Methode-impedance-viscoelasticite-materiaux-hydrocarbones.pdf
A31: BIB-030 | B31: park1999prony | C31: =IF($B31="","",IFERROR(LEFT(LEFT($V31,FIND(";",$V31&";")-1),FIND(",",LEFT($V31,FIND(";",$V31&";")-1))-1),LEFT($V31,FIND(";",$V31&";")-1))&IF((LEN($V31)-LEN(SUBSTITUTE($V31,";",""))+1)=1,"",IF((LEN($V31)-LEN(SUBSTITUTE($V31,";",""))+1)=2," & "&IFERROR(LEFT(TRIM(MID($V31,FIND(";",$V31)+1,FIND(";",$V31&";",FIND(";",$V31)+1)-FIND(";",$V31)-1)),FIND(",",TRIM(MID($V31,FIND(";",$V31)+1,FIND(";",$V31&";",FIND(";",$V31)+1)-FIND(";",$V31)-1)))-1),TRIM(MID($V31,FIND(";",$V31)+1,FIND(";",$V31&";",FIND(";",$V31)+1)-FIND(";",$V31)-1)))," et al."))&" ("&$W31&")") -> Park & Schapery (1999) | D31: Methods of interconversion between linear viscoelastic material functions. Part I—A numerical method based on Prony series | E31: =IF(OR($B31="",$AF31=""),"",HYPERLINK(IF(AND(Paramètres!$C$13<>"",$AJ31="Éditeur (abonnement)"),Paramètres!$C$13&$AF31,$AF31),"Ouvrir : "&$AE31)) -> Ouvrir : Page éditeur (DOI) | F31: Non | G31: 3 | H31: Important | I31: 2 | J31: À lire | K31: =IF($B31="","",IF($J31="Lu","Lu",IF($J31="Écarté","Écarté",IF($I31<Paramètres!$C$8,"EN RETARD",IF($I31=Paramètres!$C$8,"Ce mois-ci",IF($I31=Paramètres!$C$8+1,"Mois prochain","À venir")))))) -> Mois prochain | L31: =IF($B31="","",IF($AL31="Non vérifié","Ne pas citer en l'état : métadonnées non vérifiées",IF($AL31="Partiel","Vérification à compléter avant de citer",IF($O31="Oui","",IF(OR($AJ31="PDF libre",$AJ31="PDF libre (dépôt)"),"PDF libre à télécharger",IF($AJ31="Éditeur (abonnement)","À télécharger via l'accès ENTPE",IF($AJ31="Payant (boutique)","À consulter via l'abonnement de l'école",IF($AJ31="Non diffusé (à demander)","Document à demander (feuille Demandes)","Texte intégral à localiser")))))))) | M31: =IF($B31="","",IF(OR($J31="Lu",$J31="Écarté"),0,IFERROR(INDEX(Paramètres!$C$17:$C$19,MATCH($H31,Paramètres!$B$17:$B$19,0)),0)+Paramètres!$C$20*(7-$I31)+IF($I31<Paramètres!$C$8,Paramètres!$C$21,0)+IF($F31="Oui",Paramètres!$C$22,0)+IF($AL31<>"Vérifié",Paramètres!$C$23,0)+IF(AND($O31<>"Oui",OR($AJ31="PDF libre",$AJ31="PDF libre (dépôt)")),Paramètres!$C$24,0))) -> 85 | O31: =IF($BB31="","Non",HYPERLINK(DossierPDF&$BB31,"Oui")) -> Oui | P31: Non | Q31: Non | T31: JOUR | U31: =IF($B31="","",IFERROR(INDEX(Paramètres!$N$6:$N$13,MATCH($T31,Paramètres!$M$6:$M$13,0)),$T31)) -> Article de revue | V31: Park, S. W.; Schapery, R. A. | W31: 1999 | X31: International Journal of Solids and Structures | Y31: 36 | Z31: 11 | AA31: 1653-1675 | AC31: 10.1016/S0020-7683(98)00055-9 | AE31: Page éditeur (DOI) | AF31: https://doi.org/10.1016/S0020-7683(98)00055-9 | AG31: =IF($AC31="","",HYPERLINK("https://doi.org/"&$AC31,"doi.org")) -> doi.org | AH31: =IF($AZ31="","",HYPERLINK($AZ31,"Scholar")) -> Scholar | AI31: Payant | AJ31: Éditeur (abonnement) | AK31: Elsevier : abonnement ENTPE. | AL31: Vérifié | AM31: OpenAlex (DOI) | AN31: 22/09/2026 | AO31: Méthode numérique d'interconversion entre fonctions viscoélastiques (fluage, relaxation, module complexe) à l'aide de séries de Prony. Lien avec ta thèse : outil pour passer du 2S2P1D aux paramètres de Prony attendus par COMSOL pour G(t) et K(t). | AP31: Tiouajni et al. (2011) ; Tschoegl (1989) | AQ31: Non | AR31: =IF($B31="","",IFERROR(INDEX(Paramètres!$Q$6:$Q$13,MATCH($G31,Paramètres!$P$6:$P$13,0)),"")) -> Viscoélasticité des enrobés | AS31: =IF($B31="","",IFERROR(INDEX(Paramètres!$T$6:$T$11,MATCH($I31,Paramètres!$S$6:$S$11,0)),"")) -> novembre 2026 | AT31: =IF($B31="","",IFERROR(INDEX(Paramètres!$C$27:$C$29,MATCH($H31,Paramètres!$B$27:$B$29,0)),0)) -> 3 | AW31: =IF($B31="","",$B31&".md") -> park1999prony.md | AX31: =IF($B31="","",COUNTIF($I$2:I31,$I31)) -> 12 | AY31: =IF($B31="","",$I31&"-"&$AX31) -> 2-12 | AZ31: https://scholar.google.com/scholar?q=%22Methods+of+interconversion+between+linear+viscoelastic+material+functions.+Part+I%E2%80%94A+numerical+method+based+on+Prony+series%22 | BA31: =IF($B31="","",$M31+(1000-ROW())/100000) -> 85.00969 | BB31: BIB-030_Park-Schapery_1999_Interconversion-viscoelastic-functions-Prony.pdf
A32: BIB-031 | B32: sayegh1965viscoelastiques | C32: =IF($B32="","",IFERROR(LEFT(LEFT($V32,FIND(";",$V32&";")-1),FIND(",",LEFT($V32,FIND(";",$V32&";")-1))-1),LEFT($V32,FIND(";",$V32&";")-1))&IF((LEN($V32)-LEN(SUBSTITUTE($V32,";",""))+1)=1,"",IF((LEN($V32)-LEN(SUBSTITUTE($V32,";",""))+1)=2," & "&IFERROR(LEFT(TRIM(MID($V32,FIND(";",$V32)+1,FIND(";",$V32&";",FIND(";",$V32)+1)-FIND(";",$V32)-1)),FIND(",",TRIM(MID($V32,FIND(";",$V32)+1,FIND(";",$V32&";",FIND(";",$V32)+1)-FIND(";",$V32)-1)))-1),TRIM(MID($V32,FIND(";",$V32)+1,FIND(";",$V32&";",FIND(";",$V32)+1)-FIND(";",$V32)-1)))," et al."))&" ("&$W32&")") -> Sayegh (1965) | D32: Contribution à l'étude des propriétés viscoélastiques des bitumes purs et des bétons bitumineux | E32: =IF(OR($B32="",$AF32=""),"",HYPERLINK(IF(AND(Paramètres!$C$13<>"",$AJ32="Éditeur (abonnement)"),Paramètres!$C$13&$AF32,$AF32),"Ouvrir : "&$AE32)) -> Ouvrir : Recherche Google Scholar | F32: Oui | G32: 3 | H32: Important | I32: 2 | J32: À lire | K32: =IF($B32="","",IF($J32="Lu","Lu",IF($J32="Écarté","Écarté",IF($I32<Paramètres!$C$8,"EN RETARD",IF($I32=Paramètres!$C$8,"Ce mois-ci",IF($I32=Paramètres!$C$8+1,"Mois prochain","À venir")))))) -> Mois prochain | L32: =IF($B32="","",IF($AL32="Non vérifié","Ne pas citer en l'état : métadonnées non vérifiées",IF($AL32="Partiel","Vérification à compléter avant de citer",IF($O32="Oui","",IF(OR($AJ32="PDF libre",$AJ32="PDF libre (dépôt)"),"PDF libre à télécharger",IF($AJ32="Éditeur (abonnement)","À télécharger via l'accès ENTPE",IF($AJ32="Payant (boutique)","À consulter via l'abonnement de l'école",IF($AJ32="Non diffusé (à demander)","Document à demander (feuille Demandes)","Texte intégral à localiser")))))))) -> Vérification à compléter avant de citer | M32: =IF($B32="","",IF(OR($J32="Lu",$J32="Écarté"),0,IFERROR(INDEX(Paramètres!$C$17:$C$19,MATCH($H32,Paramètres!$B$17:$B$19,0)),0)+Paramètres!$C$20*(7-$I32)+IF($I32<Paramètres!$C$8,Paramètres!$C$21,0)+IF($F32="Oui",Paramètres!$C$22,0)+IF($AL32<>"Vérifié",Paramètres!$C$23,0)+IF(AND($O32<>"Oui",OR($AJ32="PDF libre",$AJ32="PDF libre (dépôt)")),Paramètres!$C$24,0))) -> 110 | O32: =IF($BB32="","Non",HYPERLINK(DossierPDF&$BB32,"Oui")) -> Non | P32: Non | Q32: Non | T32: THES | U32: =IF($B32="","",IFERROR(INDEX(Paramètres!$N$6:$N$13,MATCH($T32,Paramètres!$M$6:$M$13,0)),$T32)) -> Thèse | V32: Sayegh, G. | W32: 1965 | AB32: Faculté des sciences de Paris | AD32: Thèse de docteur-ingénieur | AE32: Recherche Google Scholar | AF32: https://scholar.google.com/scholar?q=%22Contribution+%C3%A0+l%27%C3%A9tude+des+propri%C3%A9t%C3%A9s+visco%C3%A9lastiques+des+bitumes+purs+et+des+b%C3%A9tons+bitumineux%22 | AG32: =IF($AC32="","",HYPERLINK("https://doi.org/"&$AC32,"doi.org")) | AH32: =IF($AZ32="","",HYPERLINK($AZ32,"Scholar")) -> Scholar | AI32: Restreint | AJ32: Non diffusé (à demander) | AK32: Aucune version numérique connue : PEB ou bibliothèque de l'Université Gustave Eiffel. | AL32: Partiel | AM32: Citations secondaires concordantes (aucune notice de catalogue consultable en ligne) | AN32: 22/09/2026 | AO32: Thèse qui ajoute au modèle de Huet un ressort de module statique : c'est le modèle de Huet-Sayegh. Lien avec ta thèse : étape entre Huet et le 2S2P1D. NON VÉRIFIÉ (partiel) : titre, grade, faculté et année relevés dans des citations concordantes ; aucune notice de catalogue ni exemplaire consultés. | AP32: Huet (1963) ; Olard & Di Benedetto (2003) | AQ32: Oui | AR32: =IF($B32="","",IFERROR(INDEX(Paramètres!$Q$6:$Q$13,MATCH($G32,Paramètres!$P$6:$P$13,0)),"")) -> Viscoélasticité des enrobés | AS32: =IF($B32="","",IFERROR(INDEX(Paramètres!$T$6:$T$11,MATCH($I32,Paramètres!$S$6:$S$11,0)),"")) -> novembre 2026 | AT32: =IF($B32="","",IFERROR(INDEX(Paramètres!$C$27:$C$29,MATCH($H32,Paramètres!$B$27:$B$29,0)),0)) -> 3 | AW32: =IF($B32="","",$B32&".md") -> sayegh1965viscoelastiques.md | AX32: =IF($B32="","",COUNTIF($I$2:I32,$I32)) -> 13 | AY32: =IF($B32="","",$I32&"-"&$AX32) -> 2-13 | AZ32: https://scholar.google.com/scholar?q=%22Contribution+%C3%A0+l%27%C3%A9tude+des+propri%C3%A9t%C3%A9s+visco%C3%A9lastiques+des+bitumes+purs+et+des+b%C3%A9tons+bitumineux%22 | BA32: =IF($B32="","",$M32+(1000-ROW())/100000) -> 110.00968
A33: BIB-032 | B33: behroozi2012aircraft | C33: =IF($B33="","",IFERROR(LEFT(LEFT($V33,FIND(";",$V33&";")-1),FIND(",",LEFT($V33,FIND(";",$V33&";")-1))-1),LEFT($V33,FIND(";",$V33&";")-1))&IF((LEN($V33)-LEN(SUBSTITUTE($V33,";",""))+1)=1,"",IF((LEN($V33)-LEN(SUBSTITUTE($V33,";",""))+1)=2," & "&IFERROR(LEFT(TRIM(MID($V33,FIND(";",$V33)+1,FIND(";",$V33&";",FIND(";",$V33)+1)-FIND(";",$V33)-1)),FIND(",",TRIM(MID($V33,FIND(";",$V33)+1,FIND(";",$V33&";",FIND(";",$V33)+1)-FIND(";",$V33)-1)))-1),TRIM(MID($V33,FIND(";",$V33)+1,FIND(";",$V33&";",FIND(";",$V33)+1)-FIND(";",$V33)-1)))," et al."))&" ("&$W33&")") -> Behroozi et al. (2012) | D33: Finite element analysis of aircraft tyre – Effect of model complexity on tyre performance characteristics | E33: =IF(OR($B33="",$AF33=""),"",HYPERLINK(IF(AND(Paramètres!$C$13<>"",$AJ33="Éditeur (abonnement)"),Paramètres!$C$13&$AF33,$AF33),"Ouvrir : "&$AE33)) -> Ouvrir : Page éditeur (DOI) | F33: Non | G33: 2 | H33: A consulter | I33: 2 | J33: À lire | K33: =IF($B33="","",IF($J33="Lu","Lu",IF($J33="Écarté","Écarté",IF($I33<Paramètres!$C$8,"EN RETARD",IF($I33=Paramètres!$C$8,"Ce mois-ci",IF($I33=Paramètres!$C$8+1,"Mois prochain","À venir")))))) -> Mois prochain | L33: =IF($B33="","",IF($AL33="Non vérifié","Ne pas citer en l'état : métadonnées non vérifiées",IF($AL33="Partiel","Vérification à compléter avant de citer",IF($O33="Oui","",IF(OR($AJ33="PDF libre",$AJ33="PDF libre (dépôt)"),"PDF libre à télécharger",IF($AJ33="Éditeur (abonnement)","À télécharger via l'accès ENTPE",IF($AJ33="Payant (boutique)","À consulter via l'abonnement de l'école",IF($AJ33="Non diffusé (à demander)","Document à demander (feuille Demandes)","Texte intégral à localiser")))))))) | M33: =IF($B33="","",IF(OR($J33="Lu",$J33="Écarté"),0,IFERROR(INDEX(Paramètres!$C$17:$C$19,MATCH($H33,Paramètres!$B$17:$B$19,0)),0)+Paramètres!$C$20*(7-$I33)+IF($I33<Paramètres!$C$8,Paramètres!$C$21,0)+IF($F33="Oui",Paramètres!$C$22,0)+IF($AL33<>"Vérifié",Paramètres!$C$23,0)+IF(AND($O33<>"Oui",OR($AJ33="PDF libre",$AJ33="PDF libre (dépôt)")),Paramètres!$C$24,0))) -> 55 | O33: =IF($BB33="","Non",HYPERLINK(DossierPDF&$BB33,"Oui")) -> Oui | P33: Non | Q33: Non | T33: JOUR | U33: =IF($B33="","",IFERROR(INDEX(Paramètres!$N$6:$N$13,MATCH($T33,Paramètres!$M$6:$M$13,0)),$T33)) -> Article de revue | V33: Behroozi, M.; Olatunbosun, O. A.; Ding, W. | W33: 2012 | X33: Materials & Design | Y33: 35 | AA33: 810-819 | AC33: 10.1016/j.matdes.2011.05.055 | AE33: Page éditeur (DOI) | AF33: https://doi.org/10.1016/j.matdes.2011.05.055 | AG33: =IF($AC33="","",HYPERLINK("https://doi.org/"&$AC33,"doi.org")) -> doi.org | AH33: =IF($AZ33="","",HYPERLINK($AZ33,"Scholar")) -> Scholar | AI33: Payant | AJ33: Éditeur (abonnement) | AK33: Elsevier : abonnement ENTPE. | AL33: Vérifié | AM33: Crossref | AN33: 22/09/2026 | AO33: Effet du niveau de détail d'un modèle éléments finis de pneu d'avion sur ses caractéristiques calculées. Lien avec ta thèse : aide à choisir la complexité d'un futur modèle de pneu d'avion. | AQ33: Non | AR33: =IF($B33="","",IFERROR(INDEX(Paramètres!$Q$6:$Q$13,MATCH($G33,Paramètres!$P$6:$P$13,0)),"")) -> Modélisation du pneu et du contact | AS33: =IF($B33="","",IFERROR(INDEX(Paramètres!$T$6:$T$11,MATCH($I33,Paramètres!$S$6:$S$11,0)),"")) -> novembre 2026 | AT33: =IF($B33="","",IFERROR(INDEX(Paramètres!$C$27:$C$29,MATCH($H33,Paramètres!$B$27:$B$29,0)),0)) -> 1 | AW33: =IF($B33="","",$B33&".md") -> behroozi2012aircraft.md | AX33: =IF($B33="","",COUNTIF($I$2:I33,$I33)) -> 14 | AY33: =IF($B33="","",$I33&"-"&$AX33) -> 2-14 | AZ33: https://scholar.google.com/scholar?q=%22Finite+element+analysis+of+aircraft+tyre+%E2%80%93+Effect+of+model+complexity+on+tyre+performance+characteristics%22 | BA33: =IF($B33="","",$M33+(1000-ROW())/100000) -> 55.00967 | BB33: BIB-032_Behroozi-etal_2012_FE-analysis-aircraft-tyre-model-complexity.pdf
A34: BIB-033 | B34: elfahham2023tire | C34: =IF($B34="","",IFERROR(LEFT(LEFT($V34,FIND(";",$V34&";")-1),FIND(",",LEFT($V34,FIND(";",$V34&";")-1))-1),LEFT($V34,FIND(";",$V34&";")-1))&IF((LEN($V34)-LEN(SUBSTITUTE($V34,";",""))+1)=1,"",IF((LEN($V34)-LEN(SUBSTITUTE($V34,";",""))+1)=2," & "&IFERROR(LEFT(TRIM(MID($V34,FIND(";",$V34)+1,FIND(";",$V34&";",FIND(";",$V34)+1)-FIND(";",$V34)-1)),FIND(",",TRIM(MID($V34,FIND(";",$V34)+1,FIND(";",$V34&";",FIND(";",$V34)+1)-FIND(";",$V34)-1)))-1),TRIM(MID($V34,FIND(";",$V34)+1,FIND(";",$V34&";",FIND(";",$V34)+1)-FIND(";",$V34)-1)))," et al."))&" ("&$W34&")") -> El Fahham et al. (2023) | D34: Analysis of vehicle tire strength test | E34: =IF(OR($B34="",$AF34=""),"",HYPERLINK(IF(AND(Paramètres!$C$13<>"",$AJ34="Éditeur (abonnement)"),Paramètres!$C$13&$AF34,$AF34),"Ouvrir : "&$AE34)) -> Ouvrir : Page éditeur (DOI) | F34: Oui | G34: 2 | H34: A consulter | I34: 2 | J34: À lire | K34: =IF($B34="","",IF($J34="Lu","Lu",IF($J34="Écarté","Écarté",IF($I34<Paramètres!$C$8,"EN RETARD",IF($I34=Paramètres!$C$8,"Ce mois-ci",IF($I34=Paramètres!$C$8+1,"Mois prochain","À venir")))))) -> Mois prochain | L34: =IF($B34="","",IF($AL34="Non vérifié","Ne pas citer en l'état : métadonnées non vérifiées",IF($AL34="Partiel","Vérification à compléter avant de citer",IF($O34="Oui","",IF(OR($AJ34="PDF libre",$AJ34="PDF libre (dépôt)"),"PDF libre à télécharger",IF($AJ34="Éditeur (abonnement)","À télécharger via l'accès ENTPE",IF($AJ34="Payant (boutique)","À consulter via l'abonnement de l'école",IF($AJ34="Non diffusé (à demander)","Document à demander (feuille Demandes)","Texte intégral à localiser")))))))) | M34: =IF($B34="","",IF(OR($J34="Lu",$J34="Écarté"),0,IFERROR(INDEX(Paramètres!$C$17:$C$19,MATCH($H34,Paramètres!$B$17:$B$19,0)),0)+Paramètres!$C$20*(7-$I34)+IF($I34<Paramètres!$C$8,Paramètres!$C$21,0)+IF($F34="Oui",Paramètres!$C$22,0)+IF($AL34<>"Vérifié",Paramètres!$C$23,0)+IF(AND($O34<>"Oui",OR($AJ34="PDF libre",$AJ34="PDF libre (dépôt)")),Paramètres!$C$24,0))) -> 65 | O34: =IF($BB34="","Non",HYPERLINK(DossierPDF&$BB34,"Oui")) -> Oui | P34: Non | Q34: Non | T34: JOUR | U34: =IF($B34="","",IFERROR(INDEX(Paramètres!$N$6:$N$13,MATCH($T34,Paramètres!$M$6:$M$13,0)),$T34)) -> Article de revue | V34: El Fahham, I. M.; Crosby, W. A.; Gaied, A. I. | W34: 2023 | X34: Journal of Terramechanics | Y34: 105 | AA34: 1-9 | AC34: 10.1016/j.jterra.2022.10.001 | AE34: Page éditeur (DOI) | AF34: https://doi.org/10.1016/j.jterra.2022.10.001 | AG34: =IF($AC34="","",HYPERLINK("https://doi.org/"&$AC34,"doi.org")) -> doi.org | AH34: =IF($AZ34="","",HYPERLINK($AZ34,"Scholar")) -> Scholar | AI34: Payant | AJ34: Éditeur (abonnement) | AK34: Elsevier : abonnement ENTPE. | AL34: Vérifié | AM34: OpenAlex (DOI) | AN34: 22/09/2026 | AO34: Analyse d'essais de résistance de pneus de véhicules. Lien avec ta thèse : cité uniquement pour la figure comparant carcasses radiale et diagonale ; pertinence secondaire. | AQ34: Non | AR34: =IF($B34="","",IFERROR(INDEX(Paramètres!$Q$6:$Q$13,MATCH($G34,Paramètres!$P$6:$P$13,0)),"")) -> Modélisation du pneu et du contact | AS34: =IF($B34="","",IFERROR(INDEX(Paramètres!$T$6:$T$11,MATCH($I34,Paramètres!$S$6:$S$11,0)),"")) -> novembre 2026 | AT34: =IF($B34="","",IFERROR(INDEX(Paramètres!$C$27:$C$29,MATCH($H34,Paramètres!$B$27:$B$29,0)),0)) -> 1 | AW34: =IF($B34="","",$B34&".md") -> elfahham2023tire.md | AX34: =IF($B34="","",COUNTIF($I$2:I34,$I34)) -> 15 | AY34: =IF($B34="","",$I34&"-"&$AX34) -> 2-15 | AZ34: https://scholar.google.com/scholar?q=%22Analysis+of+vehicle+tire+strength+test%22 | BA34: =IF($B34="","",$M34+(1000-ROW())/100000) -> 65.00966 | BB34: BIB-033_ElFahham-etal_2023_Vehicle-tire-strength-test.pdf
A35: BIB-034 | B35: ford1988truck | C35: =IF($B35="","",IFERROR(LEFT(LEFT($V35,FIND(";",$V35&";")-1),FIND(",",LEFT($V35,FIND(";",$V35&";")-1))-1),LEFT($V35,FIND(";",$V35&";")-1))&IF((LEN($V35)-LEN(SUBSTITUTE($V35,";",""))+1)=1,"",IF((LEN($V35)-LEN(SUBSTITUTE($V35,";",""))+1)=2," & "&IFERROR(LEFT(TRIM(MID($V35,FIND(";",$V35)+1,FIND(";",$V35&";",FIND(";",$V35)+1)-FIND(";",$V35)-1)),FIND(",",TRIM(MID($V35,FIND(";",$V35)+1,FIND(";",$V35&";",FIND(";",$V35)+1)-FIND(";",$V35)-1)))-1),TRIM(MID($V35,FIND(";",$V35)+1,FIND(";",$V35&";",FIND(";",$V35)+1)-FIND(";",$V35)-1)))," et al."))&" ("&$W35&")") -> Ford & Charles (1988) | D35: Heavy duty truck tire engineering | E35: =IF(OR($B35="",$AF35=""),"",HYPERLINK(IF(AND(Paramètres!$C$13<>"",$AJ35="Éditeur (abonnement)"),Paramètres!$C$13&$AF35,$AF35),"Ouvrir : "&$AE35)) -> Ouvrir : Page éditeur (DOI) | F35: Oui | G35: 2 | H35: A consulter | I35: 2 | J35: À lire | K35: =IF($B35="","",IF($J35="Lu","Lu",IF($J35="Écarté","Écarté",IF($I35<Paramètres!$C$8,"EN RETARD",IF($I35=Paramètres!$C$8,"Ce mois-ci",IF($I35=Paramètres!$C$8+1,"Mois prochain","À venir")))))) -> Mois prochain | L35: =IF($B35="","",IF($AL35="Non vérifié","Ne pas citer en l'état : métadonnées non vérifiées",IF($AL35="Partiel","Vérification à compléter avant de citer",IF($O35="Oui","",IF(OR($AJ35="PDF libre",$AJ35="PDF libre (dépôt)"),"PDF libre à télécharger",IF($AJ35="Éditeur (abonnement)","À télécharger via l'accès ENTPE",IF($AJ35="Payant (boutique)","À consulter via l'abonnement de l'école",IF($AJ35="Non diffusé (à demander)","Document à demander (feuille Demandes)","Texte intégral à localiser")))))))) -> À consulter via l'abonnement de l'école | M35: =IF($B35="","",IF(OR($J35="Lu",$J35="Écarté"),0,IFERROR(INDEX(Paramètres!$C$17:$C$19,MATCH($H35,Paramètres!$B$17:$B$19,0)),0)+Paramètres!$C$20*(7-$I35)+IF($I35<Paramètres!$C$8,Paramètres!$C$21,0)+IF($F35="Oui",Paramètres!$C$22,0)+IF($AL35<>"Vérifié",Paramètres!$C$23,0)+IF(AND($O35<>"Oui",OR($AJ35="PDF libre",$AJ35="PDF libre (dépôt)")),Paramètres!$C$24,0))) -> 65 | O35: =IF($BB35="","Non",HYPERLINK(DossierPDF&$BB35,"Oui")) -> Oui | P35: Non | Q35: Non | T35: CONF | U35: =IF($B35="","",IFERROR(INDEX(Paramètres!$N$6:$N$13,MATCH($T35,Paramètres!$M$6:$M$13,0)),$T35)) -> Communication (actes) | V35: Ford, T. L.; Charles, F. S. | W35: 1988 | X35: SAE Technical Paper Series (The Thirty-Fourth L. Ray Buckendale Lecture), SP-729 | AB35: SAE International | AC35: 10.4271/880001 | AD35: SAE Technical Paper 880001 ; 54 p. | AE35: Page éditeur (DOI) | AF35: https://doi.org/10.4271/880001 | AG35: =IF($AC35="","",HYPERLINK("https://doi.org/"&$AC35,"doi.org")) -> doi.org | AH35: =IF($AZ35="","",HYPERLINK($AZ35,"Scholar")) -> Scholar | AI35: Payant | AJ35: Payant (boutique) | AK35: Payant chez SAE ; demander à la documentation de l'ENTPE. | AL35: Vérifié | AM35: OpenAlex (DOI) + notice TRID | AN35: 22/09/2026 | AO35: Conférence de référence (Goodyear) sur l'ingénierie des pneus de camion : conception, charge, déflexion. Lien avec ta thèse : source de la déflexion nominale des pneus de camion (Fig. 1-24) qui justifie ta transposition vers le pneu d'avion. | AQ35: Oui | AR35: =IF($B35="","",IFERROR(INDEX(Paramètres!$Q$6:$Q$13,MATCH($G35,Paramètres!$P$6:$P$13,0)),"")) -> Modélisation du pneu et du contact | AS35: =IF($B35="","",IFERROR(INDEX(Paramètres!$T$6:$T$11,MATCH($I35,Paramètres!$S$6:$S$11,0)),"")) -> novembre 2026 | AT35: =IF($B35="","",IFERROR(INDEX(Paramètres!$C$27:$C$29,MATCH($H35,Paramètres!$B$27:$B$29,0)),0)) -> 1 | AW35: =IF($B35="","",$B35&".md") -> ford1988truck.md | AX35: =IF($B35="","",COUNTIF($I$2:I35,$I35)) -> 16 | AY35: =IF($B35="","",$I35&"-"&$AX35) -> 2-16 | AZ35: https://scholar.google.com/scholar?q=%22Heavy+duty+truck+tire+engineering%22 | BA35: =IF($B35="","",$M35+(1000-ROW())/100000) -> 65.00965 | BB35: BIB-034_Ford-Charles_1988_Heavy-duty-truck-tire-engineering.pdf
A36: BIB-035 | B36: gent2006pneumatic | C36: =IF($B36="","",IFERROR(LEFT(LEFT($V36,FIND(";",$V36&";")-1),FIND(",",LEFT($V36,FIND(";",$V36&";")-1))-1),LEFT($V36,FIND(";",$V36&";")-1))&IF((LEN($V36)-LEN(SUBSTITUTE($V36,";",""))+1)=1,"",IF((LEN($V36)-LEN(SUBSTITUTE($V36,";",""))+1)=2," & "&IFERROR(LEFT(TRIM(MID($V36,FIND(";",$V36)+1,FIND(";",$V36&";",FIND(";",$V36)+1)-FIND(";",$V36)-1)),FIND(",",TRIM(MID($V36,FIND(";",$V36)+1,FIND(";",$V36&";",FIND(";",$V36)+1)-FIND(";",$V36)-1)))-1),TRIM(MID($V36,FIND(";",$V36)+1,FIND(";",$V36&";",FIND(";",$V36)+1)-FIND(";",$V36)-1)))," et al."))&" ("&$W36&")") -> Gent & Walter (2006) | D36: The pneumatic tire | E36: =IF(OR($B36="",$AF36=""),"",HYPERLINK(IF(AND(Paramètres!$C$13<>"",$AJ36="Éditeur (abonnement)"),Paramètres!$C$13&$AF36,$AF36),"Ouvrir : "&$AE36)) -> Ouvrir : Texte intégral libre | F36: Non | G36: 2 | H36: A consulter | I36: 2 | J36: À lire | K36: =IF($B36="","",IF($J36="Lu","Lu",IF($J36="Écarté","Écarté",IF($I36<Paramètres!$C$8,"EN RETARD",IF($I36=Paramètres!$C$8,"Ce mois-ci",IF($I36=Paramètres!$C$8+1,"Mois prochain","À venir")))))) -> Mois prochain | L36: =IF($B36="","",IF($AL36="Non vérifié","Ne pas citer en l'état : métadonnées non vérifiées",IF($AL36="Partiel","Vérification à compléter avant de citer",IF($O36="Oui","",IF(OR($AJ36="PDF libre",$AJ36="PDF libre (dépôt)"),"PDF libre à télécharger",IF($AJ36="Éditeur (abonnement)","À télécharger via l'accès ENTPE",IF($AJ36="Payant (boutique)","À consulter via l'abonnement de l'école",IF($AJ36="Non diffusé (à demander)","Document à demander (feuille Demandes)","Texte intégral à localiser")))))))) | M36: =IF($B36="","",IF(OR($J36="Lu",$J36="Écarté"),0,IFERROR(INDEX(Paramètres!$C$17:$C$19,MATCH($H36,Paramètres!$B$17:$B$19,0)),0)+Paramètres!$C$20*(7-$I36)+IF($I36<Paramètres!$C$8,Paramètres!$C$21,0)+IF($F36="Oui",Paramètres!$C$22,0)+IF($AL36<>"Vérifié",Paramètres!$C$23,0)+IF(AND($O36<>"Oui",OR($AJ36="PDF libre",$AJ36="PDF libre (dépôt)")),Paramètres!$C$24,0))) -> 55 | O36: =IF($BB36="","Non",HYPERLINK(DossierPDF&$BB36,"Oui")) -> Oui | P36: Non | Q36: Non | T36: BOOK | U36: =IF($B36="","",IFERROR(INDEX(Paramètres!$N$6:$N$13,MATCH($T36,Paramètres!$M$6:$M$13,0)),$T36)) -> Ouvrage / guide | V36: Gent, A. N.; Walter, J. D. | W36: 2006 | AB36: National Highway Traffic Safety Administration | AD36: DOT HS 810 561 ; 707 p. (ouvrage collectif dirigé par Gent et Walter) | AE36: Texte intégral libre | AF36: https://www.fueleconomy.gov/feg/pdfs/PneumaticTire_HS-810-561.pdf | AG36: =IF($AC36="","",HYPERLINK("https://doi.org/"&$AC36,"doi.org")) | AH36: =IF($AZ36="","",HYPERLINK($AZ36,"Scholar")) -> Scholar | AI36: Libre | AJ36: PDF libre | AK36: PDF public diffusé par l'administration américaine. | AL36: Vérifié | AM36: Notice TRID 851939 | AN36: 22/09/2026 | AO36: Ouvrage de référence sur la mécanique des pneumatiques : structures radiale et diagonale, contact, empreinte. Lien avec ta thèse : bases de mécanique du pneu pour l'axe 2, en libre accès. | AQ36: Non | AR36: =IF($B36="","",IFERROR(INDEX(Paramètres!$Q$6:$Q$13,MATCH($G36,Paramètres!$P$6:$P$13,0)),"")) -> Modélisation du pneu et du contact | AS36: =IF($B36="","",IFERROR(INDEX(Paramètres!$T$6:$T$11,MATCH($I36,Paramètres!$S$6:$S$11,0)),"")) -> novembre 2026 | AT36: =IF($B36="","",IFERROR(INDEX(Paramètres!$C$27:$C$29,MATCH($H36,Paramètres!$B$27:$B$29,0)),0)) -> 1 | AW36: =IF($B36="","",$B36&".md") -> gent2006pneumatic.md | AX36: =IF($B36="","",COUNTIF($I$2:I36,$I36)) -> 17 | AY36: =IF($B36="","",$I36&"-"&$AX36) -> 2-17 | AZ36: https://scholar.google.com/scholar?q=%22The+pneumatic+tire%22 | BA36: =IF($B36="","",$M36+(1000-ROW())/100000) -> 55.00964 | BB36: BIB-035_Gent-Walter_2006_The-pneumatic-tire.pdf
A37: BIB-036 | B37: hernandez2016speed | C37: =IF($B37="","",IFERROR(LEFT(LEFT($V37,FIND(";",$V37&";")-1),FIND(",",LEFT($V37,FIND(";",$V37&";")-1))-1),LEFT($V37,FIND(";",$V37&";")-1))&IF((LEN($V37)-LEN(SUBSTITUTE($V37,";",""))+1)=1,"",IF((LEN($V37)-LEN(SUBSTITUTE($V37,";",""))+1)=2," & "&IFERROR(LEFT(TRIM(MID($V37,FIND(";",$V37)+1,FIND(";",$V37&";",FIND(";",$V37)+1)-FIND(";",$V37)-1)),FIND(",",TRIM(MID($V37,FIND(";",$V37)+1,FIND(";",$V37&";",FIND(";",$V37)+1)-FIND(";",$V37)-1)))-1),TRIM(MID($V37,FIND(";",$V37)+1,FIND(";",$V37&";",FIND(";",$V37)+1)-FIND(";",$V37)-1)))," et al."))&" ("&$W37&")") -> Hernandez & Al-Qadi (2016) | D37: Contact phenomenon of free-rolling wide-base tires: Effect of speed and temperature | E37: =IF(OR($B37="",$AF37=""),"",HYPERLINK(IF(AND(Paramètres!$C$13<>"",$AJ37="Éditeur (abonnement)"),Paramètres!$C$13&$AF37,$AF37),"Ouvrir : "&$AE37)) -> Ouvrir : Page éditeur (DOI) | F37: Non | G37: 2 | H37: A consulter | I37: 2 | J37: À lire | K37: =IF($B37="","",IF($J37="Lu","Lu",IF($J37="Écarté","Écarté",IF($I37<Paramètres!$C$8,"EN RETARD",IF($I37=Paramètres!$C$8,"Ce mois-ci",IF($I37=Paramètres!$C$8+1,"Mois prochain","À venir")))))) -> Mois prochain | L37: =IF($B37="","",IF($AL37="Non vérifié","Ne pas citer en l'état : métadonnées non vérifiées",IF($AL37="Partiel","Vérification à compléter avant de citer",IF($O37="Oui","",IF(OR($AJ37="PDF libre",$AJ37="PDF libre (dépôt)"),"PDF libre à télécharger",IF($AJ37="Éditeur (abonnement)","À télécharger via l'accès ENTPE",IF($AJ37="Payant (boutique)","À consulter via l'abonnement de l'école",IF($AJ37="Non diffusé (à demander)","Document à demander (feuille Demandes)","Texte intégral à localiser")))))))) -> À télécharger via l'accès ENTPE | M37: =IF($B37="","",IF(OR($J37="Lu",$J37="Écarté"),0,IFERROR(INDEX(Paramètres!$C$17:$C$19,MATCH($H37,Paramètres!$B$17:$B$19,0)),0)+Paramètres!$C$20*(7-$I37)+IF($I37<Paramètres!$C$8,Paramètres!$C$21,0)+IF($F37="Oui",Paramètres!$C$22,0)+IF($AL37<>"Vérifié",Paramètres!$C$23,0)+IF(AND($O37<>"Oui",OR($AJ37="PDF libre",$AJ37="PDF libre (dépôt)")),Paramètres!$C$24,0))) -> 55 | O37: =IF($BB37="","Non",HYPERLINK(DossierPDF&$BB37,"Oui")) -> Non | P37: Non | Q37: Non | T37: JOUR | U37: =IF($B37="","",IFERROR(INDEX(Paramètres!$N$6:$N$13,MATCH($T37,Paramètres!$M$6:$M$13,0)),$T37)) -> Article de revue | V37: Hernandez, J. A.; Al-Qadi, I. L. | W37: 2016 | X37: Journal of Transportation Engineering | Y37: 142 | Z37: 12 | AC37: 10.1061/(ASCE)TE.1943-5436.0000893 | AE37: Page éditeur (DOI) | AF37: https://doi.org/10.1061/(ASCE)TE.1943-5436.0000893 | AG37: =IF($AC37="","",HYPERLINK("https://doi.org/"&$AC37,"doi.org")) -> doi.org | AH37: =IF($AZ37="","",HYPERLINK($AZ37,"Scholar")) -> Scholar | AI37: Payant | AJ37: Éditeur (abonnement) | AK37: ASCE Library : abonnement ENTPE. | AL37: Vérifié | AM37: OpenAlex (DOI) ; numéro d'article non constaté | AN37: 22/09/2026 | AO37: Effet de la vitesse et de la température sur le contact de pneus larges en roulement libre, par éléments finis. Lien avec ta thèse : sensibilité de la distribution aux conditions de roulement, à garder en tête pour les gros porteurs. | AQ37: Non | AR37: =IF($B37="","",IFERROR(INDEX(Paramètres!$Q$6:$Q$13,MATCH($G37,Paramètres!$P$6:$P$13,0)),"")) -> Modélisation du pneu et du contact | AS37: =IF($B37="","",IFERROR(INDEX(Paramètres!$T$6:$T$11,MATCH($I37,Paramètres!$S$6:$S$11,0)),"")) -> novembre 2026 | AT37: =IF($B37="","",IFERROR(INDEX(Paramètres!$C$27:$C$29,MATCH($H37,Paramètres!$B$27:$B$29,0)),0)) -> 1 | AW37: =IF($B37="","",$B37&".md") -> hernandez2016speed.md | AX37: =IF($B37="","",COUNTIF($I$2:I37,$I37)) -> 18 | AY37: =IF($B37="","",$I37&"-"&$AX37) -> 2-18 | AZ37: https://scholar.google.com/scholar?q=%22Contact+phenomenon+of+free-rolling+wide-base+tires%3A+Effect+of+speed+and+temperature%22 | BA37: =IF($B37="","",$M37+(1000-ROW())/100000) -> 55.00963
A38: BIB-037 | B38: kongokonde2011these | C38: =IF($B38="","",IFERROR(LEFT(LEFT($V38,FIND(";",$V38&";")-1),FIND(",",LEFT($V38,FIND(";",$V38&";")-1))-1),LEFT($V38,FIND(";",$V38&";")-1))&IF((LEN($V38)-LEN(SUBSTITUTE($V38,";",""))+1)=1,"",IF((LEN($V38)-LEN(SUBSTITUTE($V38,";",""))+1)=2," & "&IFERROR(LEFT(TRIM(MID($V38,FIND(";",$V38)+1,FIND(";",$V38&";",FIND(";",$V38)+1)-FIND(";",$V38)-1)),FIND(",",TRIM(MID($V38,FIND(";",$V38)+1,FIND(";",$V38&";",FIND(";",$V38)+1)-FIND(";",$V38)-1)))-1),TRIM(MID($V38,FIND(";",$V38)+1,FIND(";",$V38&";",FIND(";",$V38)+1)-FIND(";",$V38)-1)))," et al."))&" ("&$W38&")") -> Kongo Kondé (2011) | D38: Modélisation du roulement d'un pneumatique d'avion | E38: =IF(OR($B38="",$AF38=""),"",HYPERLINK(IF(AND(Paramètres!$C$13<>"",$AJ38="Éditeur (abonnement)"),Paramètres!$C$13&$AF38,$AF38),"Ouvrir : "&$AE38)) -> Ouvrir : Page éditeur (DOI) | F38: Non | G38: 2 | H38: A consulter | I38: 2 | J38: À lire | K38: =IF($B38="","",IF($J38="Lu","Lu",IF($J38="Écarté","Écarté",IF($I38<Paramètres!$C$8,"EN RETARD",IF($I38=Paramètres!$C$8,"Ce mois-ci",IF($I38=Paramètres!$C$8+1,"Mois prochain","À venir")))))) -> Mois prochain | L38: =IF($B38="","",IF($AL38="Non vérifié","Ne pas citer en l'état : métadonnées non vérifiées",IF($AL38="Partiel","Vérification à compléter avant de citer",IF($O38="Oui","",IF(OR($AJ38="PDF libre",$AJ38="PDF libre (dépôt)"),"PDF libre à télécharger",IF($AJ38="Éditeur (abonnement)","À télécharger via l'accès ENTPE",IF($AJ38="Payant (boutique)","À consulter via l'abonnement de l'école",IF($AJ38="Non diffusé (à demander)","Document à demander (feuille Demandes)","Texte intégral à localiser")))))))) -> Texte intégral à localiser | M38: =IF($B38="","",IF(OR($J38="Lu",$J38="Écarté"),0,IFERROR(INDEX(Paramètres!$C$17:$C$19,MATCH($H38,Paramètres!$B$17:$B$19,0)),0)+Paramètres!$C$20*(7-$I38)+IF($I38<Paramètres!$C$8,Paramètres!$C$21,0)+IF($F38="Oui",Paramètres!$C$22,0)+IF($AL38<>"Vérifié",Paramètres!$C$23,0)+IF(AND($O38<>"Oui",OR($AJ38="PDF libre",$AJ38="PDF libre (dépôt)")),Paramètres!$C$24,0))) -> 55 | O38: =IF($BB38="","Non",HYPERLINK(DossierPDF&$BB38,"Oui")) -> Non | P38: Non | Q38: Non | T38: THES | U38: =IF($B38="","",IFERROR(INDEX(Paramètres!$N$6:$N$13,MATCH($T38,Paramètres!$M$6:$M$13,0)),$T38)) -> Thèse | V38: Kongo Kondé, A. | W38: 2011 | AB38: Aix-Marseille Université | AC38: 10.70675/8e64093dzdd25z4a64za9fczf6d298da3f8a | AD38: NNT 2011AIX10009 | AE38: Page éditeur (DOI) | AF38: https://doi.org/10.70675/8e64093dzdd25z4a64za9fczf6d298da3f8a | AG38: =IF($AC38="","",HYPERLINK("https://doi.org/"&$AC38,"doi.org")) -> doi.org | AH38: =IF($AZ38="","",HYPERLINK($AZ38,"Scholar")) -> Scholar | AI38: A verifier | AJ38: Notice en ligne (texte à localiser) | AK38: Notice theses.fr ; chercher le texte intégral sur HAL (thèses en ligne). | AL38: Vérifié | AM38: theses.fr (NNT) + Crossref (DOI theses.fr) | AN38: 22/09/2026 | AO38: Thèse sur la modélisation du roulement d'un pneu d'avion par éléments finis, en français. Lien avec ta thèse : détail méthodologique des travaux de Kongo Kondé et al. (2013). | AP38: Kongo Kondé et al. (2013) | AQ38: Oui | AR38: =IF($B38="","",IFERROR(INDEX(Paramètres!$Q$6:$Q$13,MATCH($G38,Paramètres!$P$6:$P$13,0)),"")) -> Modélisation du pneu et du contact | AS38: =IF($B38="","",IFERROR(INDEX(Paramètres!$T$6:$T$11,MATCH($I38,Paramètres!$S$6:$S$11,0)),"")) -> novembre 2026 | AT38: =IF($B38="","",IFERROR(INDEX(Paramètres!$C$27:$C$29,MATCH($H38,Paramètres!$B$27:$B$29,0)),0)) -> 1 | AW38: =IF($B38="","",$B38&".md") -> kongokonde2011these.md | AX38: =IF($B38="","",COUNTIF($I$2:I38,$I38)) -> 19 | AY38: =IF($B38="","",$I38&"-"&$AX38) -> 2-19 | AZ38: https://scholar.google.com/scholar?q=%22Mod%C3%A9lisation+du+roulement+d%27un+pneumatique+d%27avion%22 | BA38: =IF($B38="","",$M38+(1000-ROW())/100000) -> 55.00962
A39: BIB-038 | B39: liu2022ring | C39: =IF($B39="","",IFERROR(LEFT(LEFT($V39,FIND(";",$V39&";")-1),FIND(",",LEFT($V39,FIND(";",$V39&";")-1))-1),LEFT($V39,FIND(";",$V39&";")-1))&IF((LEN($V39)-LEN(SUBSTITUTE($V39,";",""))+1)=1,"",IF((LEN($V39)-LEN(SUBSTITUTE($V39,";",""))+1)=2," & "&IFERROR(LEFT(TRIM(MID($V39,FIND(";",$V39)+1,FIND(";",$V39&";",FIND(";",$V39)+1)-FIND(";",$V39)-1)),FIND(",",TRIM(MID($V39,FIND(";",$V39)+1,FIND(";",$V39&";",FIND(";",$V39)+1)-FIND(";",$V39)-1)))-1),TRIM(MID($V39,FIND(";",$V39)+1,FIND(";",$V39&";",FIND(";",$V39)+1)-FIND(";",$V39)-1)))," et al."))&" ("&$W39&")") -> Liu et al. (2022) | D39: In-plane flexible ring modeling and a nonlinear stiffness solution for heavy-load radial tires | E39: =IF(OR($B39="",$AF39=""),"",HYPERLINK(IF(AND(Paramètres!$C$13<>"",$AJ39="Éditeur (abonnement)"),Paramètres!$C$13&$AF39,$AF39),"Ouvrir : "&$AE39)) -> Ouvrir : Texte intégral libre | F39: Oui | G39: 2 | H39: A consulter | I39: 2 | J39: À lire | K39: =IF($B39="","",IF($J39="Lu","Lu",IF($J39="Écarté","Écarté",IF($I39<Paramètres!$C$8,"EN RETARD",IF($I39=Paramètres!$C$8,"Ce mois-ci",IF($I39=Paramètres!$C$8+1,"Mois prochain","À venir")))))) -> Mois prochain | L39: =IF($B39="","",IF($AL39="Non vérifié","Ne pas citer en l'état : métadonnées non vérifiées",IF($AL39="Partiel","Vérification à compléter avant de citer",IF($O39="Oui","",IF(OR($AJ39="PDF libre",$AJ39="PDF libre (dépôt)"),"PDF libre à télécharger",IF($AJ39="Éditeur (abonnement)","À télécharger via l'accès ENTPE",IF($AJ39="Payant (boutique)","À consulter via l'abonnement de l'école",IF($AJ39="Non diffusé (à demander)","Document à demander (feuille Demandes)","Texte intégral à localiser")))))))) | M39: =IF($B39="","",IF(OR($J39="Lu",$J39="Écarté"),0,IFERROR(INDEX(Paramètres!$C$17:$C$19,MATCH($H39,Paramètres!$B$17:$B$19,0)),0)+Paramètres!$C$20*(7-$I39)+IF($I39<Paramètres!$C$8,Paramètres!$C$21,0)+IF($F39="Oui",Paramètres!$C$22,0)+IF($AL39<>"Vérifié",Paramètres!$C$23,0)+IF(AND($O39<>"Oui",OR($AJ39="PDF libre",$AJ39="PDF libre (dépôt)")),Paramètres!$C$24,0))) -> 65 | O39: =IF($BB39="","Non",HYPERLINK(DossierPDF&$BB39,"Oui")) -> Oui | P39: Non | Q39: Non | T39: JOUR | U39: =IF($B39="","",IFERROR(INDEX(Paramètres!$N$6:$N$13,MATCH($T39,Paramètres!$M$6:$M$13,0)),$T39)) -> Article de revue | V39: Liu, Z.; Liu, Y.; Gao, Q. | W39: 2022 | X39: Mechanical Systems and Signal Processing | Y39: 171 | AA39: 108956 | AC39: 10.1016/j.ymssp.2022.108956 | AE39: Texte intégral libre | AF39: https://www.sciencedirect.com/science/article/pii/S0888327022001376/pdf | AG39: =IF($AC39="","",HYPERLINK("https://doi.org/"&$AC39,"doi.org")) -> doi.org | AH39: =IF($AZ39="","",HYPERLINK($AZ39,"Scholar")) -> Scholar | AI39: Libre | AJ39: PDF libre | AK39: Libre accès (article hybride) sur ScienceDirect. | AL39: Vérifié | AM39: OpenAlex (DOI) | AN39: 22/09/2026 | AO39: Modèle d'anneau flexible et solution de raideur non linéaire pour pneus radiaux fortement chargés. Lien avec ta thèse : piste pour relier déflexion du pneu et forme de la distribution. | AQ39: Non | AR39: =IF($B39="","",IFERROR(INDEX(Paramètres!$Q$6:$Q$13,MATCH($G39,Paramètres!$P$6:$P$13,0)),"")) -> Modélisation du pneu et du contact | AS39: =IF($B39="","",IFERROR(INDEX(Paramètres!$T$6:$T$11,MATCH($I39,Paramètres!$S$6:$S$11,0)),"")) -> novembre 2026 | AT39: =IF($B39="","",IFERROR(INDEX(Paramètres!$C$27:$C$29,MATCH($H39,Paramètres!$B$27:$B$29,0)),0)) -> 1 | AW39: =IF($B39="","",$B39&".md") -> liu2022ring.md | AX39: =IF($B39="","",COUNTIF($I$2:I39,$I39)) -> 20 | AY39: =IF($B39="","",$I39&"-"&$AX39) -> 2-20 | AZ39: https://scholar.google.com/scholar?q=%22In-plane+flexible+ring+modeling+and+a+nonlinear+stiffness+solution+for+heavy-load+radial+tires%22 | BA39: =IF($B39="","",$M39+(1000-ROW())/100000) -> 65.00961 | BB39: BIB-038_Liu-etal_2022_Flexible-ring-model-heavy-load-radial-tires.pdf
A40: BIB-039 | B40: liu2022deeplearning | C40: =IF($B40="","",IFERROR(LEFT(LEFT($V40,FIND(";",$V40&";")-1),FIND(",",LEFT($V40,FIND(";",$V40&";")-1))-1),LEFT($V40,FIND(";",$V40&";")-1))&IF((LEN($V40)-LEN(SUBSTITUTE($V40,";",""))+1)=1,"",IF((LEN($V40)-LEN(SUBSTITUTE($V40,";",""))+1)=2," & "&IFERROR(LEFT(TRIM(MID($V40,FIND(";",$V40)+1,FIND(";",$V40&";",FIND(";",$V40)+1)-FIND(";",$V40)-1)),FIND(",",TRIM(MID($V40,FIND(";",$V40)+1,FIND(";",$V40&";",FIND(";",$V40)+1)-FIND(";",$V40)-1)))-1),TRIM(MID($V40,FIND(";",$V40)+1,FIND(";",$V40&";",FIND(";",$V40)+1)-FIND(";",$V40)-1)))," et al."))&" ("&$W40&")") -> Liu & Al-Qadi (2022) | D40: Three-dimensional tire-pavement contact stresses prediction by deep learning approach | E40: =IF(OR($B40="",$AF40=""),"",HYPERLINK(IF(AND(Paramètres!$C$13<>"",$AJ40="Éditeur (abonnement)"),Paramètres!$C$13&$AF40,$AF40),"Ouvrir : "&$AE40)) -> Ouvrir : Page éditeur (DOI) | F40: Non | G40: 2 | H40: A consulter | I40: 2 | J40: À lire | K40: =IF($B40="","",IF($J40="Lu","Lu",IF($J40="Écarté","Écarté",IF($I40<Paramètres!$C$8,"EN RETARD",IF($I40=Paramètres!$C$8,"Ce mois-ci",IF($I40=Paramètres!$C$8+1,"Mois prochain","À venir")))))) -> Mois prochain | L40: =IF($B40="","",IF($AL40="Non vérifié","Ne pas citer en l'état : métadonnées non vérifiées",IF($AL40="Partiel","Vérification à compléter avant de citer",IF($O40="Oui","",IF(OR($AJ40="PDF libre",$AJ40="PDF libre (dépôt)"),"PDF libre à télécharger",IF($AJ40="Éditeur (abonnement)","À télécharger via l'accès ENTPE",IF($AJ40="Payant (boutique)","À consulter via l'abonnement de l'école",IF($AJ40="Non diffusé (à demander)","Document à demander (feuille Demandes)","Texte intégral à localiser")))))))) | M40: =IF($B40="","",IF(OR($J40="Lu",$J40="Écarté"),0,IFERROR(INDEX(Paramètres!$C$17:$C$19,MATCH($H40,Paramètres!$B$17:$B$19,0)),0)+Paramètres!$C$20*(7-$I40)+IF($I40<Paramètres!$C$8,Paramètres!$C$21,0)+IF($F40="Oui",Paramètres!$C$22,0)+IF($AL40<>"Vérifié",Paramètres!$C$23,0)+IF(AND($O40<>"Oui",OR($AJ40="PDF libre",$AJ40="PDF libre (dépôt)")),Paramètres!$C$24,0))) -> 55 | O40: =IF($BB40="","Non",HYPERLINK(DossierPDF&$BB40,"Oui")) -> Oui | P40: Non | Q40: Non | T40: JOUR | U40: =IF($B40="","",IFERROR(INDEX(Paramètres!$N$6:$N$13,MATCH($T40,Paramètres!$M$6:$M$13,0)),$T40)) -> Article de revue | V40: Liu, X.; Al-Qadi, I. L. | W40: 2022 | X40: International Journal of Pavement Engineering | Y40: 23 | Z40: 14 | AA40: 4991-5002 | AC40: 10.1080/10298436.2021.1990288 | AE40: Page éditeur (DOI) | AF40: https://doi.org/10.1080/10298436.2021.1990288 | AG40: =IF($AC40="","",HYPERLINK("https://doi.org/"&$AC40,"doi.org")) -> doi.org | AH40: =IF($AZ40="","",HYPERLINK($AZ40,"Scholar")) -> Scholar | AI40: Payant | AJ40: Éditeur (abonnement) | AK40: Taylor & Francis : abonnement ENTPE. | AL40: Vérifié | AM40: Crossref (mise en ligne le 19/10/2021, volume 23 de 2022) | AN40: 22/09/2026 | AO40: Prédiction des contraintes de contact tridimensionnelles par apprentissage profond entraîné sur un modèle éléments finis de pneu. Lien avec ta thèse : piste pour générer des empreintes pour des couples charge/gonflage non mesurés. | AQ40: Non | AR40: =IF($B40="","",IFERROR(INDEX(Paramètres!$Q$6:$Q$13,MATCH($G40,Paramètres!$P$6:$P$13,0)),"")) -> Modélisation du pneu et du contact | AS40: =IF($B40="","",IFERROR(INDEX(Paramètres!$T$6:$T$11,MATCH($I40,Paramètres!$S$6:$S$11,0)),"")) -> novembre 2026 | AT40: =IF($B40="","",IFERROR(INDEX(Paramètres!$C$27:$C$29,MATCH($H40,Paramètres!$B$27:$B$29,0)),0)) -> 1 | AW40: =IF($B40="","",$B40&".md") -> liu2022deeplearning.md | AX40: =IF($B40="","",COUNTIF($I$2:I40,$I40)) -> 21 | AY40: =IF($B40="","",$I40&"-"&$AX40) -> 2-21 | AZ40: https://scholar.google.com/scholar?q=%22Three-dimensional+tire-pavement+contact+stresses+prediction+by+deep+learning+approach%22 | BA40: =IF($B40="","",$M40+(1000-ROW())/100000) -> 55.0096 | BB40: BIB-039_Liu-AlQadi_2022_3D-contact-stresses-deep-learning.pdf
A41: BIB-040 | B41: rosu2018aircraft | C41: =IF($B41="","",IFERROR(LEFT(LEFT($V41,FIND(";",$V41&";")-1),FIND(",",LEFT($V41,FIND(";",$V41&";")-1))-1),LEFT($V41,FIND(";",$V41&";")-1))&IF((LEN($V41)-LEN(SUBSTITUTE($V41,";",""))+1)=1,"",IF((LEN($V41)-LEN(SUBSTITUTE($V41,";",""))+1)=2," & "&IFERROR(LEFT(TRIM(MID($V41,FIND(";",$V41)+1,FIND(";",$V41&";",FIND(";",$V41)+1)-FIND(";",$V41)-1)),FIND(",",TRIM(MID($V41,FIND(";",$V41)+1,FIND(";",$V41&";",FIND(";",$V41)+1)-FIND(";",$V41)-1)))-1),TRIM(MID($V41,FIND(";",$V41)+1,FIND(";",$V41&";",FIND(";",$V41)+1)-FIND(";",$V41)-1)))," et al."))&" ("&$W41&")") -> Rosu et al. (2018) | D41: Finite element modeling of an aircraft tire rolling on a steel drum: Experimental investigations and numerical simulations | E41: =IF(OR($B41="",$AF41=""),"",HYPERLINK(IF(AND(Paramètres!$C$13<>"",$AJ41="Éditeur (abonnement)"),Paramètres!$C$13&$AF41,$AF41),"Ouvrir : "&$AE41)) -> Ouvrir : Texte intégral libre | F41: Non | G41: 2 | H41: A consulter | I41: 2 | J41: À lire | K41: =IF($B41="","",IF($J41="Lu","Lu",IF($J41="Écarté","Écarté",IF($I41<Paramètres!$C$8,"EN RETARD",IF($I41=Paramètres!$C$8,"Ce mois-ci",IF($I41=Paramètres!$C$8+1,"Mois prochain","À venir")))))) -> Mois prochain | L41: =IF($B41="","",IF($AL41="Non vérifié","Ne pas citer en l'état : métadonnées non vérifiées",IF($AL41="Partiel","Vérification à compléter avant de citer",IF($O41="Oui","",IF(OR($AJ41="PDF libre",$AJ41="PDF libre (dépôt)"),"PDF libre à télécharger",IF($AJ41="Éditeur (abonnement)","À télécharger via l'accès ENTPE",IF($AJ41="Payant (boutique)","À consulter via l'abonnement de l'école",IF($AJ41="Non diffusé (à demander)","Document à demander (feuille Demandes)","Texte intégral à localiser")))))))) | M41: =IF($B41="","",IF(OR($J41="Lu",$J41="Écarté"),0,IFERROR(INDEX(Paramètres!$C$17:$C$19,MATCH($H41,Paramètres!$B$17:$B$19,0)),0)+Paramètres!$C$20*(7-$I41)+IF($I41<Paramètres!$C$8,Paramètres!$C$21,0)+IF($F41="Oui",Paramètres!$C$22,0)+IF($AL41<>"Vérifié",Paramètres!$C$23,0)+IF(AND($O41<>"Oui",OR($AJ41="PDF libre",$AJ41="PDF libre (dépôt)")),Paramètres!$C$24,0))) -> 55 | O41: =IF($BB41="","Non",HYPERLINK(DossierPDF&$BB41,"Oui")) -> Oui | P41: Non | Q41: Non | T41: JOUR | U41: =IF($B41="","",IFERROR(INDEX(Paramètres!$N$6:$N$13,MATCH($T41,Paramètres!$M$6:$M$13,0)),$T41)) -> Article de revue | V41: Rosu, I.; Elias-Birembaux, H.; Lebon, F. | W41: 2018 | X41: Applied Sciences | Y41: 8 | Z41: 4 | AA41: 593 | AC41: 10.3390/app8040593 | AE41: Texte intégral libre | AF41: https://www.mdpi.com/2076-3417/8/4/593/pdf?version=1525347784 | AG41: =IF($AC41="","",HYPERLINK("https://doi.org/"&$AC41,"doi.org")) -> doi.org | AH41: =IF($AZ41="","",HYPERLINK($AZ41,"Scholar")) -> Scholar | AI41: Libre | AJ41: PDF libre | AK41: Article en libre accès (MDPI). | AL41: Vérifié | AM41: OpenAlex (DOI) | AN41: 22/09/2026 | AO41: Modèle éléments finis d'un pneu d'avion roulant sur un tambour, confronté à des mesures. Lien avec ta thèse : validation expérimentale d'un modèle de pneu d'avion, en libre accès. | AP41: Kongo Kondé et al. (2013) | AQ41: Non | AR41: =IF($B41="","",IFERROR(INDEX(Paramètres!$Q$6:$Q$13,MATCH($G41,Paramètres!$P$6:$P$13,0)),"")) -> Modélisation du pneu et du contact | AS41: =IF($B41="","",IFERROR(INDEX(Paramètres!$T$6:$T$11,MATCH($I41,Paramètres!$S$6:$S$11,0)),"")) -> novembre 2026 | AT41: =IF($B41="","",IFERROR(INDEX(Paramètres!$C$27:$C$29,MATCH($H41,Paramètres!$B$27:$B$29,0)),0)) -> 1 | AW41: =IF($B41="","",$B41&".md") -> rosu2018aircraft.md | AX41: =IF($B41="","",COUNTIF($I$2:I41,$I41)) -> 22 | AY41: =IF($B41="","",$I41&"-"&$AX41) -> 2-22 | AZ41: https://scholar.google.com/scholar?q=%22Finite+element+modeling+of+an+aircraft+tire+rolling+on+a+steel+drum%3A+Experimental+investigations+and+numerical+simulations%22 | BA41: =IF($B41="","",$M41+(1000-ROW())/100000) -> 55.00959 | BB41: BIB-040_Rosu-etal_2018_FE-aircraft-tire-rolling-steel-drum.pdf
A42: BIB-041 | B42: tang2022radialtire | C42: =IF($B42="","",IFERROR(LEFT(LEFT($V42,FIND(";",$V42&";")-1),FIND(",",LEFT($V42,FIND(";",$V42&";")-1))-1),LEFT($V42,FIND(";",$V42&";")-1))&IF((LEN($V42)-LEN(SUBSTITUTE($V42,";",""))+1)=1,"",IF((LEN($V42)-LEN(SUBSTITUTE($V42,";",""))+1)=2," & "&IFERROR(LEFT(TRIM(MID($V42,FIND(";",$V42)+1,FIND(";",$V42&";",FIND(";",$V42)+1)-FIND(";",$V42)-1)),FIND(",",TRIM(MID($V42,FIND(";",$V42)+1,FIND(";",$V42&";",FIND(";",$V42)+1)-FIND(";",$V42)-1)))-1),TRIM(MID($V42,FIND(";",$V42)+1,FIND(";",$V42&";",FIND(";",$V42)+1)-FIND(";",$V42)-1)))," et al."))&" ("&$W42&")") -> Tang et al. (2022) | D42: Predictions of three-dimensional contact stresses of a radial truck tire under different driving modes | E42: =IF(OR($B42="",$AF42=""),"",HYPERLINK(IF(AND(Paramètres!$C$13<>"",$AJ42="Éditeur (abonnement)"),Paramètres!$C$13&$AF42,$AF42),"Ouvrir : "&$AE42)) -> Ouvrir : Texte intégral libre | F42: Non | G42: 2 | H42: A consulter | I42: 2 | J42: À lire | K42: =IF($B42="","",IF($J42="Lu","Lu",IF($J42="Écarté","Écarté",IF($I42<Paramètres!$C$8,"EN RETARD",IF($I42=Paramètres!$C$8,"Ce mois-ci",IF($I42=Paramètres!$C$8+1,"Mois prochain","À venir")))))) -> Mois prochain | L42: =IF($B42="","",IF($AL42="Non vérifié","Ne pas citer en l'état : métadonnées non vérifiées",IF($AL42="Partiel","Vérification à compléter avant de citer",IF($O42="Oui","",IF(OR($AJ42="PDF libre",$AJ42="PDF libre (dépôt)"),"PDF libre à télécharger",IF($AJ42="Éditeur (abonnement)","À télécharger via l'accès ENTPE",IF($AJ42="Payant (boutique)","À consulter via l'abonnement de l'école",IF($AJ42="Non diffusé (à demander)","Document à demander (feuille Demandes)","Texte intégral à localiser")))))))) | M42: =IF($B42="","",IF(OR($J42="Lu",$J42="Écarté"),0,IFERROR(INDEX(Paramètres!$C$17:$C$19,MATCH($H42,Paramètres!$B$17:$B$19,0)),0)+Paramètres!$C$20*(7-$I42)+IF($I42<Paramètres!$C$8,Paramètres!$C$21,0)+IF($F42="Oui",Paramètres!$C$22,0)+IF($AL42<>"Vérifié",Paramètres!$C$23,0)+IF(AND($O42<>"Oui",OR($AJ42="PDF libre",$AJ42="PDF libre (dépôt)")),Paramètres!$C$24,0))) -> 55 | O42: =IF($BB42="","Non",HYPERLINK(DossierPDF&$BB42,"Oui")) -> Oui | P42: Non | Q42: Non | T42: JOUR | U42: =IF($B42="","",IFERROR(INDEX(Paramètres!$N$6:$N$13,MATCH($T42,Paramètres!$M$6:$M$13,0)),$T42)) -> Article de revue | V42: Tang, X.; Xie, J.; Xie, H.; Zhang, H. | W42: 2022 | X42: Advances in Mechanical Engineering | Y42: 14 | Z42: 4 | AA42: 16878132221092346 | AC42: 10.1177/16878132221092346 | AE42: Texte intégral libre | AF42: https://doi.org/10.1177/16878132221092346 | AG42: =IF($AC42="","",HYPERLINK("https://doi.org/"&$AC42,"doi.org")) -> doi.org | AH42: =IF($AZ42="","",HYPERLINK($AZ42,"Scholar")) -> Scholar | AI42: Libre | AJ42: PDF libre | AK42: Article en libre accès (SAGE). | AL42: Vérifié | AM42: OpenAlex (DOI) | AN42: 22/09/2026 | AO42: Prédiction par éléments finis des trois composantes de contrainte de contact d'un pneu radial de camion selon le mode de conduite. Lien avec ta thèse : données 3D, dont tangentielles, pour ta perspective n° 2. | AQ42: Non | AR42: =IF($B42="","",IFERROR(INDEX(Paramètres!$Q$6:$Q$13,MATCH($G42,Paramètres!$P$6:$P$13,0)),"")) -> Modélisation du pneu et du contact | AS42: =IF($B42="","",IFERROR(INDEX(Paramètres!$T$6:$T$11,MATCH($I42,Paramètres!$S$6:$S$11,0)),"")) -> novembre 2026 | AT42: =IF($B42="","",IFERROR(INDEX(Paramètres!$C$27:$C$29,MATCH($H42,Paramètres!$B$27:$B$29,0)),0)) -> 1 | AW42: =IF($B42="","",$B42&".md") -> tang2022radialtire.md | AX42: =IF($B42="","",COUNTIF($I$2:I42,$I42)) -> 23 | AY42: =IF($B42="","",$I42&"-"&$AX42) -> 2-23 | AZ42: https://scholar.google.com/scholar?q=%22Predictions+of+three-dimensional+contact+stresses+of+a+radial+truck+tire+under+different+driving+modes%22 | BA42: =IF($B42="","",$M42+(1000-ROW())/100000) -> 55.00958 | BB42: BIB-041_Tang-etal_2022_3D-contact-stresses-radial-truck-tire.pdf
